Workbook

Sheet M&S
A1: CHANGE LIST | D1: Note lại ở cột này nha còn lại t lock hết r
A2: STT | B2: Current arguement | C2: Pending resolvement | D2: Suggested arguement | E2: Disapproved | F2: Why (Optional)
C3: =COUNTIF(C4:C253,"No") -> 3 | E3: =COUNTIF(E4:E253,"Denied") -> 0
A4: 1 | B4: Odd pricing - Standard: 6,790,000 ₫ - Advanced: 8,990,000 ₫ - E-bike: 17,990,000 ₫ | C4: YES | E4: FALSE
A5: 2 | B5: Giảm cho distributor 20% | C5: NO | E5: FALSE
A6: 3 | B6: 2 distributor chính - 200 chiếc/distri./month Các distributor, kênh bán hàng còn lại - 100 chiếc/month | C6: NO | E6: FALSE
A7: 4 | B7: Toàn bộ timeline plan marketing - Budget: chưa rõ - Projected sale: chưa có - Projected supply: chưa có | C7: NO | E7: FALSE
A8: 5 | C8: FALSE | E8: FALSE
A9: 6 | C9: FALSE | E9: FALSE
A10: 7 | C10: FALSE | E10: FALSE
A11: 8 | C11: FALSE | E11: FALSE
A12: 9 | C12: FALSE | E12: FALSE
A13: 10 | C13: FALSE | E13: FALSE
A14: 11 | C14: FALSE | E14: FALSE
A15: 12 | C15: FALSE | E15: FALSE
A16: 13 | C16: FALSE | E16: FALSE
A17: 14 | C17: FALSE | E17: FALSE
A18: 15 | C18: FALSE | E18: FALSE
A19: 16 | C19: FALSE | E19: FALSE
... A203: 200 | C203: FALSE | E203: FALSE

Sheet Parameter
A1: PARAMETER SHEET
A4: I/ Capital related
A6: WORKING CAPITAL
A7: Cash balance | B7: 0.1 | C7: Minimum | D7: Owner's investment
A8: Account receivable | B8: 0.5 | C8: On purchase | D8: Distributor
B9: 0.3 | C9: 1st period after purchase
B10: =1-B8-B9 -> 0.2 | C10: 2nd period after purchase
A11: Account payable | B11: 0.7 | C11: On purchase | D11: Inventory
B12: =1-B11 -> 0.3 | C12: 1st period after purchase
A13: Inventory | B13: 0.1 | C13: Minimum | D13: Production cap
B14: ='Operations plan'!C67 -> 0.12 | C14: Preproduce 1 month prior | D14: Store
B15: ='Operations plan'!C70 -> 0.12 | C15: Preproduce 1 month prior | D15: Distributors
A18: CAPITAL STRUCTURE
A19: Equity Funding | B19: Amount | C19: Corresponding percentage (%) | D19: Date received
A20: Owner Investment | B20: =SUM(B21:B24) -> 36000000000 | C20: 0.5
A21: Hoàng Anh Tú | B21: 7300000000 | C21: =B21/B$20 -> 0.20277778 | D21: 45657
A22: Nguyễn Phạm Gia Bảo | B22: 9400000000 | C22: =B22/B$20 -> 0.26111111 | D22: 45657
A23: Phạm Đình Khánh Băng | B23: 9700000000 | C23: =B23/B$20 -> 0.26944444 | D23: 45657
A24: Nguyễn Gia Khánh | B24: 9600000000 | C24: =B24/B$20 -> 0.26666667 | D24: 45657
A25: Bank loan | B25: =C25*$B$27 -> 1.44e+10 | C25: =1-(C20+C26) -> 0.2 | D25: 45780
A26: Angel investors | B26: =C26*$B$27 -> 21600000000 | C26: 0.3 | D26: 45700
A27: TOTAL | B27: =B20/C20 -> 72000000000
A30: REPAYMENT PLAN
A31: Loan | B31: =B25 -> 1.44e+10 | C31: Loan term | D31: 1 year
A32: Interest rate | B32: 0.0731 | C32: Repayment form | D32: Equal principle
A33: Renewal | B33: Annually | C33: Payment period | D33: Monthly
B34: 46022 | C34: 46387 | D34: 46752
A35: Loan balance | B35: =$B$31 -> 1.44e+10 | C35: =B39 -> 1.44e+10 | D35: =C39 -> 1.44e+10
A36: Repayments | B36: =SUM(B37:B38) -> #NAME? | C36: =SUM(C37:C38) -> #NAME? | D36: =SUM(D37:D38) -> #NAME?
A37: Paid interest | B37: {=SUM($B$31*(1-SEQUENCE(1,13,0)/12)*$B$32/12)} -> #NAME? | C37: {=SUM($B$31*(1-SEQUENCE(1,13,0)/12)*$B$32/12)} -> #NAME? | D37: {=SUM($B$31*(1-SEQUENCE(1,13,0)/12)*$B$32/12)} -> #NAME?
A38: Paid principal | B38: =B35/12*(DATEDIF(D25,DATEVALUE("12-31-2025"),"M")) -> #VALUE! | C38: =C35 -> 1.44e+10 | D38: =D35 -> 1.44e+10
A39: New loan | B39: =$B$31 -> 1.44e+10 | C39: =$B$31 -> 1.44e+10 | D39: =$B$31 -> 1.44e+10
A42: TAXATION
A43: Tax | B43: 0.2 | C43: Per year | D43: Positive year net income
A46: LONG-TERM ASSETS & DEPRECIATION
A47: Please refer to "Item list" and "Spending" spreadsheets for further information
A51: II/ Operation
A53: PRODUCTION & SALES
A54: Production capacity | B54: =ROUNDDOWN(('Operations plan'!C61+'Operations plan'!C58)/B55,-2) -> 2400 | C54: Products/month | D54: Maximum
A55: Estimated mobilized | B55: 0.8 | C55: In general | D55: Production capaitcy
A56: Base volume
A57: Standard | B57: ='Operations plan'!C7 -> 90 | C57: Product/month | D57: In-store
B58: ='Operations plan'!C17 -> 1200 | C58: Product/month | D58: Distributors
A59: E-bike | B59: ='Operations plan'!C8 -> 50 | C59: Product/month | D59: In-store
B60: ='Operations plan'!C18 -> 600 | C60: Product/month | D60: Distributors
A61: Base price
A62: Standard | B62: ='Operations plan'!C28 -> 6790000 | C62: VNĐ | D62: Respective discount
A63: Ebike | B63: ='Operations plan'!C29 -> 17990000 | C63: VNĐ | D63: Respective discount
A64: Material cost
A65: Standard | B65: 3350000 | C65: Per product
A66: E-bike | B66: 10800000 | C66: Per product
A69: INVENTORY & PREPRODUCE
A70: Base inventory | B70: 0.1 | C70: Products/month | D70: Production capacity
A71: Preproduce | B71: ='Operations plan'!C67 -> 0.12 | C71: Products/month | D71: Next period estimated sales
A74: PREMISES PAYMENT
A75: Factory | B75: 80000000 | C75: Per month | D75: 45658
A76: Office | B76: 50000000 | C76: Per month | D76: 45689
A77: Store | B77: 120000000 | C77: Per month | D77: 45809
A80: UTILITIES
A81: Factory | B81: 70000 | C81: Per month | D81: On product
A82: Office | B82: 3500000 | C82: Per month | D82: On total
A83: Store | B83: 7500000 | C83: Per month | D83: On total
A86: III/ Workforce resources
A88: Salary coverage
A89: Insurance | B89: 0.32 | C89: Per month | D89: Basic salery
A90: Basic salery | B90: 5200000 | C90: Per month | D90: Personel
A93: IV/ Ratios
A95: COMMON FINANCIAL RATIO
B96: 2025 | C96: 2026 | D96: 2027
A97: Gross profit margin | B97: ='INCOME STATEMENT'!J192/'INCOME STATEMENT'!J190 -> 0.15519188 | C97: ='INCOME STATEMENT'!K192/'INCOME STATEMENT'!K190 -> 0.23959217 | D97: ='INCOME STATEMENT'!L192/'INCOME STATEMENT'!L190 -> 0.28264621
A98: Current Ratio | B98: ='BALANCE SHEET'!V34/'BALANCE SHEET'!V46 -> 1.7986031 | C98: ='BALANCE SHEET'!W34/'BALANCE SHEET'!W46 -> 3.1922705 | D98: ='BALANCE SHEET'!X34/'BALANCE SHEET'!X46 -> 6.6218166
A99: Debt-to-Equity | B99: ='BALANCE SHEET'!V46/'BALANCE SHEET'!V50 -> 0.14175116 | C99: ='BALANCE SHEET'!W46/'BALANCE SHEET'!W50 -> 0.1482543 | D99: ='BALANCE SHEET'!X46/'BALANCE SHEET'!X50 -> 0.1088802
A100: Debt -to-Assets | B100: ='BALANCE SHEET'!V46/'BALANCE SHEET'!V43 -> 0.12415241 | C100: ='BALANCE SHEET'!W46/'BALANCE SHEET'!W43 -> 0.12911278 | D100: ='BALANCE SHEET'!X46/'BALANCE SHEET'!X43 -> 0.098189325
A101: Assets-to-Equity Ratio | B101: ='BALANCE SHEET'!V43/'BALANCE SHEET'!V50 -> 1.1417512 | C101: ='BALANCE SHEET'!W43/'BALANCE SHEET'!W50 -> 1.1482543 | D101: ='BALANCE SHEET'!X43/'BALANCE SHEET'!X50 -> 1.1088802
A104: BREAK-EVEN POINT
B105: 2025 | C105: 2026 | D105: 2027
A106: Profit on total product
A107: Standard | B107: {=SUM(('Operations plan'!E28:P28-B65-$B$81)*'Operations plan'!E7:P7+('Operations plan'!E38:P38-B65-$B$81)*'Operations plan'!E17:P17)} -> 25463130000 | C107: {=SUM(('Operations plan'!R28:AC28-B65-$B$81)*'Operations plan'!R7:AC7+('Operations plan'!R38:AC38-B65-$B$81)*'Operations plan'!R17:AC17)} -> 47657520000 | D107: {=SUM(('Operations plan'!AE28:AP28-B65-$B$81)*'Operations plan'!AE7:AP7+('Operations plan'!AE38:AP38-B65-$B$81)*'Operations plan'!AE17:AP17)} -> 50998530000
A108: E-bike | B108: {=SUM(('Operations plan'!E29:P29-B66-$B$81)*'Operations plan'!E8:P8+('Operations plan'!E39:P39-B66-$B$81)*'Operations plan'!E18:P18)} -> 0 | C108: {=SUM(('Operations plan'!R29:AC29-B66-$B$81)*'Operations plan'!R8:AC8+('Operations plan'!R39:AC39-B66-$B$81)*'Operations plan'!R18:AC18)} -> 3192600000 | D108: {=SUM(('Operations plan'!AE29:AP29-B66-$B$81)*'Operations plan'!AE8:AP8+('Operations plan'!AE39:AP39-B66-$B$81)*'Operations plan'!AE18:AP18)} -> 26724010000
A109: Number of sales
A110: Standard | B110: =SUM('Operations plan'!E59:P59,'Operations plan'!E62:P62) -> 9345 | C110: =SUM('Operations plan'!R59:AC59,'Operations plan'!R62:AC62) -> 17442 | D110: =SUM('Operations plan'!AE59:AP59,'Operations plan'!AE62:AP62) -> 18651
A111: E-bike | B111: =SUM('Operations plan'!E60:P60,'Operations plan'!E63:P63) -> 0 | C111: =SUM('Operations plan'!R60:AC60,'Operations plan'!R63:AC63) -> 600 | D111: =SUM('Operations plan'!AE60:AP60,'Operations plan'!AE63:AP63) -> 4807
A112: Average profit per sale
A113: Standard | B113: =B107/B110 -> 2724786.5 | C113: =C107/C110 -> 2732342.6 | D113: =D107/D110 -> 2734359
A114: E-bike | C114: =C108/C111 -> 5321000 | D114: =D108/D111 -> 5559394.6
A115: Sales contribution
A116: Standard | B116: =B110/(B110+B111) -> 1 | C116: =C110/(C110+C111) -> 0.96674426 | D116: =D110/(D110+D111) -> 0.79508057
A117: E-bike | B117: =B111/(B111+B110) -> 0 | C117: =C111/(C111+C110) -> 0.033255737 | D117: =D111/(D111+D110) -> 0.20491943
A118: Blended profit per sale-WACM | B118: =SUMPRODUCT(B116:B117,B113:B114) -> 2724786.5 | C118: =SUMPRODUCT(C116:C117,C113:C114) -> 2818430.3 | D118: =SUMPRODUCT(D116:D117,D113:D114) -> 3313263.7
A119: Fixed cost | B119: =Expenses!E76-Expenses!E74 -> 2.0033096e+10 | C119: =Expenses!F76-Expenses!F74 -> 31164023500 | D119: =Expenses!G76-Expenses!G74 -> 38711096300
A120: Break-even at (monthly): | B120: =B119/B118/6 -> 1225.3618 | C120: =C119/C118/12 -> 921.43557 | D120: =D119/D118/12 -> 973.63958
A121: Break-even (yearly): | B121: =B119/B118 -> 7352.1707 | C121: =C119/C118 -> 11057.227 | D121: =D119/D118 -> 11683.675

Sheet Delayed payment
A1: AR plan | G1: 2025 | T1: 2026 | AG1: 2027
G2: Q1 | J2: Q2 | M2: Q3 | P2: Q4 | T2: Q1 | W2: Q2 | Z2: Q3 | AC2: Q4 | AG2: Q1 | AJ2: Q2 | AM2: Q3 | AP2: Q4
G3: 1 | H3: 2 | I3: 3 | J3: 4 | K3: 5 | L3: 6 | M3: 7 | N3: 8 | O3: 9 | P3: 10 | Q3: 11 | R3: 12 | T3: 1 | U3: 2 | V3: 3 | W3: 4 | X3: 5 | Y3: 6 | Z3: 7 | AA3: 8 | AB3: 9 | AC3: 10 | AD3: 11 | AE3: 12 | AG3: 1 | AH3: 2 | AI3: 3 | AJ3: 4 | AK3: 5 | AL3: 6 | AM3: 7 | AN3: 8 | AO3: 9 | AP3: 10 | AQ3: 11 | AR3: 12
A4: Distributor vol. | C4: ='Operations plan'!C16 -> 1800 | D4: ='Operations plan'!D16 -> 0 | G4: ='Operations plan'!E16 -> 0 | H4: ='Operations plan'!F16 -> 0 | I4: ='Operations plan'!G16 -> 0 | J4: ='Operations plan'!H16 -> 0 | K4: ='Operations plan'!I16 -> 0 | L4: ='Operations plan'!J16 -> 1200 | M4: ='Operations plan'!K16 -> 1200 | N4: ='Operations plan'!L16 -> 1260 | ... R4: ='Operations plan'!P16 -> 1320 | T4: ='Operations plan'!R16 -> 1140 | U4: ='Operations plan'!S16 -> 1140 | V4: ='Operations plan'!T16 -> 1140 | W4: ='Operations plan'!U16 -> 1380 | X4: ='Operations plan'!V16 -> 1380 | Y4: ='Operations plan'!W16 -> 1380 | Z4: ='Operations plan'!X16 -> 1440 | AA4: ='Operations plan'!Y16 -> 1440 | ... AE4: ='Operations plan'!AC16 -> 1800 | AG4: ='Operations plan'!AE16 -> 1530 | AH4: ='Operations plan'!AF16 -> 1530 | AI4: ='Operations plan'!AG16 -> 1530 | AJ4: ='Operations plan'!AH16 -> 1800 | AK4: ='Operations plan'!AI16 -> 1800 | AL4: ='Operations plan'!AJ16 -> 1800 | AM4: ='Operations plan'!AK16 -> 1890 | AN4: ='Operations plan'!AL16 -> 1890 | ... AR4: ='Operations plan'!AP16 -> 1980
B5: Standard | C5: ='Operations plan'!C17 -> 1200 | D5: ='Operations plan'!D17 -> 1200 | G5: ='Operations plan'!E17 -> 0 | H5: ='Operations plan'!F17 -> 0 | I5: ='Operations plan'!G17 -> 0 | J5: ='Operations plan'!H17 -> 0 | K5: ='Operations plan'!I17 -> 0 | L5: ='Operations plan'!J17 -> 1200 | M5: ='Operations plan'!K17 -> 1200 | N5: ='Operations plan'!L17 -> 1260 | ... R5: ='Operations plan'!P17 -> 1320 | T5: ='Operations plan'!R17 -> 1140 | U5: ='Operations plan'!S17 -> 1140 | V5: ='Operations plan'!T17 -> 1140 | W5: ='Operations plan'!U17 -> 1380 | X5: ='Operations plan'!V17 -> 1380 | Y5: ='Operations plan'!W17 -> 1380 | Z5: ='Operations plan'!X17 -> 1440 | AA5: ='Operations plan'!Y17 -> 1440 | ... AE5: ='Operations plan'!AC17 -> 1500 | AG5: ='Operations plan'!AE17 -> 1320 | AH5: ='Operations plan'!AF17 -> 1320 | AI5: ='Operations plan'!AG17 -> 1320 | AJ5: ='Operations plan'!AH17 -> 1440 | AK5: ='Operations plan'!AI17 -> 1440 | AL5: ='Operations plan'!AJ17 -> 1440 | AM5: ='Operations plan'!AK17 -> 1500 | AN5: ='Operations plan'!AL17 -> 1500 | ... AR5: ='Operations plan'!AP17 -> 1560
B6: E-bike | C6: ='Operations plan'!C18 -> 600 | D6: ='Operations plan'!D18 -> 600 | G6: ='Operations plan'!E18 -> 0 | H6: ='Operations plan'!F18 -> 0 | I6: ='Operations plan'!G18 -> 0 | J6: ='Operations plan'!H18 -> 0 | K6: ='Operations plan'!I18 -> 0 | L6: ='Operations plan'!J18 -> 0 | M6: ='Operations plan'!K18 -> 0 | N6: ='Operations plan'!L18 -> 0 | ... R6: ='Operations plan'!P18 -> 0 | T6: ='Operations plan'!R18 -> 0 | U6: ='Operations plan'!S18 -> 0 | V6: ='Operations plan'!T18 -> 0 | W6: ='Operations plan'!U18 -> 0 | X6: ='Operations plan'!V18 -> 0 | Y6: ='Operations plan'!W18 -> 0 | Z6: ='Operations plan'!X18 -> 0 | AA6: ='Operations plan'!Y18 -> 0 | ... AE6: ='Operations plan'!AC18 -> 300 | AG6: ='Operations plan'!AE18 -> 210 | AH6: ='Operations plan'!AF18 -> 210 | AI6: ='Operations plan'!AG18 -> 210 | AJ6: ='Operations plan'!AH18 -> 360 | AK6: ='Operations plan'!AI18 -> 360 | AL6: ='Operations plan'!AJ18 -> 360 | AM6: ='Operations plan'!AK18 -> 390 | AN6: ='Operations plan'!AL18 -> 390 | ... AR6: ='Operations plan'!AP18 -> 420
A7: Dis. price | C7: ='Operations plan'!C37 -> Base \ Sale | D7: ='Operations plan'!D37 -> 18942000000 | G7: ='Operations plan'!E37 -> 0 | H7: ='Operations plan'!F37 -> 0 | I7: ='Operations plan'!G37 -> 0 | J7: ='Operations plan'!H37 -> 0 | K7: ='Operations plan'!I37 -> 0 | L7: ='Operations plan'!J37 -> 7333200000 | M7: ='Operations plan'!K37 -> 7333200000 | N7: ='Operations plan'!L37 -> 7699860000 | ... R7: ='Operations plan'!P37 -> 8066520000 | T7: ='Operations plan'!R37 -> 6966540000 | U7: ='Operations plan'!S37 -> 6966540000 | V7: ='Operations plan'!T37 -> 6966540000 | W7: ='Operations plan'!U37 -> 8433180000 | X7: ='Operations plan'!V37 -> 8433180000 | Y7: ='Operations plan'!W37 -> 8433180000 | Z7: ='Operations plan'!X37 -> 8799840000 | AA7: ='Operations plan'!Y37 -> 8799840000 | ... AE7: ='Operations plan'!AC37 -> 14023800000 | AG7: ='Operations plan'!AE37 -> 11466630000 | AH7: ='Operations plan'!AF37 -> 11466630000 | AI7: ='Operations plan'!AG37 -> 11466630000 | AJ7: ='Operations plan'!AH37 -> 14628600000 | AK7: ='Operations plan'!AI37 -> 14628600000 | AL7: ='Operations plan'!AJ37 -> 14628600000 | AM7: ='Operations plan'!AK37 -> 15480990000 | AN7: ='Operations plan'!AL37 -> 15480990000 | ... AR7: ='Operations plan'!AP37 -> 16333380000
B8: Standard | C8: ='Operations plan'!C38 -> 6790000 | D8: ='Operations plan'!D38 -> 6790000 | G8: ='Operations plan'!E38 -> 6111000 | H8: ='Operations plan'!F38 -> 6111000 | I8: ='Operations plan'!G38 -> 6111000 | J8: ='Operations plan'!H38 -> 6111000 | K8: ='Operations plan'!I38 -> 6111000 | L8: ='Operations plan'!J38 -> 6111000 | M8: ='Operations plan'!K38 -> 6111000 | N8: ='Operations plan'!L38 -> 6111000 | ... R8: ='Operations plan'!P38 -> 6111000 | T8: ='Operations plan'!R38 -> 6111000 | U8: ='Operations plan'!S38 -> 6111000 | V8: ='Operations plan'!T38 -> 6111000 | W8: ='Operations plan'!U38 -> 6111000 | X8: ='Operations plan'!V38 -> 6111000 | Y8: ='Operations plan'!W38 -> 6111000 | Z8: ='Operations plan'!X38 -> 6111000 | AA8: ='Operations plan'!Y38 -> 6111000 | ... AE8: ='Operations plan'!AC38 -> 6111000 | AG8: ='Operations plan'!AE38 -> 6111000 | AH8: ='Operations plan'!AF38 -> 6111000 | AI8: ='Operations plan'!AG38 -> 6111000 | AJ8: ='Operations plan'!AH38 -> 6111000 | AK8: ='Operations plan'!AI38 -> 6111000 | AL8: ='Operations plan'!AJ38 -> 6111000 | AM8: ='Operations plan'!AK38 -> 6111000 | AN8: ='Operations plan'!AL38 -> 6111000 | ... AR8: ='Operations plan'!AP38 -> 6111000
B9: E-bike | C9: ='Operations plan'!C39 -> 17990000 | D9: ='Operations plan'!D39 -> 17990000 | G9: ='Operations plan'!E39 -> 16191000 | H9: ='Operations plan'!F39 -> 16191000 | I9: ='Operations plan'!G39 -> 16191000 | J9: ='Operations plan'!H39 -> 16191000 | K9: ='Operations plan'!I39 -> 16191000 | L9: ='Operations plan'!J39 -> 16191000 | M9: ='Operations plan'!K39 -> 16191000 | N9: ='Operations plan'!L39 -> 16191000 | ... R9: ='Operations plan'!P39 -> 16191000 | T9: ='Operations plan'!R39 -> 16191000 | U9: ='Operations plan'!S39 -> 16191000 | V9: ='Operations plan'!T39 -> 16191000 | W9: ='Operations plan'!U39 -> 16191000 | X9: ='Operations plan'!V39 -> 16191000 | Y9: ='Operations plan'!W39 -> 16191000 | Z9: ='Operations plan'!X39 -> 16191000 | AA9: ='Operations plan'!Y39 -> 16191000 | ... AE9: ='Operations plan'!AC39 -> 16191000 | AG9: ='Operations plan'!AE39 -> 16191000 | AH9: ='Operations plan'!AF39 -> 16191000 | AI9: ='Operations plan'!AG39 -> 16191000 | AJ9: ='Operations plan'!AH39 -> 16191000 | AK9: ='Operations plan'!AI39 -> 16191000 | AL9: ='Operations plan'!AJ39 -> 16191000 | AM9: ='Operations plan'!AK39 -> 16191000 | AN9: ='Operations plan'!AL39 -> 16191000 | ... AR9: ='Operations plan'!AP39 -> 16191000
A11: Trả | B11: Trả ngay | C11: =Parameter!B8 -> 0.5 | G11: =$C11*G$7 -> 0 | H11: =$C11*H7 -> 0 | I11: =$C11*I7 -> 0 | J11: =$C11*J7 -> 0 | K11: =$C11*K7 -> 0 | L11: =$C11*L7 -> 3666600000 | M11: =$C11*M7 -> 3666600000 | N11: =$C11*N7 -> 3849930000 | O11: =$C11*O7 -> 3849930000 | ... R11: =$C11*R7 -> 4033260000 | T11: =$C11*T7 -> 3483270000 | U11: =$C11*U7 -> 3483270000 | V11: =$C11*V7 -> 3483270000 | W11: =$C11*W7 -> 4216590000 | X11: =$C11*X7 -> 4216590000 | Y11: =$C11*Y7 -> 4216590000 | Z11: =$C11*Z7 -> 4399920000 | AA11: =$C11*AA7 -> 4399920000 | ... AE11: =$C11*AE7 -> 7011900000 | AG11: =$C11*AG7 -> 5733315000 | AH11: =$C11*AH7 -> 5733315000 | AI11: =$C11*AI7 -> 5733315000 | AJ11: =$C11*AJ7 -> 7314300000 | AK11: =$C11*AK7 -> 7314300000 | AL11: =$C11*AL7 -> 7314300000 | AM11: =$C11*AM7 -> 7740495000 | AN11: =$C11*AN7 -> 7740495000 | ... AR11: =$C11*AR7 -> 8166690000
B12: Trả 1 kì trước
B13: Trả 2 kì trước | C13: =Parameter!B10 -> 0.2 | G13: =$C13*G9 -> 3238200 | H13: =$C13*H9 -> 3238200 | I13: =$C13*I9 -> 3238200 | J13: =$C13*J9 -> 3238200 | K13: =$C13*K9 -> 3238200 | L13: =$C13*L9 -> 3238200 | M13: =$C13*M9 -> 3238200 | N13: =$C13*N9 -> 3238200 | ... R13: =$C13*R9 -> 3238200 | T13: =$C13*T9 -> 3238200 | U13: =$C13*U9 -> 3238200 | V13: =$C13*V9 -> 3238200 | W13: =$C13*W9 -> 3238200 | X13: =$C13*X9 -> 3238200 | Y13: =$C13*Y9 -> 3238200 | Z13: =$C13*Z9 -> 3238200 | AA13: =$C13*AA9 -> 3238200 | ... AE13: =$C13*AE9 -> 3238200 | AG13: =$C13*AG9 -> 3238200 | AH13: =$C13*AH9 -> 3238200 | AI13: =$C13*AI9 -> 3238200 | AJ13: =$C13*AJ9 -> 3238200 | AK13: =$C13*AK9 -> 3238200 | AL13: =$C13*AL9 -> 3238200 | AM13: =$C13*AM9 -> 3238200 | AN13: =$C13*AN9 -> 3238200 | ... AR13: =$C13*AR9 -> 3238200
B17: Nợ 1 kì trước | C17: =Parameter!B9 -> 0.3 | G17: =IF( ISBLANK(#REF!), IF( ISBLANK(D$3), 0, D$7 *$C17 ),#REF! * $C17 ) -> #REF! | H17: =IF( ISBLANK(G$3), IF( ISBLANK(#REF!), 0,#REF! * $C17 ), G$7 * $C17 ) -> 0 | I17: =IF( ISBLANK(H$3), IF( ISBLANK(G$3), 0, G$7 *$C17 ), H$7 * $C17 ) -> 0 | J17: =IF( ISBLANK(I$3), IF( ISBLANK(H$3), 0, H$7 *$C17 ), I$7 * $C17 ) -> 0 | K17: =IF( ISBLANK(J$3), IF( ISBLANK(I$3), 0, I$7 *$C17 ), J$7 * $C17 ) -> 0 | L17: =IF( ISBLANK(K$3), IF( ISBLANK(J$3), 0, J$7 *$C17 ), K$7 * $C17 ) -> 0 | M17: =IF( ISBLANK(L$3), IF( ISBLANK(K$3), 0, K$7 *$C17 ), L$7 * $C17 ) -> 2199960000 | N17: =IF( ISBLANK(M$3), IF( ISBLANK(L$3), 0, L$7 *$C17 ), M$7 * $C17 ) -> 2199960000 | O17: =IF( ISBLANK(N$3), IF( ISBLANK(M$3), 0, M$7 *$C17 ), N$7 * $C17 ) -> 2309958000 | P17: =IF( ISBLANK(O$3), IF( ISBLANK(N$3), 0, N$7 *$C17 ), O$7 * $C17 ) -> 2309958000 | ... R17: =IF( ISBLANK(Q$3), IF( ISBLANK(P$3), 0, P$7 *$C17 ), Q$7 * $C17 ) -> 2419956000 | T17: =IF( ISBLANK(#REF!), IF( ISBLANK(R$3), 0, R$7 *$C17 ),#REF! * $C17 ) -> #REF! | U17: =IF( ISBLANK(T$3), IF( ISBLANK(#REF!), 0,#REF! * $C17 ), T$7 * $C17 ) -> 2089962000 | V17: =IF( ISBLANK(U$3), IF( ISBLANK(T$3), 0, T$7 *$C17 ), U$7 * $C17 ) -> 2089962000 | W17: =IF( ISBLANK(V$3), IF( ISBLANK(U$3), 0, U$7 *$C17 ), V$7 * $C17 ) -> 2089962000 | X17: =IF( ISBLANK(W$3), IF( ISBLANK(V$3), 0, V$7 *$C17 ), W$7 * $C17 ) -> 2529954000 | Y17: =IF( ISBLANK(X$3), IF( ISBLANK(W$3), 0, W$7 *$C17 ), X$7 * $C17 ) -> 2529954000 | Z17: =IF( ISBLANK(Y$3), IF( ISBLANK(X$3), 0, X$7 *$C17 ), Y$7 * $C17 ) -> 2529954000 | AA17: =IF( ISBLANK(Z$3), IF( ISBLANK(Y$3), 0, Y$7 *$C17 ), Z$7 * $C17 ) -> 2639952000 | AB17: =IF( ISBLANK(AA$3), IF( ISBLANK(Z$3), 0, Z$7 *$C17 ), AA$7 * $C17 ) -> 2639952000 | AC17: =IF( ISBLANK(AB$3), IF( ISBLANK(AA$3), 0, AA$7 *$C17 ), AB$7 * $C17 ) -> 2639952000 | ... AE17: =IF( ISBLANK(AD$3), IF( ISBLANK(AC$3), 0, AC$7 *$C17 ), AD$7 * $C17 ) -> 4207140000 | AG17: =IF( ISBLANK(#REF!), IF( ISBLANK(AE$3), 0, AE$7 *$C17 ),#REF! * $C17 ) -> #REF! | AH17: =IF( ISBLANK(AG$3), IF( ISBLANK(#REF!), 0,#REF! * $C17 ), AG$7 * $C17 ) -> 3439989000 | AI17: =IF( ISBLANK(AH$3), IF( ISBLANK(AG$3), 0, AG$7 *$C17 ), AH$7 * $C17 ) -> 3439989000 | AJ17: =IF( ISBLANK(AI$3), IF( ISBLANK(AH$3), 0, AH$7 *$C17 ), AI$7 * $C17 ) -> 3439989000 | AK17: =IF( ISBLANK(AJ$3), IF( ISBLANK(AI$3), 0, AI$7 *$C17 ), AJ$7 * $C17 ) -> 4388580000 | AL17: =IF( ISBLANK(AK$3), IF( ISBLANK(AJ$3), 0, AJ$7 *$C17 ), AK$7 * $C17 ) -> 4388580000 | AM17: =IF( ISBLANK(AL$3), IF( ISBLANK(AK$3), 0, AK$7 *$C17 ), AL$7 * $C17 ) -> 4388580000 | AN17: =IF( ISBLANK(AM$3), IF( ISBLANK(AL$3), 0, AL$7 *$C17 ), AM$7 * $C17 ) -> 4644297000 | AO17: =IF( ISBLANK(AN$3), IF( ISBLANK(AM$3), 0, AM$7 *$C17 ), AN$7 * $C17 ) -> 4644297000 | AP17: =IF( ISBLANK(AO$3), IF( ISBLANK(AN$3), 0, AN$7 *$C17 ), AO$7 * $C17 ) -> 4790016000 | ... AR17: =IF( ISBLANK(AQ$3), IF( ISBLANK(AP$3), 0, AP$7 *$C17 ), AQ$7 * $C17 ) -> 4900014000
B18: Nợ 2 kì trước | G18: =IF( ISBLANK(#REF!), IF( ISBLANK(D$3), 0, D$7 *$C18 ),#REF! * $C18 ) -> #REF! | H18: =IF( ISBLANK(G$3), IF( ISBLANK(#REF!), 0,#REF! * $C18 ), G$7 * $C18 ) -> 0 | I18: =IF( ISBLANK(H$3), IF( ISBLANK(G$3), 0, G$7 *$C18 ), H$7 * $C18 ) -> 0 | J18: =IF( ISBLANK(I$3), IF( ISBLANK(H$3), 0, H$7 *$C18 ), I$7 * $C18 ) -> 0 | K18: =IF( ISBLANK(J$3), IF( ISBLANK(I$3), 0, I$7 *$C18 ), J$7 * $C18 ) -> 0 | L18: =IF( ISBLANK(K$3), IF( ISBLANK(J$3), 0, J$7 *$C18 ), K$7 * $C18 ) -> 0 | M18: =IF( ISBLANK(L$3), IF( ISBLANK(K$3), 0, K$7 *$C18 ), L$7 * $C18 ) -> 0 | N18: =IF( ISBLANK(M$3), IF( ISBLANK(L$3), 0, L$7 *$C18 ), M$7 * $C18 ) -> 0 | O18: =IF( ISBLANK(N$3), IF( ISBLANK(M$3), 0, M$7 *$C18 ), N$7 * $C18 ) -> 0 | P18: =IF( ISBLANK(O$3), IF( ISBLANK(N$3), 0, N$7 *$C18 ), O$7 * $C18 ) -> 0 | ... R18: =IF( ISBLANK(Q$3), IF( ISBLANK(P$3), 0, P$7 *$C18 ), Q$7 * $C18 ) -> 0 | T18: =IF( ISBLANK(#REF!), IF( ISBLANK(R$3), 0, R$7 *$C18 ),#REF! * $C18 ) -> #REF! | U18: =IF( ISBLANK(T$3), IF( ISBLANK(#REF!), 0,#REF! * $C18 ), T$7 * $C18 ) -> 0 | V18: =IF( ISBLANK(U$3), IF( ISBLANK(T$3), 0, T$7 *$C18 ), U$7 * $C18 ) -> 0 | W18: =IF( ISBLANK(V$3), IF( ISBLANK(U$3), 0, U$7 *$C18 ), V$7 * $C18 ) -> 0 | X18: =IF( ISBLANK(W$3), IF( ISBLANK(V$3), 0, V$7 *$C18 ), W$7 * $C18 ) -> 0 | Y18: =IF( ISBLANK(X$3), IF( ISBLANK(W$3), 0, W$7 *$C18 ), X$7 * $C18 ) -> 0 | Z18: =IF( ISBLANK(Y$3), IF( ISBLANK(X$3), 0, X$7 *$C18 ), Y$7 * $C18 ) -> 0 | AA18: =IF( ISBLANK(Z$3), IF( ISBLANK(Y$3), 0, Y$7 *$C18 ), Z$7 * $C18 ) -> 0 | AB18: =IF( ISBLANK(AA$3), IF( ISBLANK(Z$3), 0, Z$7 *$C18 ), AA$7 * $C18 ) -> 0 | AC18: =IF( ISBLANK(AB$3), IF( ISBLANK(AA$3), 0, AA$7 *$C18 ), AB$7 * $C18 ) -> 0 | ... AE18: =IF( ISBLANK(AD$3), IF( ISBLANK(AC$3), 0, AC$7 *$C18 ), AD$7 * $C18 ) -> 0 | AG18: =IF( ISBLANK(#REF!), IF( ISBLANK(AE$3), 0, AE$7 *$C18 ),#REF! * $C18 ) -> #REF! | AH18: =IF( ISBLANK(AG$3), IF( ISBLANK(#REF!), 0,#REF! * $C18 ), AG$7 * $C18 ) -> 0 | AI18: =IF( ISBLANK(AH$3), IF( ISBLANK(AG$3), 0, AG$7 *$C18 ), AH$7 * $C18 ) -> 0 | AJ18: =IF( ISBLANK(AI$3), IF( ISBLANK(AH$3), 0, AH$7 *$C18 ), AI$7 * $C18 ) -> 0 | AK18: =IF( ISBLANK(AJ$3), IF( ISBLANK(AI$3), 0, AI$7 *$C18 ), AJ$7 * $C18 ) -> 0 | AL18: =IF( ISBLANK(AK$3), IF( ISBLANK(AJ$3), 0, AJ$7 *$C18 ), AK$7 * $C18 ) -> 0 | AM18: =IF( ISBLANK(AL$3), IF( ISBLANK(AK$3), 0, AK$7 *$C18 ), AL$7 * $C18 ) -> 0 | AN18: =IF( ISBLANK(AM$3), IF( ISBLANK(AL$3), 0, AL$7 *$C18 ), AM$7 * $C18 ) -> 0 | AO18: =IF( ISBLANK(AN$3), IF( ISBLANK(AM$3), 0, AM$7 *$C18 ), AN$7 * $C18 ) -> 0 | AP18: =IF( ISBLANK(AO$3), IF( ISBLANK(AN$3), 0, AN$7 *$C18 ), AO$7 * $C18 ) -> 0 | ... AR18: =IF( ISBLANK(AQ$3), IF( ISBLANK(AP$3), 0, AP$7 *$C18 ), AQ$7 * $C18 ) -> 0
A20: On purchase | B20: =Parameter!B8 -> 0.5 | G20: =$B20*G$7 -> 0 | H20: =$B20*H$7 -> 0 | I20: =$B20*I$7 -> 0 | J20: =$B20*J$7 -> 0 | K20: =$B20*K$7 -> 0 | L20: =$B20*L$7 -> 3666600000 | M20: =$B20*M$7 -> 3666600000 | N20: =$B20*N$7 -> 3849930000 | ... R20: =$B20*R$7 -> 4033260000 | T20: =$B20*T$7 -> 3483270000 | U20: =$B20*U$7 -> 3483270000 | V20: =$B20*V$7 -> 3483270000 | W20: =$B20*W$7 -> 4216590000 | X20: =$B20*X$7 -> 4216590000 | Y20: =$B20*Y$7 -> 4216590000 | Z20: =$B20*Z$7 -> 4399920000 | AA20: =$B20*AA$7 -> 4399920000 | ... AE20: =$B20*AE$7 -> 7011900000 | AG20: =$B20*AG$7 -> 5733315000 | AH20: =$B20*AH$7 -> 5733315000 | AI20: =$B20*AI$7 -> 5733315000 | AJ20: =$B20*AJ$7 -> 7314300000 | AK20: =$B20*AK$7 -> 7314300000 | AL20: =$B20*AL$7 -> 7314300000 | AM20: =$B20*AM$7 -> 7740495000 | AN20: =$B20*AN$7 -> 7740495000 | ... AT20: =$B20*AT$7 -> 0
A21: For 1st prior period | B21: =Parameter!B9 -> 0.3 | G21: =F$7*$B21 -> 0 | H21: =G$7*$B21 -> 0 | I21: =H$7*$B21 -> 0 | J21: =I$7*$B21 -> 0 | K21: =J$7*$B21 -> 0 | L21: =K$7*$B21 -> 0 | M21: =L$7*$B21 -> 2199960000 | N21: =M$7*$B21 -> 2199960000 | ... R21: =Q$7*$B21 -> 2419956000 | T21: =R$7*$B21 -> 2419956000 | U21: =T$7*$B21 -> 2089962000 | V21: =U$7*$B21 -> 2089962000 | W21: =V$7*$B21 -> 2089962000 | X21: =W$7*$B21 -> 2529954000 | Y21: =X$7*$B21 -> 2529954000 | Z21: =Y$7*$B21 -> 2529954000 | AA21: =Z$7*$B21 -> 2639952000 | AB21: =AA$7*$B21 -> 2639952000 | ... AE21: =AD$7*$B21 -> 4207140000 | AG21: =AE$7*$B21 -> 4207140000 | AH21: =AG$7*$B21 -> 3439989000 | AI21: =AH$7*$B21 -> 3439989000 | AJ21: =AI$7*$B21 -> 3439989000 | AK21: =AJ$7*$B21 -> 4388580000 | AL21: =AK$7*$B21 -> 4388580000 | AM21: =AL$7*$B21 -> 4388580000 | AN21: =AM$7*$B21 -> 4644297000 | AO21: =AN$7*$B21 -> 4644297000 | ... AT21: =AS$7*$B21 -> 0
A22: For 2nd prior period | B22: =Parameter!B10 -> 0.2 | G22: =E$7*$B22 -> 0 | H22: =F$7*$B22 -> 0 | I22: =G$7*$B22 -> 0 | J22: =H$7*$B22 -> 0 | K22: =I$7*$B22 -> 0 | L22: =J$7*$B22 -> 0 | M22: =K$7*$B22 -> 0 | N22: =L$7*$B22 -> 1466640000 | ... R22: =P$7*$B22 -> 1613304000 | T22: =Q$7*$B22 -> 1613304000 | U22: =R$7*$B22 -> 1613304000 | V22: =T$7*$B22 -> 1393308000 | W22: =U$7*$B22 -> 1393308000 | X22: =V$7*$B22 -> 1393308000 | Y22: =W$7*$B22 -> 1686636000 | Z22: =X$7*$B22 -> 1686636000 | AA22: =Y$7*$B22 -> 1686636000 | AB22: =Z$7*$B22 -> 1759968000 | AC22: =AA$7*$B22 -> 1759968000 | ... AE22: =AC$7*$B22 -> 1833300000 | AG22: =AD$7*$B22 -> 2804760000 | AH22: =AE$7*$B22 -> 2804760000 | AI22: =AG$7*$B22 -> 2293326000 | AJ22: =AH$7*$B22 -> 2293326000 | AK22: =AI$7*$B22 -> 2293326000 | AL22: =AJ$7*$B22 -> 2925720000 | AM22: =AK$7*$B22 -> 2925720000 | AN22: =AL$7*$B22 -> 2925720000 | AO22: =AM$7*$B22 -> 3096198000 | AP22: =AN$7*$B22 -> 3096198000 | ... AT22: =AR$7*$B22 -> 3266676000
A23: TOTAL PAYMENT | G23: =SUM(G20:G22) -> 0 | H23: =SUM(H20:H22) -> 0 | I23: =SUM(I20:I22) -> 0 | J23: =SUM(J20:J22) -> 0 | K23: =SUM(K20:K22) -> 0 | L23: =SUM(L20:L22) -> 3666600000 | M23: =SUM(M20:M22) -> 5866560000 | N23: =SUM(N20:N22) -> 7516530000 | ... R23: =SUM(R20:R22) -> 8066520000 | T23: =SUM(T20:T22) -> 7516530000 | U23: =SUM(U20:U22) -> 7186536000 | V23: =SUM(V20:V22) -> 6966540000 | W23: =SUM(W20:W22) -> 7699860000 | X23: =SUM(X20:X22) -> 8139852000 | Y23: =SUM(Y20:Y22) -> 8433180000 | Z23: =SUM(Z20:Z22) -> 8616510000 | AA23: =SUM(AA20:AA22) -> 8726508000 | ... AE23: =SUM(AE20:AE22) -> 13052340000 | AG23: =SUM(AG20:AG22) -> 12745215000 | AH23: =SUM(AH20:AH22) -> 11978064000 | AI23: =SUM(AI20:AI22) -> 11466630000 | AJ23: =SUM(AJ20:AJ22) -> 13047615000 | AK23: =SUM(AK20:AK22) -> 13996206000 | AL23: =SUM(AL20:AL22) -> 14628600000 | AM23: =SUM(AM20:AM22) -> 15054795000 | AN23: =SUM(AN20:AN22) -> 15310512000 | ... AT23: =SUM(AT20:AT22) -> 3266676000
A24: Recievable (Offseting):
A25: For 1st following period | F25: =G21 -> 0 | G25: =H21 -> 0 | H25: =I21 -> 0 | I25: =J21 -> 0 | J25: =K21 -> 0 | K25: =L21 -> 0 | L25: =M21 -> 2199960000 | M25: =N21 -> 2199960000 | ... Q25: =R21 -> 2419956000 | R25: =T21 -> 2419956000 | T25: =U21 -> 2089962000 | U25: =V21 -> 2089962000 | V25: =W21 -> 2089962000 | W25: =X21 -> 2529954000 | X25: =Y21 -> 2529954000 | Y25: =Z21 -> 2529954000 | Z25: =AA21 -> 2639952000 | AA25: =AB21 -> 2639952000 | ... AD25: =AE21 -> 4207140000 | AE25: =AG21 -> 4207140000 | AF25: =IF(ISBLANK(AF3),AE25) -> 4207140000 | AG25: =AH21 -> 3439989000 | AH25: =AI21 -> 3439989000 | AI25: =AJ21 -> 3439989000 | AJ25: =AK21 -> 4388580000 | AK25: =AL21 -> 4388580000 | AL25: =AM21 -> 4388580000 | AM25: =AN21 -> 4644297000 | AN25: =AO21 -> 4644297000 | ... AS25: =AT21 -> 0 | AT25: =BA21 -> 0
A26: For 2nd following period | E26: =G22 -> 0 | F26: =H22 -> 0 | G26: =I22 -> 0 | H26: =J22 -> 0 | I26: =K22 -> 0 | J26: =L22 -> 0 | K26: =M22 -> 0 | L26: =N22 -> 1466640000 | ... P26: =R22 -> 1613304000 | Q26: =T22 -> 1613304000 | R26: =U22 -> 1613304000 | T26: =V22 -> 1393308000 | U26: =W22 -> 1393308000 | V26: =X22 -> 1393308000 | W26: =Y22 -> 1686636000 | X26: =Z22 -> 1686636000 | Y26: =AA22 -> 1686636000 | Z26: =AB22 -> 1759968000 | AA26: =AC22 -> 1759968000 | ... AC26: =AE22 -> 1833300000 | AD26: =AG22 -> 2804760000 | AE26: =AH22 -> 2804760000 | AF26: =IF(ISBLANK(AF3),AE26) -> 2804760000 | AG26: =AI22 -> 2293326000 | AH26: =AJ22 -> 2293326000 | AI26: =AK22 -> 2293326000 | AJ26: =AL22 -> 2925720000 | AK26: =AM22 -> 2925720000 | AL26: =AN22 -> 2925720000 | AM26: =AO22 -> 3096198000 | AN26: =AP22 -> 3096198000 | ... AR26: =AT22 -> 3266676000 | AS26: =BA22 -> 0 | AT26: =BB22 -> 0
A27: ACCOUNT RECEIVABLE | G27: =SUM(G25:G26)-SUM(G21:G22)+F27 -> 0 | H27: =SUM(H25:H26)-SUM(H21:H22)+G27 -> 0 | I27: =SUM(I25:I26)-SUM(I21:I22)+H27 -> 0 | J27: =SUM(J25:J26)-SUM(J21:J22)+I27 -> 0 | K27: =SUM(K25:K26)-SUM(K21:K22)+J27 -> 0 | L27: =SUM(L25:L26)-SUM(L21:L22)+K27 -> 3666600000 | M27: =SUM(M25:M26)-SUM(M21:M22)+L27 -> 5133240000 | N27: =SUM(N25:N26)-SUM(N21:N22)+M27 -> 5316570000 | ... AE27: =SUM(AE25:AE26)-SUM(AE21:AE22)+AD27 -> 9816660000 | AG27: =SUM(AG25:AG26)-SUM(AG21:AG22)+AE27 -> 8538075000 | AH27: =SUM(AH25:AH26)-SUM(AH21:AH22)+AG27 -> 8026641000 | AI27: =SUM(AI25:AI26)-SUM(AI21:AI22)+AH27 -> 8026641000 | AJ27: =SUM(AJ25:AJ26)-SUM(AJ21:AJ22)+AI27 -> 9607626000 | AK27: =SUM(AK25:AK26)-SUM(AK21:AK22)+AJ27 -> 10240020000 | AL27: =SUM(AL25:AL26)-SUM(AL21:AL22)+AK27 -> 10240020000 | AM27: =SUM(AM25:AM26)-SUM(AM21:AM22)+AL27 -> 10666215000 | AN27: =SUM(AN25:AN26)-SUM(AN21:AN22)+AM27 -> 10836693000 | AO27: =SUM(AO25:AO26)-SUM(AO21:AO22)+AN27 -> 11079558000 | ... AT27: =SUM(AT25:AT26)-SUM(AT21:AT22)+AS27 -> 0
A30: AP plan | G30: 2025 | T30: 2026 | AG30: 2027
G31: Q1 | J31: Q2 | M31: Q3 | P31: Q4 | T31: Q1 | W31: Q2 | Z31: Q3 | AC31: Q4 | AG31: Q1 | AJ31: Q2 | AM31: Q3 | AP31: Q4
G32: 1 | H32: 2 | I32: 3 | J32: 4 | K32: 5 | L32: 6 | M32: 7 | N32: 8 | O32: 9 | P32: 10 | Q32: 11 | R32: 12 | T32: 1 | U32: 2 | V32: 3 | W32: 4 | X32: 5 | Y32: 6 | Z32: 7 | AA32: 8 | AB32: 9 | AC32: 10 | AD32: 11 | AE32: 12 | AG32: 1 | AH32: 2 | AI32: 3 | AJ32: 4 | AK32: 5 | AL32: 6 | AM32: 7 | AN32: 8 | AO32: 9 | AP32: 10 | AQ32: 11 | AR32: 12
A33: Production outputs | C33: Mat cost | E33: =SUM(E34:E35) -> 0 | F33: =SUM(F34:F35) -> 0 | G33: ='Operations plan'!E77 -> 0 | H33: ='Operations plan'!F77 -> 0 | I33: ='Operations plan'!G77 -> 0 | J33: ='Operations plan'!H77 -> 0 | K33: ='Operations plan'!I77 -> 274 | L33: ='Operations plan'!J77 -> 1200 | M33: ='Operations plan'!K77 -> 1219 | N33: ='Operations plan'!L77 -> 1350 | ... R33: ='Operations plan'!P77 -> 1389 | T33: ='Operations plan'!R77 -> 1204 | U33: ='Operations plan'!S77 -> 1204 | V33: ='Operations plan'!T77 -> 1237 | W33: ='Operations plan'!U77 -> 1476 | X33: ='Operations plan'!V77 -> 1476 | Y33: ='Operations plan'!W77 -> 1483 | Z33: ='Operations plan'!X77 -> 1532 | AA33: ='Operations plan'!Y77 -> 1532 | ... AE33: ='Operations plan'!AC77 -> 1878 | AG33: ='Operations plan'!AE77 -> 1651 | AH33: ='Operations plan'!AF77 -> 1641 | AI33: ='Operations plan'!AG77 -> 1679 | AJ33: ='Operations plan'!AH77 -> 1962 | AK33: ='Operations plan'!AI77 -> 1962 | AL33: ='Operations plan'!AJ77 -> 1971 | AM33: ='Operations plan'!AK77 -> 2042 | AN33: ='Operations plan'!AL77 -> 2046 | ... AR33: ='Operations plan'!AP77 -> 1906
B34: Standard | C34: =Parameter!B65 -> 3350000 | E34: =E21+E24+E31 -> 0 | F34: =F21+F24+F31 -> 0 | G34: ='Operations plan'!E78 -> 0 | H34: ='Operations plan'!F78 -> 0 | I34: ='Operations plan'!G78 -> 0 | J34: ='Operations plan'!H78 -> 0 | K34: ='Operations plan'!I78 -> 274 | L34: ='Operations plan'!J78 -> 1200 | M34: ='Operations plan'!K78 -> 1219 | N34: ='Operations plan'!L78 -> 1350 | ... R34: ='Operations plan'!P78 -> 1389 | T34: ='Operations plan'!R78 -> 1204 | U34: ='Operations plan'!S78 -> 1204 | V34: ='Operations plan'!T78 -> 1237 | W34: ='Operations plan'!U78 -> 1476 | X34: ='Operations plan'!V78 -> 1476 | Y34: ='Operations plan'!W78 -> 1483 | Z34: ='Operations plan'!X78 -> 1532 | AA34: ='Operations plan'!Y78 -> 1532 | ... AE34: ='Operations plan'!AC78 -> 1582 | AG34: ='Operations plan'!AE78 -> 1391 | AH34: ='Operations plan'!AF78 -> 1391 | AI34: ='Operations plan'!AG78 -> 1409 | AJ34: ='Operations plan'!AH78 -> 1547 | AK34: ='Operations plan'!AI78 -> 1547 | AL34: ='Operations plan'!AJ78 -> 1553 | AM34: ='Operations plan'!AK78 -> 1598 | AN34: ='Operations plan'!AL78 -> 1598 | ... AR34: ='Operations plan'!AP78 -> 1482
B35: E-bike | C35: =Parameter!B66 -> 10800000 | E35: =E22+E25+E32 -> 0 | F35: =F22+F25+F32 -> 0 | G35: ='Operations plan'!E79 -> 0 | H35: ='Operations plan'!F79 -> 0 | I35: ='Operations plan'!G79 -> 0 | J35: ='Operations plan'!H79 -> 0 | K35: ='Operations plan'!I79 -> 0 | L35: ='Operations plan'!J79 -> 0 | M35: ='Operations plan'!K79 -> 0 | N35: ='Operations plan'!L79 -> 0 | ... R35: ='Operations plan'!P79 -> 0 | T35: ='Operations plan'!R79 -> 0 | U35: ='Operations plan'!S79 -> 0 | V35: ='Operations plan'!T79 -> 0 | W35: ='Operations plan'!U79 -> 0 | X35: ='Operations plan'!V79 -> 0 | Y35: ='Operations plan'!W79 -> 0 | Z35: ='Operations plan'!X79 -> 0 | AA35: ='Operations plan'!Y79 -> 0 | ... AE35: ='Operations plan'!AC79 -> 296 | AG35: ='Operations plan'!AE79 -> 260 | AH35: ='Operations plan'!AF79 -> 250 | AI35: ='Operations plan'!AG79 -> 270 | AJ35: ='Operations plan'!AH79 -> 415 | AK35: ='Operations plan'!AI79 -> 415 | AL35: ='Operations plan'!AJ79 -> 418 | AM35: ='Operations plan'!AK79 -> 444 | AN35: ='Operations plan'!AL79 -> 448 | ... AR35: ='Operations plan'!AP79 -> 424
A38: On purchase | B38: =Parameter!B11 -> 0.7 | C38: =Parameter!B11 -> 0.7 | G38: =$C38*SUMPRODUCT($C$34:$C$35,G34:G35) -> 0 | H38: =$C38*SUMPRODUCT($C$34:$C$35,H34:H35) -> 0 | I38: =$C38*SUMPRODUCT($C$34:$C$35,I34:I35) -> 0 | J38: =$C38*SUMPRODUCT($C$34:$C$35,J34:J35) -> 0 | K38: =$C38*SUMPRODUCT($C$34:$C$35,K34:K35) -> 642530000 | L38: =$C38*SUMPRODUCT($C$34:$C$35,L34:L35) -> 2814000000 | M38: =$C38*SUMPRODUCT($C$34:$C$35,M34:M35) -> 2858555000 | N38: =$C38*SUMPRODUCT($C$34:$C$35,N34:N35) -> 3165750000 | ... R38: =$C38*SUMPRODUCT($C$34:$C$35,R34:R35) -> 3257205000 | T38: =$C38*SUMPRODUCT($C$34:$C$35,T34:T35) -> 2823380000 | U38: =$C38*SUMPRODUCT($C$34:$C$35,U34:U35) -> 2823380000 | V38: =$C38*SUMPRODUCT($C$34:$C$35,V34:V35) -> 2900765000 | W38: =$C38*SUMPRODUCT($C$34:$C$35,W34:W35) -> 3461220000 | X38: =$C38*SUMPRODUCT($C$34:$C$35,X34:X35) -> 3461220000 | Y38: =$C38*SUMPRODUCT($C$34:$C$35,Y34:Y35) -> 3477635000 | Z38: =$C38*SUMPRODUCT($C$34:$C$35,Z34:Z35) -> 3592540000 | AA38: =$C38*SUMPRODUCT($C$34:$C$35,AA34:AA35) -> 3592540000 | ... AE38: =$C38*SUMPRODUCT($C$34:$C$35,AE34:AE35) -> 5947550000 | AG38: =$C38*SUMPRODUCT($C$34:$C$35,AG34:AG35) -> 5227495000 | AH38: =$C38*SUMPRODUCT($C$34:$C$35,AH34:AH35) -> 5151895000 | AI38: =$C38*SUMPRODUCT($C$34:$C$35,AI34:AI35) -> 5345305000 | AJ38: =$C38*SUMPRODUCT($C$34:$C$35,AJ34:AJ35) -> 6765115000 | AK38: =$C38*SUMPRODUCT($C$34:$C$35,AK34:AK35) -> 6765115000 | AL38: =$C38*SUMPRODUCT($C$34:$C$35,AL34:AL35) -> 6801865000 | AM38: =$C38*SUMPRODUCT($C$34:$C$35,AM34:AM35) -> 7103950000 | AN38: =$C38*SUMPRODUCT($C$34:$C$35,AN34:AN35) -> 7134190000 | ... AR38: =$C38*SUMPRODUCT($C$34:$C$35,AR34:AR35) -> 6680730000
A39: For prior period | B39: =Parameter!B12 -> 0.3 | C39: =Parameter!B12 -> 0.3 | G39: =$C39*SUMPRODUCT($C$34:$C$35,F34:F35) -> 0 | H39: =$C39*SUMPRODUCT($C$34:$C$35,G34:G35) -> 0 | I39: =$C39*SUMPRODUCT($C$34:$C$35,H34:H35) -> 0 | J39: =$C39*SUMPRODUCT($C$34:$C$35,I34:I35) -> 0 | K39: =$C39*SUMPRODUCT($C$34:$C$35,J34:J35) -> 0 | L39: =$C39*SUMPRODUCT($C$34:$C$35,K34:K35) -> 2.7537e+08 | M39: =$C39*SUMPRODUCT($C$34:$C$35,L34:L35) -> 1.206e+09 | N39: =$C39*SUMPRODUCT($C$34:$C$35,M34:M35) -> 1.225095e+09 | ... R39: =$C39*SUMPRODUCT($C$34:$C$35,Q34:Q35) -> 1.422075e+09 | T39: =$C39*SUMPRODUCT($C$34:$C$35,R34:R35) -> 1.395945e+09 | U39: =$C39*SUMPRODUCT($C$34:$C$35,T34:T35) -> 1.21002e+09 | V39: =$C39*SUMPRODUCT($C$34:$C$35,U34:U35) -> 1.21002e+09 | W39: =$C39*SUMPRODUCT($C$34:$C$35,V34:V35) -> 1.243185e+09 | X39: =$C39*SUMPRODUCT($C$34:$C$35,W34:W35) -> 1.48338e+09 | Y39: =$C39*SUMPRODUCT($C$34:$C$35,X34:X35) -> 1.48338e+09 | Z39: =$C39*SUMPRODUCT($C$34:$C$35,Y34:Y35) -> 1.490415e+09 | AA39: =$C39*SUMPRODUCT($C$34:$C$35,Z34:Z35) -> 1.53966e+09 | AB39: =$C39*SUMPRODUCT($C$34:$C$35,AA34:AA35) -> 1.53966e+09 | ... AE39: =$C39*SUMPRODUCT($C$34:$C$35,AD34:AD35) -> 2.80881e+09 | AG39: =$C39*SUMPRODUCT($C$34:$C$35,AE34:AE35) -> 2.54895e+09 | AH39: =$C39*SUMPRODUCT($C$34:$C$35,AG34:AG35) -> 2.240355e+09 | AI39: =$C39*SUMPRODUCT($C$34:$C$35,AH34:AH35) -> 2.207955e+09 | AJ39: =$C39*SUMPRODUCT($C$34:$C$35,AI34:AI35) -> 2.290845e+09 | AK39: =$C39*SUMPRODUCT($C$34:$C$35,AJ34:AJ35) -> 2.899335e+09 | AL39: =$C39*SUMPRODUCT($C$34:$C$35,AK34:AK35) -> 2.899335e+09 | AM39: =$C39*SUMPRODUCT($C$34:$C$35,AL34:AL35) -> 2.915085e+09 | AN39: =$C39*SUMPRODUCT($C$34:$C$35,AM34:AM35) -> 3.04455e+09 | AO39: =$C39*SUMPRODUCT($C$34:$C$35,AN34:AN35) -> 3.05751e+09 | ... AT39: =$C39*SUMPRODUCT($C$34:$C$35,AS34:AS35) -> 0
A40: TOTAL PAYMENT | G40: =SUM(G38:G39) -> 0 | H40: =SUM(H38:H39) -> 0 | I40: =SUM(I38:I39) -> 0 | J40: =SUM(J38:J39) -> 0 | K40: =SUM(K38:K39) -> 642530000 | L40: =SUM(L38:L39) -> 3089370000 | M40: =SUM(M38:M39) -> 4064555000 | N40: =SUM(N38:N39) -> 4390845000 | ... AE40: =SUM(AE38:AE39) -> 8756360000 | AG40: =SUM(AG38:AG39) -> 7776445000 | AH40: =SUM(AH38:AH39) -> 7392250000 | AI40: =SUM(AI38:AI39) -> 7553260000 | AJ40: =SUM(AJ38:AJ39) -> 9055960000 | AK40: =SUM(AK38:AK39) -> 9664450000 | AL40: =SUM(AL38:AL39) -> 9701200000 | AM40: =SUM(AM38:AM39) -> 10019035000 | AN40: =SUM(AN38:AN39) -> 10178740000 | ... AT40: =SUM(AT38:AT39) -> 0
A41: Payable (Offseting)
A42: For following period | F42: =G39 -> 0 | G42: =H39 -> 0 | H42: =I39 -> 0 | I42: =J39 -> 0 | J42: =K39 -> 0 | K42: =L39 -> 2.7537e+08 | L42: =M39 -> 1.206e+09 | M42: =N39 -> 1.225095e+09 | ... Q42: =R39 -> 1.422075e+09 | R42: =T39 -> 1.395945e+09 | S42: =IF(ISBLANK(S32),R42) -> 1.395945e+09 | T42: =U39 -> 1.21002e+09 | U42: =V39 -> 1.21002e+09 | V42: =W39 -> 1.243185e+09 | W42: =X39 -> 1.48338e+09 | X42: =Y39 -> 1.48338e+09 | Y42: =Z39 -> 1.490415e+09 | Z42: =AA39 -> 1.53966e+09 | AA42: =AB39 -> 1.53966e+09 | ... AD42: =AE39 -> 2.80881e+09 | AE42: =AG39 -> 2.54895e+09 | AF42: =IF(ISBLANK(AF32),AE42) -> 2.54895e+09 | AG42: =AH39 -> 2.240355e+09 | AH42: =AI39 -> 2.207955e+09 | AI42: =AJ39 -> 2.290845e+09 | AJ42: =AK39 -> 2.899335e+09 | AK42: =AL39 -> 2.899335e+09 | AL42: =AM39 -> 2.915085e+09 | AM42: =AN39 -> 3.04455e+09 | AN42: =AO39 -> 3.05751e+09 | ... AS42: =AT39 -> 0 | AT42: =BA39 -> 0
A43: ACCOUNT PAYABLE | G43: =G42-G39+F45 -> 0 | H43: =H42-H39+G43 -> 0 | I43: =I42-I39+H43 -> 0 | J43: =J42-J39+I43 -> 0 | K43: =K42-K39+J43 -> 2.7537e+08 | L43: =L42-L39+K43 -> 1.206e+09 | M43: =M42-M39+L43 -> 1.225095e+09 | N43: =N42-N39+M43 -> 1.35675e+09 | O43: =O42-O39+N43 -> 1.36479e+09 | ... R43: =R42-R39+Q43 -> 1.395945e+09 | T43: =T42-T39+R43 -> 1.21002e+09 | U43: =U42-U39+T43 -> 1.21002e+09 | V43: =V42-V39+U43 -> 1.243185e+09 | W43: =W42-W39+V43 -> 1.48338e+09 | X43: =X42-X39+W43 -> 1.48338e+09 | Y43: =Y42-Y39+X43 -> 1.490415e+09 | Z43: =Z42-Z39+Y43 -> 1.53966e+09 | AA43: =AA42-AA39+Z43 -> 1.53966e+09 | AB43: =AB42-AB39+AA43 -> 1.546695e+09 | ... AE43: =AE42-AE39+AD43 -> 2.54895e+09 | AG43: =AG42-AG39+AE43 -> 2.240355e+09 | AH43: =AH42-AH39+AG43 -> 2.207955e+09 | AI43: =AI42-AI39+AH43 -> 2.290845e+09 | AJ43: =AJ42-AJ39+AI43 -> 2.899335e+09 | AK43: =AK42-AK39+AJ43 -> 2.899335e+09 | AL43: =AL42-AL39+AK43 -> 2.915085e+09 | AM43: =AM42-AM39+AL43 -> 3.04455e+09 | AN43: =AN42-AN39+AM43 -> 3.05751e+09 | AO43: =AO42-AO39+AN43 -> 3.1518e+09 | ... AT43: =AT42-AT39+AS43 -> 0

Sheet Marketing plan
A1: Marketing | E1: 2025 | R1: 2026 | AJ1: 2027
E2: Q1 | H2: Q2 | K2: Q3 | N2: Q4 | R2: Q1 | U2: Q2 | AA2: Q3 | AD2: Q4 | AJ2: Q1 | AM2: Q2 | AS2: Q3 | AV2: Q4
E3: 1 | F3: 2 | G3: 3 | H3: 4 | I3: 5 | J3: 6 | K3: 7 | L3: 8 | M3: 9 | N3: 10 | O3: 11 | P3: 12 | R3: 1 | S3: 2 | T3: 3 | U3: 4/H1 | V3: 4/H2 | W3: 5/H1 | X3: 5/H2 | Y3: 6/H1 | Z3: 6/H2 | AA3: 7 | AB3: 8 | AC3: 9 | AD3: 10/1H | AE3: 10/2H | AF3: 11/1H | AG3: 11/2H | AH3: 12/1H | AI3: 12/2H | AJ3: 1 | AK3: 2 | AL3: 3 | AM3: 4/H1 | AN3: 4/H2 | AO3: 5/H1 | AP3: 5/H2 | AQ3: 6/H1 | AR3: 6/H2 | AS3: 7 | AT3: 8 | AU3: 9 | AV3: 10/1H | AW3: 10/2H | AX3: 11/1H | AY3: 11/2H | AZ3: 12/1H | BA3: 12/2H
A4: Advertising | E4: =SUM(E5:E10) -> 0 | F4: =SUM(F5:F10) -> 0 | G4: =SUM(G5:G10) -> 0 | H4: =SUM(H5:H10) -> 0 | I4: =SUM(I5:I10) -> 11000000 | J4: =SUM(J5:J10) -> 20000000 | K4: =SUM(K5:K10) -> 8500000 | L4: =SUM(L5:L10) -> 22000000 | ... P4: =SUM(P5:P10) -> 8500000 | R4: =SUM(R5:R10) -> 6500000 | S4: =SUM(S5:S10) -> 6500000 | T4: =SUM(T5:T10) -> 7500000 | U4: =SUM(U5:U10) -> 3750000 | V4: =SUM(V5:V10) -> 3750000 | W4: =SUM(W5:W10) -> 5750000 | X4: =SUM(X5:X10) -> 5750000 | Y4: =SUM(Y5:Y10) -> 3750000 | ... BA4: =SUM(BA5:BA10) -> 4250000
A5: Print Ads | I5: 3000000 | J5: 3000000 | K5: =500000 -> 500000 | L5: 3000000 | M5: 500000 | N5: 500000 | O5: 500000 | P5: 500000 | R5: 500000 | S5: 500000 | T5: 500000 | U5: =500000/2 -> 250000 | V5: =500000/2 -> 250000 | W5: =500000/2 -> 250000 | X5: =500000/2 -> 250000 | Y5: =500000/2 -> 250000 | Z5: =500000/2 -> 250000 | AA5: 500000 | AB5: 500000 | AC5: 500000 | AD5: 250000 | AE5: 250000 | AF5: =3000000/2 -> 1500000 | AG5: =3000000/2 -> 1500000 | AH5: 250000 | AI5: 250000 | AJ5: 3000000 | AK5: 500000 | AL5: =500000 -> 500000 | AM5: 250000 | AN5: 250000 | AO5: 250000 | AP5: 250000 | AQ5: 250000 | AR5: 250000 | AS5: 500000 | AT5: 500000 | AU5: 500000 | AV5: 250000 | AW5: 250000 | AX5: 250000 | AY5: 250000 | AZ5: 250000 | BA5: 250000
A6: Banner Ads | I6: 3000000 | J6: 6000000 | K6: 3000000 | L6: 6000000 | M6: 3000000 | N6: 3000000 | O6: 3000000 | P6: 3000000 | R6: 3000000 | S6: 3000000 | T6: 3000000 | U6: =3000000/2 -> 1500000 | V6: =3000000/2 -> 1500000 | W6: =3000000/2 -> 1500000 | X6: =3000000/2 -> 1500000 | Y6: =3000000/2 -> 1500000 | Z6: =3000000/2 -> 1500000 | AA6: 3000000 | AB6: 3000000 | AC6: 3000000 | AD6: =3000000/2 -> 1500000 | AE6: =3000000/2 -> 1500000 | AF6: =6000000/2 -> 3000000 | AG6: =6000000/2 -> 3000000 | AH6: =3000000/2 -> 1500000 | AI6: =3000000/2 -> 1500000 | AJ6: 6000000 | AK6: 3000000 | AL6: 3000000 | AM6: =3000000/2 -> 1500000 | AN6: =3000000/2 -> 1500000 | AO6: =3000000/2 -> 1500000 | AP6: =3000000/2 -> 1500000 | AQ6: =3000000/2 -> 1500000 | AR6: =3000000/2 -> 1500000 | AS6: 3000000 | AT6: 3000000 | AU6: 3000000 | AV6: =3000000/2 -> 1500000 | AW6: =3000000/2 -> 1500000 | AX6: =3000000/2 -> 1500000 | AY6: =3000000/2 -> 1500000 | AZ6: =3000000/2 -> 1500000 | BA6: =3000000/2 -> 1500000
A7: Public Relations | I7: 2000000 | J7: 3000000 | K7: 3000000 | L7: 5000000 | M7: 2000000 | N7: 2000000 | O7: 2000000 | P7: 2000000 | R7: 2000000 | S7: 2000000 | T7: 2000000 | U7: 1000000 | V7: 1000000 | W7: 1000000 | X7: 1000000 | Y7: 1000000 | Z7: 1000000 | AA7: 2000000 | AB7: 2000000 | AC7: 2000000 | AD7: 1000000 | AE7: 1000000 | AF7: =5000000/2 -> 2500000 | AG7: =5000000/2 -> 2500000 | AH7: 1000000 | AI7: 1000000 | AJ7: 5000000 | AK7: 2000000 | AL7: 2000000 | AM7: 1000000 | AN7: 1000000 | AO7: 1000000 | AP7: 1000000 | AQ7: 1000000 | AR7: 1000000 | AS7: 2000000 | AT7: 2000000 | AU7: 2000000 | AV7: 1000000 | AW7: 1000000 | AX7: 1000000 | AY7: 1000000 | AZ7: 1000000 | BA7: 1000000
A8: Press Releases | J8: 3000000 | L8: 3000000 | W8: =3000000/2 -> 1500000 | X8: =3000000/2 -> 1500000 | AF8: =3000000/2 -> 1500000 | AG8: =3000000/2 -> 1500000 | AH8: =3000000/2 -> 1500000 | AI8: =3000000/2 -> 1500000 | AJ8: 3000000
A9: Booths | I9: 3000000 | J9: 5000000 | K9: 2000000 | L9: 5000000 | M9: 2000000 | AF9: =10000000/2 -> 5000000 | AG9: =10000000/2 -> 5000000 | AJ9: 10000000
A10: Collaborations | N10: 2000000 | O10: 2000000 | P10: 3000000 | R10: 1000000 | S10: 1000000 | T10: 2000000 | U10: =2000000/2 -> 1000000 | V10: =2000000/2 -> 1000000 | W10: =3000000/2 -> 1500000 | X10: =3000000/2 -> 1500000 | Y10: =2000000/2 -> 1000000 | Z10: 1000000 | AA10: 1000000 | AB10: 2000000 | AC10: 2000000 | AD10: 1500000 | AE10: 1500000 | AF10: =5000000/2 -> 2500000 | AG10: =5000000/2 -> 2500000 | AH10: =3000000/2 -> 1500000 | AI10: =3000000/2 -> 1500000 | AJ10: 5000000 | AK10: 1000000 | AL10: 2000000 | AM10: 1000000 | AN10: 1000000 | AO10: =3000000/2 -> 1500000 | AP10: =3000000/2 -> 1500000 | AQ10: 1000000 | AR10: 1000000 | AS10: 1000000 | AT10: 2000000 | AU10: 1000000 | AV10: =1000000/2 -> 500000 | AW10: =1000000/2 -> 500000 | AX10: =1000000/2 -> 500000 | AY10: =1000000/2 -> 500000 | AZ10: =3000000/2 -> 1500000 | BA10: =3000000/2 -> 1500000
A11: Promotional Expenses | J11: =J16*(J17*J19+J18*J20)+J21+J22 -> 0 | K11: =K16*(K17*K19+K18*K20)+K21+K22 -> 0 | L11: =L16*(L17*L19+L18*L20)+L21+L22 -> 5000000 | M11: =M16*(M17*M19+M18*M20)+M21+M22 -> 5000000 | N11: =N16*(N17*N19+N18*N20)+N21+N22 -> 5000000 | O11: =O16*(O17*O19+O18*O20)+O21+O22 -> 5000000 | P11: =P16*(P17*P19+P18*P20)+P21+P22 -> 5000000 | R11: =R16*(R17*R19+R18*R20)+R21+R22 -> 86751600 | S11: =S16*(S17*S19+S18*S20)+S21+S22 -> 86751600 | T11: =T16*(T17*T19+T18*T20)+T21+T22 -> 86751600 | U11: =U16*(U17*U19+U18*U20)+U21+U22 -> 3750000 | V11: =V16*(V17*V19+V18*V20)+V21+V22 -> 3750000 | W11: =W16*(W17*W19+W18*W20)+W21+W22 -> 103970400 | X11: =X16*(X17*X19+X18*X20)+X21+X22 -> 103970400 | Y11: =Y16*(Y17*Y19+Y18*Y20)+Y21+Y22 -> 2500000 | ... BA11: =BA16*(BA17*BA19+BA18*BA20)+BA21+BA22 -> 2500000
A12: Promotion for new customers | B12: % | W12: 0.02 | X12: 0.02 | AE12: 0.02 | AF12: 0.02 | AG12: 0.02 | AO12: 0.02 | AP12: 0.02 | AW12: 0.02 | AX12: 0.02 | AY12: 0.02
A13: Flash sales | B13: %
A14: Eco-Ride New Year Sale | B14: % | R14: 0.01 | S14: 0.01 | T14: 0.01 | AJ14: 0.01 | AK14: 0.01 | AL14: 0.01
A15: Fall Sales | B15: % | AA15: 0.01 | AB15: 0.01 | AC15: 0.01 | AS15: 0.01 | AT15: 0.01 | AU15: 0.01
A16: Sum % | B16: % | J16: =SUM(J12:J15) -> 0 | K16: =SUM(K12:K15) -> 0 | L16: =SUM(L12:L15) -> 0 | M16: =SUM(M12:M15) -> 0 | N16: =SUM(N12:N15) -> 0 | O16: =SUM(O12:O15) -> 0 | P16: =SUM(P12:P15) -> 0 | R16: =SUM(R12:R15) -> 0.01 | S16: =SUM(S12:S15) -> 0.01 | T16: =SUM(T12:T15) -> 0.01 | U16: =SUM(U12:U15) -> 0 | V16: =SUM(V12:V15) -> 0 | W16: =SUM(W12:W15) -> 0.02 | X16: =SUM(X12:X15) -> 0.02 | Y16: =SUM(Y12:Y15) -> 0 | ... BA16: =SUM(BA12:BA15) -> 0
A17: Selling price | C17: Standard | J17: ='Operations plan'!$C$28 -> 6790000 | K17: ='Operations plan'!$C$28 -> 6790000 | L17: ='Operations plan'!$C$28 -> 6790000 | M17: ='Operations plan'!$C$28 -> 6790000 | N17: ='Operations plan'!$C$28 -> 6790000 | O17: ='Operations plan'!$C$28 -> 6790000 | P17: ='Operations plan'!$C$28 -> 6790000 | R17: ='Operations plan'!$C$28 -> 6790000 | S17: ='Operations plan'!$C$28 -> 6790000 | T17: ='Operations plan'!$C$28 -> 6790000 | U17: ='Operations plan'!$C$28 -> 6790000 | V17: ='Operations plan'!$C$28 -> 6790000 | W17: ='Operations plan'!$C$28 -> 6790000 | X17: ='Operations plan'!$C$28 -> 6790000 | Y17: ='Operations plan'!$C$28 -> 6790000 | ... BA17: ='Operations plan'!$C$28 -> 6790000
C18: E-Bike | J18: ='Operations plan'!$C$29 -> 17990000 | K18: ='Operations plan'!$C$29 -> 17990000 | L18: ='Operations plan'!$C$29 -> 17990000 | M18: ='Operations plan'!$C$29 -> 17990000 | N18: ='Operations plan'!$C$29 -> 17990000 | O18: ='Operations plan'!$C$29 -> 17990000 | P18: ='Operations plan'!$C$29 -> 17990000 | R18: ='Operations plan'!$C$29 -> 17990000 | S18: ='Operations plan'!$C$29 -> 17990000 | T18: ='Operations plan'!$C$29 -> 17990000 | U18: ='Operations plan'!$C$29 -> 17990000 | V18: ='Operations plan'!$C$29 -> 17990000 | W18: ='Operations plan'!$C$29 -> 17990000 | X18: ='Operations plan'!$C$29 -> 17990000 | Y18: ='Operations plan'!$C$29 -> 17990000 | ... BA18: ='Operations plan'!$C$29 -> 17990000
A19: Sale vol. | B19: product | C19: Standard | J19: ='Operations plan'!J7+'Operations plan'!J17 -> 1200 | K19: ='Operations plan'!K7+'Operations plan'!K17 -> 1200 | L19: ='Operations plan'!L7+'Operations plan'!L17 -> 1350 | M19: ='Operations plan'!M7+'Operations plan'!M17 -> 1350 | N19: ='Operations plan'!N7+'Operations plan'!N17 -> 1415 | O19: ='Operations plan'!O7+'Operations plan'!O17 -> 1415 | P19: ='Operations plan'!P7+'Operations plan'!P17 -> 1415 | R19: ='Operations plan'!R7+'Operations plan'!R17 -> 1204 | S19: ='Operations plan'!S7+'Operations plan'!S17 -> 1204 | T19: ='Operations plan'!T7+'Operations plan'!T17 -> 1204 | U19: =('Operations plan'!U7+'Operations plan'!U17)/2 -> 738 | V19: =('Operations plan'!U7+'Operations plan'!U17)/2 -> 738 | W19: =('Operations plan'!V7+'Operations plan'!V17)/2 -> 738 | X19: =('Operations plan'!V7+'Operations plan'!V17)/2 -> 738 | Y19: =('Operations plan'!W7+'Operations plan'!W17)/2 -> 738 | Z19: =('Operations plan'!W7+'Operations plan'!W17)/2 -> 738 | AA19: ='Operations plan'!X7+'Operations plan'!X17 -> 1532 | AB19: ='Operations plan'!Y7+'Operations plan'!Y17 -> 1532 | AC19: ='Operations plan'!Z7+'Operations plan'!Z17 -> 1532 | AD19: =('Operations plan'!AA7+'Operations plan'!AA17)/2 -> 798.5 | AE19: =('Operations plan'!AA7+'Operations plan'!AA17)/2 -> 798.5 | AF19: =('Operations plan'!AB7+'Operations plan'!AB17)/2 -> 801 | AG19: =('Operations plan'!AB7+'Operations plan'!AB17)/2 -> 801 | AH19: =('Operations plan'!AC7+'Operations plan'!AC17)/2 -> 803.5 | AI19: =('Operations plan'!AC7+'Operations plan'!AC17)/2 -> 803.5 | AJ19: ='Operations plan'!AE7+'Operations plan'!AE17 -> 1391 | AK19: ='Operations plan'!AF7+'Operations plan'!AF17 -> 1391 | AL19: ='Operations plan'!AG7+'Operations plan'!AG17 -> 1391 | AM19: ='Operations plan'!AH7+'Operations plan'!AH17 -> 1547 | AN19: =AM19 -> 1547 | AO19: ='Operations plan'!AI7+'Operations plan'!AI17 -> 1547 | AP19: =AO19 -> 1547 | AQ19: =('Operations plan'!AJ7+'Operations plan'!AJ17)/2 -> 773.5 | AR19: =AQ19 -> 773.5 | AS19: ='Operations plan'!AK7+'Operations plan'!AK17 -> 1598 | AT19: ='Operations plan'!AL7+'Operations plan'!AL17 -> 1598 | AU19: ='Operations plan'!AM7+'Operations plan'!AM17 -> 1598 | AV19: =('Operations plan'!AN7+'Operations plan'!AN17)/2 -> 838 | AW19: =AV19 -> 838 | AX19: =('Operations plan'!AO7+'Operations plan'!AO17)/2 -> 840.5 | AY19: =AX19 -> 840.5 | AZ19: =('Operations plan'!AP7+'Operations plan'!AP17)/2 -> 843 | BA19: =AZ19 -> 843
B20: product | C20: E-Bike | J20: ='Operations plan'!J8+'Operations plan'!J18 -> 0 | K20: ='Operations plan'!K8+'Operations plan'!K18 -> 0 | L20: ='Operations plan'!L8+'Operations plan'!L18 -> 0 | M20: ='Operations plan'!M8+'Operations plan'!M18 -> 0 | N20: ='Operations plan'!N8+'Operations plan'!N18 -> 0 | O20: ='Operations plan'!O8+'Operations plan'!O18 -> 0 | P20: ='Operations plan'!P8+'Operations plan'!P18 -> 0 | R20: ='Operations plan'!R8+'Operations plan'!R18 -> 0 | S20: ='Operations plan'!S8+'Operations plan'!S18 -> 0 | T20: ='Operations plan'!T8+'Operations plan'!T18 -> 0 | U20: =('Operations plan'!U8+'Operations plan'!U18)/2 -> 0 | V20: =('Operations plan'!U8+'Operations plan'!U18)/2 -> 0 | W20: =('Operations plan'!V8+'Operations plan'!V18)/2 -> 0 | X20: =('Operations plan'!V8+'Operations plan'!V18)/2 -> 0 | Y20: =('Operations plan'!W8+'Operations plan'!W18)/2 -> 0 | Z20: =('Operations plan'!W8+'Operations plan'!W18)/2 -> 0 | AA20: ='Operations plan'!X8+'Operations plan'!X18 -> 0 | AB20: ='Operations plan'!Y8+'Operations plan'!Y18 -> 0 | AC20: ='Operations plan'!Z8+'Operations plan'!Z18 -> 0 | AD20: =('Operations plan'!AA8+'Operations plan'!AA18)/2 -> 0 | AE20: =('Operations plan'!AA8+'Operations plan'!AA18)/2 -> 0 | AF20: =('Operations plan'!AB8+'Operations plan'!AB18)/2 -> 150 | AG20: =('Operations plan'!AB8+'Operations plan'!AB18)/2 -> 150 | AH20: =('Operations plan'!AC8+'Operations plan'!AC18)/2 -> 150 | AI20: =('Operations plan'!AC8+'Operations plan'!AC18)/2 -> 150 | AJ20: ='Operations plan'!AE8+'Operations plan'!AE18 -> 260 | AK20: ='Operations plan'!AF8+'Operations plan'!AF18 -> 250 | AL20: ='Operations plan'!AG8+'Operations plan'!AG18 -> 250 | AM20: ='Operations plan'!AH8+'Operations plan'!AH18 -> 415 | AN20: =AM20 -> 415 | AO20: ='Operations plan'!AI8+'Operations plan'!AI18 -> 415 | AP20: =AO20 -> 415 | AQ20: =('Operations plan'!AJ8+'Operations plan'!AJ18)/2 -> 207.5 | AR20: =AQ20 -> 207.5 | AS20: ='Operations plan'!AK8+'Operations plan'!AK18 -> 444 | AT20: ='Operations plan'!AL8+'Operations plan'!AL18 -> 444 | AU20: ='Operations plan'!AM8+'Operations plan'!AM18 -> 474 | AV20: =('Operations plan'!AN8+'Operations plan'!AN18)/2 -> 238.5 | AW20: =AV20 -> 238.5 | AX20: =('Operations plan'!AO8+'Operations plan'!AO18)/2 -> 240 | AY20: =AX20 -> 240 | AZ20: =('Operations plan'!AP8+'Operations plan'!AP18)/2 -> 241.5 | BA20: =AZ20 -> 241.5
A21: In-app promotions | U21: =5000000/4 -> 1250000 | V21: =5000000/4 -> 1250000 | W21: =5000000/4 -> 1250000 | X21: =5000000/4 -> 1250000
A22: Loyalty membership discounts | L22: 5000000 | M22: 5000000 | N22: 5000000 | O22: 5000000 | P22: 5000000 | R22: 5000000 | S22: 5000000 | T22: 5000000 | U22: =5000000/2 -> 2500000 | V22: =5000000/2 -> 2500000 | W22: =5000000/2 -> 2500000 | X22: =5000000/2 -> 2500000 | Y22: =5000000/2 -> 2500000 | Z22: =5000000/2 -> 2500000 | AA22: 5000000 | AB22: 5000000 | AC22: 5000000 | AD22: =5000000/2 -> 2500000 | AE22: =5000000/2 -> 2500000 | AF22: =5000000/2 -> 2500000 | AG22: =5000000/2 -> 2500000 | AH22: =5000000/2 -> 2500000 | AI22: =5000000/2 -> 2500000 | AJ22: 5000000 | AK22: 5000000 | AL22: 5000000 | AM22: =5000000/2 -> 2500000 | AN22: =5000000/2 -> 2500000 | AO22: =5000000/2 -> 2500000 | AP22: =5000000/2 -> 2500000 | AQ22: =5000000/2 -> 2500000 | AR22: =5000000/2 -> 2500000 | AS22: 5000000 | AT22: 5000000 | AU22: 5000000 | AV22: =5000000/2 -> 2500000 | AW22: =5000000/2 -> 2500000 | AX22: =5000000/2 -> 2500000 | AY22: =5000000/2 -> 2500000 | AZ22: =5000000/2 -> 2500000 | BA22: =5000000/2 -> 2500000
A23: Digital Marketing | E23: =SUM(E24:E28) -> 61250000 | F23: =SUM(F24:F28) -> 61250000 | G23: =SUM(G24:G28) -> 61250000 | H23: =SUM(H24:H28) -> 58750000 | I23: =SUM(I24:I28) -> 58750000 | J23: =SUM(J24:J28) -> 58750000 | K23: =SUM(K24:K28) -> 58750000 | L23: =SUM(L24:L28) -> 133750000 | ... P23: =SUM(P24:P28) -> 123750000 | R23: =SUM(R24:R28) -> 56750000 | S23: =SUM(S24:S28) -> 56750000 | T23: =SUM(T24:T28) -> 56750000 | U23: =SUM(U24:U28) -> 21125000 | V23: =SUM(V24:V28) -> 21125000 | W23: =SUM(W24:W28) -> 33000000 | X23: =SUM(X24:X28) -> 33000000 | Y23: =SUM(Y24:Y28) -> 33000000 | ... BA23: =SUM(BA24:BA28) -> 80500000
A24: Digital Ads | E24: 30000000 | F24: 30000000 | G24: 30000000 | H24: 30000000 | I24: 30000000 | J24: 30000000 | K24: 30000000 | L24: 100000000 | M24: 30000000 | N24: 30000000 | O24: 100000000 | P24: 100000000 | R24: 30000000 | S24: 30000000 | T24: 30000000 | AA24: 30000000 | AB24: 30000000 | AC24: 30000000 | AD24: 30000000 | AE24: =100000000/2 -> 50000000 | AF24: =100000000/2 -> 50000000 | AG24: =100000000/2 -> 50000000 | AH24: =100000000/2 -> 50000000 | AI24: =100000000/2 -> 50000000 | AJ24: 30000000 | AK24: 30000000 | AL24: 30000000 | AM24: =100000000/2 -> 50000000 | AN24: =100000000/2 -> 50000000 | AO24: =100000000/2 -> 50000000 | AP24: =100000000/2 -> 50000000 | AQ24: =100000000/2 -> 50000000 | AR24: =100000000/2 -> 50000000 | AS24: 30000000 | AT24: 30000000 | AU24: 30000000 | AV24: =100000000/2 -> 50000000 | AW24: =100000000/2 -> 50000000 | AX24: =100000000/2 -> 50000000 | AY24: =100000000/2 -> 50000000 | AZ24: =100000000/2 -> 50000000 | BA24: =100000000/2 -> 50000000
A25: Website | E25: 15000000 | F25: 15000000 | G25: 15000000 | H25: 12500000 | I25: 12500000 | J25: 12500000 | K25: 12500000 | L25: 12500000 | M25: 12500000 | N25: 12500000 | O25: 12500000 | P25: 12500000 | R25: 12500000 | S25: 12500000 | T25: 12500000 | U25: =25000000/2 -> 12500000 | V25: 12500000 | W25: 12500000 | X25: 12500000 | Y25: 12500000 | Z25: 12500000 | AA25: 12500000 | AB25: 12500000 | AC25: 12500000 | AD25: =25000000/2 -> 12500000 | AE25: 12500000 | AF25: 12500000 | AG25: 12500000 | AH25: 12500000 | AI25: 12500000 | AJ25: 12500000 | AK25: 12500000 | AL25: 12500000 | AM25: =25000000/2 -> 12500000 | AN25: 12500000 | AO25: 12500000 | AP25: 12500000 | AQ25: 12500000 | AR25: 12500000 | AS25: 12500000 | AT25: 12500000 | AU25: 12500000 | AV25: =25000000/2 -> 12500000 | AW25: 12500000 | AX25: 12500000 | AY25: 12500000 | AZ25: 12500000 | BA25: 12500000
A26: Email Marketing | E26: 5000000 | F26: 5000000 | G26: 5000000 | H26: 5000000 | I26: 5000000 | J26: 5000000 | K26: =J26 -> 5000000 | L26: 10000000 | M26: 5000000 | R26: 3000000 | S26: 3000000 | T26: 3000000 | U26: 3000000 | V26: 3000000 | W26: 3000000 | X26: 3000000 | Y26: 3000000 | Z26: 3000000 | AA26: 3000000 | AB26: 3000000 | AC26: 3000000 | AD26: 3000000 | AE26: 3000000 | AF26: 3000000 | AG26: 3000000 | AH26: 3000000 | AI26: 3000000 | AJ26: 3000000 | AK26: 3000000 | AL26: 3000000 | AM26: 3000000 | AN26: 3000000 | AO26: 3000000 | AP26: 3000000 | AQ26: 3000000 | AR26: 3000000 | AS26: 3000000 | AT26: 3000000 | AU26: 3000000 | AV26: 3000000 | AW26: 3000000 | AX26: 3000000 | AY26: 3000000 | AZ26: 3000000 | BA26: 3000000
A27: SEO | E27: 5000000 | F27: 5000000 | G27: 5000000 | H27: 5000000 | I27: 5000000 | J27: 5000000 | K27: 5000000 | L27: 5000000 | M27: 5000000 | N27: 5000000 | O27: 5000000 | P27: 5000000 | R27: 5000000 | S27: 5000000 | T27: 5000000 | U27: =5000000/2 -> 2500000 | V27: =5000000/2 -> 2500000 | W27: =5000000/2 -> 2500000 | X27: =5000000/2 -> 2500000 | Y27: =5000000/2 -> 2500000 | Z27: =5000000/2 -> 2500000 | AA27: 5000000 | AB27: 5000000 | AC27: 5000000 | AD27: =5000000/2 -> 2500000 | AE27: =5000000/2 -> 2500000 | AF27: =5000000/2 -> 2500000 | AG27: =5000000/2 -> 2500000 | AH27: =5000000/2 -> 2500000 | AI27: =5000000/2 -> 2500000 | AJ27: 5000000 | AK27: 5000000 | AL27: 5000000 | AM27: =5000000/2 -> 2500000 | AN27: =5000000/2 -> 2500000 | AO27: =5000000/2 -> 2500000 | AP27: =5000000/2 -> 2500000 | AQ27: =5000000/2 -> 2500000 | AR27: =5000000/2 -> 2500000 | AS27: 5000000 | AT27: 5000000 | AU27: 5000000 | AV27: =5000000/2 -> 2500000 | AW27: =5000000/2 -> 2500000 | AX27: =5000000/2 -> 2500000 | AY27: =5000000/2 -> 2500000 | AZ27: =5000000/2 -> 2500000 | BA27: =5000000/2 -> 2500000
A28: App Development | E28: =100000000/16 -> 6250000 | F28: =E28 -> 6250000 | G28: =E28 -> 6250000 | H28: =G28 -> 6250000 | I28: =H28 -> 6250000 | J28: =I28 -> 6250000 | K28: =J28 -> 6250000 | L28: =K28 -> 6250000 | M28: =L28 -> 6250000 | N28: =M28 -> 6250000 | O28: =N28 -> 6250000 | P28: =O28 -> 6250000 | R28: =P28 -> 6250000 | S28: =R28 -> 6250000 | T28: =S28 -> 6250000 | U28: =T28/2 -> 3125000 | V28: =U28 -> 3125000 | W28: =30000000/2 -> 15000000 | X28: =W28 -> 15000000 | Y28: =X28 -> 15000000 | Z28: =Y28 -> 15000000 | AA28: 25000000 | AB28: 25000000 | AC28: 25000000 | AD28: =25000000/2 -> 12500000 | AE28: =25000000/2 -> 12500000 | AF28: =25000000/2 -> 12500000 | AG28: =25000000/2 -> 12500000 | AH28: =25000000/2 -> 12500000 | AI28: =25000000/2 -> 12500000 | AJ28: 25000000 | AK28: 25000000 | AL28: 25000000 | AM28: =25000000/2 -> 12500000 | AN28: =25000000/2 -> 12500000 | AO28: =25000000/2 -> 12500000 | AP28: =25000000/2 -> 12500000 | AQ28: =25000000/2 -> 12500000 | AR28: =25000000/2 -> 12500000 | AS28: 25000000 | AT28: 25000000 | AU28: 25000000 | AV28: =25000000/2 -> 12500000 | AW28: =25000000/2 -> 12500000 | AX28: =25000000/2 -> 12500000 | AY28: =25000000/2 -> 12500000 | AZ28: =25000000/2 -> 12500000 | BA28: =25000000/2 -> 12500000
A29: Viral video | H29: 30000000 | I29: 30000000 | J29: 30000000
A30: Trade Marketing | J30: =J$31*('Operations plan'!$C$38*'Operations plan'!J17+'Operations plan'!$C$39*'Operations plan'!J18) -> 244440000 | K30: =K$31*('Operations plan'!$C$38*'Operations plan'!K17+'Operations plan'!$C$39*'Operations plan'!K18) -> 244440000 | L30: =L$31*('Operations plan'!$C$38*'Operations plan'!L17+'Operations plan'!$C$39*'Operations plan'!L18) -> 0 | M30: =M$31*('Operations plan'!$C$38*'Operations plan'!M17+'Operations plan'!$C$39*'Operations plan'!M18) -> 0 | N30: =N$31*('Operations plan'!$C$38*'Operations plan'!N17+'Operations plan'!$C$39*'Operations plan'!N18) -> 179256000 | O30: =O$31*('Operations plan'!$C$38*'Operations plan'!O17+'Operations plan'!$C$39*'Operations plan'!O18) -> 537768000 | P30: =P$31*('Operations plan'!$C$38*'Operations plan'!P17+'Operations plan'!$C$39*'Operations plan'!P18) -> 537768000 | R30: =R$31*('Operations plan'!$C$38*'Operations plan'!Q17+'Operations plan'!$C$39*'Operations plan'!Q18) -> 0 | S30: =S$31*('Operations plan'!$C$38*'Operations plan'!R17+'Operations plan'!$C$39*'Operations plan'!R18) -> 232218000 | T30: =T$31*('Operations plan'!$C$38*'Operations plan'!S17+'Operations plan'!$C$39*'Operations plan'!S18) -> 0 | U30: =(U$31*('Operations plan'!$C$38*'Operations plan'!T17+'Operations plan'!$C$39*'Operations plan'!T18))/2 -> 0 | V30: =(V$31*('Operations plan'!$C$38*'Operations plan'!T17+'Operations plan'!$C$39*'Operations plan'!T18))/2 -> 0 | W30: =(W$31*('Operations plan'!$C$38*'Operations plan'!V17+'Operations plan'!$C$39*'Operations plan'!V18))/2 -> 0 | X30: =(X$31*('Operations plan'!$C$38*'Operations plan'!V17+'Operations plan'!$C$39*'Operations plan'!V18))/2 -> 0 | Y30: =(Y$31*('Operations plan'!$C$38*'Operations plan'!W17+'Operations plan'!$C$39*'Operations plan'!W18))/2 -> 140553000 | Z30: =(Z$31*('Operations plan'!$C$38*'Operations plan'!W17+'Operations plan'!$C$39*'Operations plan'!W18))/2 -> 140553000 | AA30: =AA$31*('Operations plan'!$C$38*'Operations plan'!X17+'Operations plan'!$C$39*'Operations plan'!X18) -> 293328000 | AB30: =AB$31*('Operations plan'!$C$38*'Operations plan'!Y17+'Operations plan'!$C$39*'Operations plan'!Y18) -> 0 | AC30: =AC$31*('Operations plan'!$C$38*'Operations plan'!Z17+'Operations plan'!$C$39*'Operations plan'!Z18) -> 0 | AD30: =(AD$31*('Operations plan'!$C$38*'Operations plan'!AA17+'Operations plan'!$C$39*'Operations plan'!AA18))/2 -> 101850000 | AE30: =AD30 -> 101850000 | AF30: =(AF$31*('Operations plan'!$C$38*'Operations plan'!AB17+'Operations plan'!$C$39*'Operations plan'!AB18))/2 -> 467460000 | AG30: =AF30 -> 467460000 | AH30: =(AH$31*('Operations plan'!$C$38*'Operations plan'!AC17+'Operations plan'!$C$39*'Operations plan'!AC18))/2 -> 467460000 | AI30: =(AH$31*('Operations plan'!$C$38*'Operations plan'!AC17+'Operations plan'!$C$39*'Operations plan'!AC18))/2 -> 467460000 | AJ30: =AJ$31*('Operations plan'!$C$38*'Operations plan'!AE17+'Operations plan'!$C$39*'Operations plan'!AE18) -> 382221000 | AK30: =AK$31*('Operations plan'!$C$38*'Operations plan'!AF17+'Operations plan'!$C$39*'Operations plan'!AF18) -> 382221000 | AL30: =AL$31*('Operations plan'!$C$38*'Operations plan'!AG17+'Operations plan'!$C$39*'Operations plan'!AG18) -> 0 | AM30: =(AM$31*('Operations plan'!$C$38*'Operations plan'!AH17+'Operations plan'!$C$39*'Operations plan'!AH18))/2 -> 0 | AN30: =(AN$31*('Operations plan'!$C$38*'Operations plan'!AH17+'Operations plan'!$C$39*'Operations plan'!AH18))/2 -> 0 | AO30: =(AO$31*('Operations plan'!$C$38*'Operations plan'!AI17+'Operations plan'!$C$39*'Operations plan'!AI18))/2 -> 0 | AP30: =(AP$31*('Operations plan'!$C$38*'Operations plan'!AI17+'Operations plan'!$C$39*'Operations plan'!AI18))/2 -> 0 | AQ30: =(AQ$31*('Operations plan'!$C$38*'Operations plan'!AJ17+'Operations plan'!$C$39*'Operations plan'!AJ18))/2 -> 243810000 | AR30: =(AQ$31*('Operations plan'!$C$38*'Operations plan'!AJ17+'Operations plan'!$C$39*'Operations plan'!AJ18))/2 -> 243810000 | AS30: =(AS$31*('Operations plan'!$C$38*'Operations plan'!AK17+'Operations plan'!$C$39*'Operations plan'!AK18))/2 -> 258016500 | AT30: =(AT$31*('Operations plan'!$C$38*'Operations plan'!AL17+'Operations plan'!$C$39*'Operations plan'!AL18))/2 -> 0 | AU30: =(AU$31*('Operations plan'!$C$38*'Operations plan'!AM17+'Operations plan'!$C$39*'Operations plan'!AM18))/2 -> 0 | AV30: =(AV$31*('Operations plan'!$C$38*'Operations plan'!AN17+'Operations plan'!$C$39*'Operations plan'!AN18))/2 -> 181482000 | AW30: =(AW$31*('Operations plan'!$C$38*'Operations plan'!AN17+'Operations plan'!$C$39*'Operations plan'!AN18))/2 -> 181482000 | AX30: =(AX$31*('Operations plan'!$C$38*'Operations plan'!AO17+'Operations plan'!$C$39*'Operations plan'!AO18))/2 -> 544446000 | AY30: =(AY$31*('Operations plan'!$C$38*'Operations plan'!AO17+'Operations plan'!$C$39*'Operations plan'!AO18))/2 -> 544446000 | AZ30: =(AZ$31*('Operations plan'!$C$38*'Operations plan'!AP17+'Operations plan'!$C$39*'Operations plan'!AP18))/2 -> 544446000 | BA30: =(BA$31*('Operations plan'!$C$38*'Operations plan'!AP17+'Operations plan'!$C$39*'Operations plan'!AP18))/2 -> 544446000
A31: Trade Discount | B31: % | J31: 0.03 | K31: 0.03 | L31: 0 | M31: 0 | N31: 0.02 | O31: 0.06 | P31: 0.06 | R31: 0.03 | S31: 0.03 | T31: 0 | U31: 0 | V31: 0 | W31: 0 | X31: 0 | Y31: 0.03 | Z31: 0.03 | AA31: 0.03 | AB31: 0 | AC31: 0 | AD31: 0.02 | AE31: 0.02 | AF31: 0.06 | AG31: 0.06 | AH31: 0.06 | AI31: 0.06 | AJ31: 0.03 | AK31: 0.03 | AL31: 0 | AM31: 0 | AN31: 0 | AO31: 0 | AP31: 0 | AQ31: 0.03 | AR31: 0.03 | AS31: 0.03 | AT31: 0 | AU31: 0 | AV31: 0.02 | AW31: 0.02 | AX31: 0.06 | AY31: 0.06 | AZ31: 0.06 | BA31: 0.06
A32: M&S Expenses | E32: =E30+E23+E11+E4 -> 61250000 | F32: =F30+F23+F11+F4 -> 61250000 | G32: =G30+G23+G11+G4 -> 61250000 | H32: =H30+H23+H11+H4 -> 58750000 | I32: =I30+I23+I11+I4 -> 69750000 | J32: =J30+J23+J11+J4 -> 323190000 | K32: =K30+K23+K11+K4 -> 311690000 | L32: =L30+L23+L11+L4 -> 160750000 | ... P32: =P30+P23+P11+P4 -> 675018000 | R32: =R30+R23+R11+R4 -> 150001600 | S32: =S30+S23+S11+S4 -> 382219600 | T32: =T30+T23+T11+T4 -> 151001600 | U32: =U30+U23+U11+U4 -> 28625000 | V32: =V30+V23+V11+V4 -> 28625000 | W32: =W30+W23+W11+W4 -> 142720400 | X32: =X30+X23+X11+X4 -> 142720400 | Y32: =Y30+Y23+Y11+Y4 -> 179803000 | ... BA32: =BA30+BA23+BA11+BA4 -> 631696000
A35: Marketing Costs (classified by Fixed Costs and Variable Costs) | E35: 2025 | R35: 2026 | AE35: 2027
E36: Q1 | H36: Q2 | K36: Q3 | N36: Q4 | R36: Q1 | U36: Q2 | X36: Q3 | AA36: Q4 | AE36: Q1 | AH36: Q2 | AK36: Q3 | AN36: Q4
E37: 1 | F37: 2 | G37: 3 | H37: 4 | I37: 5 | J37: 6 | K37: 7 | L37: 8 | M37: 9 | N37: 10 | O37: 11 | P37: 12 | R37: 1 | S37: 2 | T37: 3 | U37: 4 | V37: 5 | W37: 6 | X37: 7 | Y37: 8 | Z37: 9 | AA37: 10 | AB37: 11 | AC37: 12 | AE37: 1 | AF37: 2 | AG37: 3 | AH37: 4 | AI37: 5 | AJ37: 6 | AK37: 7 | AL37: 8 | AM37: 9 | AN37: 10 | AO37: 11 | AP37: 12
A38: Fix | E38: =E4+E25+E28+E29+E27 -> 26250000 | F38: =F4+F25+F28+F29+F27 -> 26250000 | G38: =G4+G25+G28+G29+G27 -> 26250000 | H38: =H4+H25+H28+H29+H27 -> 53750000 | I38: =I4+I25+I28+I29+I27 -> 64750000 | J38: =J4+J25+J28+J29+J27 -> 73750000 | K38: =K4+K25+K28+K29+K27 -> 32250000 | L38: =L4+L25+L28+L29+L27 -> 45750000 | ... T38: =T4+T25+T28+T29+T27 -> 31250000 | U38: =U4+U25+U28+U29+U27+V4+V25+V28+V29+V27 -> 43750000 | V38: =W4+W25+W28+W29+W27+X4+X25+X28+X29+X27 -> 71500000 | W38: =Y4+Y25+Y28+Y29+Y27+Z4+Z25+Z28+Z29+Z27 -> 67500000 | X38: =AA4+AA25+AA28+AA29+AA27 -> 49000000 | Y38: =AB4+AB25+AB28+AB29+AB27 -> 50000000 | Z38: =AC4+AC25+AC28+AC29+AC27 -> 50000000 | AA38: =AD4+AD25+AD28+AD29+AD27+AE4+AE25+AE28+AE29+AE27 -> 63500000 | AB38: =AF4+AF25+AF28+AF29+AF27+AG4+AG25+AG28+AG29+AG27 -> 87000000 | AC38: =AH4+AH25+AH28+AH29+AH27+AI4+AI25+AI28+AI29+AI27 -> 66500000 | AE38: =AJ4+AJ25+AJ28+AJ29+AJ27 -> 74500000 | AF38: =AK4+AK25+AK28+AK29+AK27 -> 49000000 | AG38: =AL4+AL25+AL28+AL29+AL27 -> 50000000 | AH38: =AM4+AM25+AM28+AM29+AM27+AN4+AN25+AN28+AN29+AN27 -> 62500000 | AI38: =AO4+AO25+AO28+AO29+AO27+AP4+AP25+AP28+AP29+AP27 -> 63500000 | AJ38: =AQ4+AQ25+AQ28+AQ29+AQ27+AR4+AR25+AR28+AR29+AR27 -> 62500000 | AK38: =AS4+AS25+AS28+AS29+AS27 -> 49000000 | AL38: =AT4+AT25+AT28+AT29+AT27 -> 50000000 | AM38: =AU4+AU25+AU28+AU29+AU27 -> 49000000 | AN38: =AV4+AV25+AV28+AV29+AV27+AW4+AW25+AW28+AW29+AW27 -> 61500000 | AO38: =AX4+AX25+AX28+AX29+AX27+AY4+AY25+AY28+AY29+AY27 -> 61500000 | AP38: =AZ4+AZ25+AZ28+AZ29+AZ27+BA4+BA25+BA28+BA29+BA27 -> 63500000
A39: Variable | E39: =E11+E24+E26+E30 -> 35000000 | F39: =F11+F24+F26+F30 -> 35000000 | G39: =G11+G24+G26+G30 -> 35000000 | H39: =H11+H24+H26+H30 -> 35000000 | I39: =I11+I24+I26+I30 -> 35000000 | J39: =J11+J24+J26+J30 -> 279440000 | K39: =K11+K24+K26+K30 -> 279440000 | L39: =L11+L24+L26+L30 -> 115000000 | ... T39: =T11+T24+T26+T30 -> 119751600 | U39: =U40-U38 -> 13500000 | V39: =V40-V38 -> 213940800 | W39: =W40-W38 -> 292106000 | X39: =X40-X38 -> 435350800 | Y39: =Y40-Y38 -> 142022800 | Z39: =Z40-Z38 -> 142022800 | AA39: =AA40-AA38 -> 403136300 | AB39: =AB40-AB38 -> 1371411600 | AC39: =AC40-AC38 -> 1045920000 | AE39: =AE40-AE38 -> 561443900 | AF39: =AF40-AF38 -> 559644900 | AG39: =AG40-AG38 -> 177423900 | AH39: =AH40-AH38 -> 111000000 | AI39: =AI40-AI38 -> 829799200 | AJ39: =AJ40-AJ38 -> 598620000 | AK39: =AK40-AK38 -> 484396300 | AL39: =AL40-AL38 -> 226379800 | ... AP39: =AP40-AP38 -> 1199892000
A40: M&S Expenses | E40: =E32 -> 61250000 | F40: =F32 -> 61250000 | G40: =G32 -> 61250000 | H40: =H32 -> 58750000 | I40: =I32 -> 69750000 | J40: =J32 -> 323190000 | K40: =K32 -> 311690000 | L40: =L32 -> 160750000 | ... T40: =T32 -> 151001600 | U40: =U32+V32 -> 57250000 | V40: =W32+X32 -> 285440800 | W40: =Y32+Z32 -> 359606000 | X40: =AA32 -> 484350800 | Y40: =AB32 -> 192022800 | Z40: =AC32 -> 192022800 | AA40: =AD32+AE32 -> 466636300 | AB40: =AF32+AG32 -> 1458411600 | AC40: =AH32+AI32 -> 1112420000 | AE40: =AJ32 -> 635943900 | AF40: =AK32 -> 608644900 | AG40: =AL32 -> 227423900 | AH40: =AM32+AN32 -> 173500000 | AI40: =AO32+AP32 -> 893299200 | AJ40: =AQ32+AR32 -> 661120000 | AK40: =AS32 -> 533396300 | AL40: =AT32 -> 276379800 | AM40: =AU32 -> 280776800 | AN40: =AV32+AW32 -> 735076700 | AO40: =AX32+AY32 -> 1662375800 | AP40: =AZ32+BA32 -> 1263392000

Sheet Operations plan
E1: 2025 | R1: 2026 | AE1: 2027
E2: Q1 | H2: Q2 | K2: Q3 | N2: Q4 | R2: Q1 | U2: Q2 | X2: Q3 | AA2: Q4 | AE2: Q1 | AH2: Q2 | AK2: Q3 | AN2: Q4
E3: 1 | F3: 2 | G3: 3 | H3: 4 | I3: 5 | J3: 6 | K3: 7 | L3: 8 | M3: 9 | N3: 10 | O3: 11 | P3: 12 | R3: 1 | S3: 2 | T3: 3 | U3: 4 | V3: 5 | W3: 6 | X3: 7 | Y3: 8 | Z3: 9 | AA3: 10 | AB3: 11 | AC3: 12 | AE3: 1 | AF3: 2 | AG3: 3 | AH3: 4 | AI3: 5 | AJ3: 6 | AK3: 7 | AL3: 8 | AM3: 9 | AN3: 10 | AO3: 11 | AP3: 12
A5: A - Sale volume
A6: Store sales estimation | C6: =SUM(C7:C8) -> 140 | E6: =SUM(E7:E8) -> 0 | F6: =SUM(F7:F8) -> 0 | G6: =SUM(G7:G8) -> 0 | H6: =SUM(H7:H8) -> 0 | I6: =SUM(I7:I8) -> 0 | J6: =SUM(J7:J8) -> 0 | K6: =SUM(K7:K8) -> 0 | L6: =SUM(L7:L8) -> 90 | ... P6: =SUM(P7:P8) -> 95 | R6: =SUM(R7:R8) -> 64 | S6: =SUM(S7:S8) -> 64 | T6: =SUM(T7:T8) -> 64 | U6: =SUM(U7:U8) -> 96 | V6: =SUM(V7:V8) -> 96 | W6: =SUM(W7:W8) -> 96 | X6: =SUM(X7:X8) -> 92 | Y6: =SUM(Y7:Y8) -> 92 | ... AC6: =SUM(AC7:AC8) -> 107 | AE6: =SUM(AE7:AE8) -> 121 | AF6: =SUM(AF7:AF8) -> 111 | AG6: =SUM(AG7:AG8) -> 111 | AH6: =SUM(AH7:AH8) -> 162 | AI6: =SUM(AI7:AI8) -> 162 | AJ6: =SUM(AJ7:AJ8) -> 162 | AK6: =SUM(AK7:AK8) -> 152 | AL6: =SUM(AL7:AL8) -> 152 | ... AP6: =SUM(AP7:AP8) -> 189
B7: Standard | C7: 90 | D7: =C7 -> 90 | E7: 0 | F7: 0 | G7: 0 | H7: 0 | I7: 0 | J7: 0 | K7: 0 | L7: 90 | M7: 90 | N7: 95 | O7: 95 | P7: 95 | R7: 64 | S7: 64 | T7: 64 | U7: 96 | V7: 96 | W7: 96 | X7: 92 | Y7: 92 | Z7: 92 | AA7: 97 | AB7: 102 | AC7: 107 | AE7: 71 | AF7: 71 | AG7: 71 | AH7: 107 | AI7: 107 | AJ7: 107 | AK7: 98 | AL7: 98 | AM7: 98 | AN7: 116 | AO7: 121 | AP7: 126
B8: E-bike | C8: 50 | D8: =C8 -> 50 | E8: 0 | F8: 0 | G8: 0 | H8: 0 | I8: 0 | J8: 0 | K8: 0 | L8: 0 | M8: 0 | N8: 0 | O8: 0 | P8: 0 | R8: 0 | S8: 0 | T8: 0 | U8: 0 | V8: 0 | W8: 0 | X8: 0 | Y8: 0 | Z8: 0 | AA8: 0 | AB8: 0 | AC8: 0 | AE8: 50 | AF8: 40 | AG8: 40 | AH8: 55 | AI8: 55 | AJ8: 55 | AK8: 54 | AL8: 54 | AM8: 54 | AN8: 57 | AO8: 60 | AP8: 63
A9: Store vol. - Accumulating %
A10: Chỉ để xem thôi | B10: Standard | E10: =D10+E13 -> -1 | F10: =E10+F13 -> -1 | G10: =F10+G13 -> -1 | H10: =G10+H13 -> -1 | I10: =H10+I13 -> -1 | J10: =I10+J13 -> -1 | K10: =J10+K13 -> -1 | L10: =K10+L13 -> 0 | ... AP10: =AO10+AP13 -> 0.35
B11: E-bike | E11: =D11+E14 -> -1 | F11: =E11+F14 -> -1 | G11: =F11+G14 -> -1 | H11: =G11+H14 -> -1 | I11: =H11+I14 -> -1 | J11: =I11+J14 -> -1 | K11: =J11+K14 -> -1 | L11: =K11+L14 -> -1 | ... AP11: =AO11+AP14 -> 0.23
A12: Store sales adjustment
A13: Dự kiến tăng giảm store sale | B13: Standard | E13: -1 | F13: 0 | G13: 0 | H13: 0 | I13: 0 | J13: 0 | K13: 0 | L13: 1 | M13: 0 | N13: 0.05 | O13: 0 | P13: 0 | R13: -0.35 | S13: 0 | T13: 0 | U13: 0.35 | V13: 0 | W13: 0 | X13: -0.05 | Y13: 0 | Z13: 0 | AA13: 0.05 | AB13: 0.05 | AC13: 0.05 | AE13: -0.4 | AF13: 0 | AG13: 0 | AH13: 0.4 | AI13: 0 | AJ13: 0 | AK13: -0.1 | AL13: 0 | AM13: 0 | AN13: 0.2 | AO13: 0.05 | AP13: 0.05
B14: E-bike | E14: -1 | F14: 0 | G14: 0 | H14: 0 | I14: 0 | J14: 0 | K14: 0 | L14: 0 | M14: 0 | N14: 0 | O14: 0 | P14: 0 | R14: 0 | S14: 0 | T14: 0 | U14: 0 | V14: 0 | W14: 0 | X14: 0 | Y14: 0 | Z14: 0 | AA14: 0 | AB14: 0 | AC14: 0 | AE14: 1 | AF14: -0.2 | AG14: 0 | AH14: 0.3 | AI14: 0 | AJ14: 0 | AK14: -0.02 | AL14: 0 | AM14: 0 | AN14: 0.05 | AO14: 0.05 | AP14: 0.05
A16: Distributor vol. | C16: =SUM(C17:C18) -> 1800 | E16: =SUM(E17:E18) -> 0 | F16: =SUM(F17:F18) -> 0 | G16: =SUM(G17:G18) -> 0 | H16: =SUM(H17:H18) -> 0 | I16: =SUM(I17:I18) -> 0 | J16: =SUM(J17:J18) -> 1200 | K16: =SUM(K17:K18) -> 1200 | L16: =SUM(L17:L18) -> 1260 | ... P16: =SUM(P17:P18) -> 1320 | R16: =SUM(R17:R18) -> 1140 | S16: =SUM(S17:S18) -> 1140 | T16: =SUM(T17:T18) -> 1140 | U16: =SUM(U17:U18) -> 1380 | V16: =SUM(V17:V18) -> 1380 | W16: =SUM(W17:W18) -> 1380 | X16: =SUM(X17:X18) -> 1440 | Y16: =SUM(Y17:Y18) -> 1440 | ... AC16: =SUM(AC17:AC18) -> 1800 | AE16: =SUM(AE17:AE18) -> 1530 | AF16: =SUM(AF17:AF18) -> 1530 | AG16: =SUM(AG17:AG18) -> 1530 | AH16: =SUM(AH17:AH18) -> 1800 | AI16: =SUM(AI17:AI18) -> 1800 | AJ16: =SUM(AJ17:AJ18) -> 1800 | AK16: =SUM(AK17:AK18) -> 1890 | AL16: =SUM(AL17:AL18) -> 1890 | ... AP16: =SUM(AP17:AP18) -> 1980
B17: Standard | C17: 1200 | D17: =C17 -> 1200 | E17: 0 | F17: 0 | G17: 0 | H17: 0 | I17: 0 | J17: 1200 | K17: 1200 | L17: 1260 | M17: 1260 | N17: 1320 | O17: 1320 | P17: 1320 | R17: 1140 | S17: 1140 | T17: 1140 | U17: 1380 | V17: 1380 | W17: 1380 | X17: 1440 | Y17: 1440 | Z17: 1440 | AA17: 1500 | AB17: 1500 | AC17: 1500 | AE17: 1320 | AF17: 1320 | AG17: 1320 | AH17: 1440 | AI17: 1440 | AJ17: 1440 | AK17: 1500 | AL17: 1500 | AM17: 1500 | AN17: 1560 | AO17: 1560 | AP17: 1560
B18: E-bike | C18: 600 | D18: =C18 -> 600 | E18: 0 | F18: 0 | G18: 0 | H18: 0 | I18: 0 | J18: 0 | K18: 0 | L18: 0 | M18: 0 | N18: 0 | O18: 0 | P18: 0 | R18: 0 | S18: 0 | T18: 0 | U18: 0 | V18: 0 | W18: 0 | X18: 0 | Y18: 0 | Z18: 0 | AA18: 0 | AB18: 300 | AC18: 300 | AE18: 210 | AF18: 210 | AG18: 210 | AH18: 360 | AI18: 360 | AJ18: 360 | AK18: 390 | AL18: 390 | AM18: 420 | AN18: 420 | AO18: 420 | AP18: 420
A19: Dis vol. - Accumulating %
B20: Standard | E20: =D20+E23 -> -1 | F20: =E20+F23 -> -1 | G20: =F20+G23 -> -1 | H20: =G20+H23 -> -1 | I20: =H20+I23 -> -1 | J20: =I20+J23 -> 0 | K20: =J20+K23 -> 0 | L20: =K20+L23 -> 0.05 | ... AP20: =AO20+AP23 -> 0.3
B21: E-bike | E21: =D21+E24 -> -1 | F21: =E21+F24 -> -1 | G21: =F21+G24 -> -1 | H21: =G21+H24 -> -1 | I21: =H21+I24 -> -1 | J21: =I21+J24 -> -1 | K21: =J21+K24 -> -1 | L21: =K21+L24 -> -1 | ... AP21: =AO21+AP24 -> -0.3
A22: Dis. vol. adjustment
A23: Dự kiến tăng giảm cung cho phân phối | B23: Standard | E23: -1 | F23: 0 | G23: 0 | H23: 0 | I23: 0 | J23: 1 | K23: 0 | L23: 0.05 | M23: 0 | N23: 0.05 | O23: 0 | P23: 0 | R23: -0.15 | S23: 0 | T23: 0 | U23: 0.2 | V23: 0 | W23: 0 | X23: 0.05 | Y23: 0 | Z23: 0 | AA23: 0.05 | AB23: 0 | AC23: 0 | AE23: -0.15 | AF23: 0 | AG23: 0 | AH23: 0.1 | AI23: 0 | AJ23: 0 | AK23: 0.05 | AL23: 0 | AM23: 0 | AN23: 0.05 | AO23: 0 | AP23: 0
B24: E-bike | E24: -1 | F24: 0 | G24: 0 | H24: 0 | I24: 0 | J24: 0 | K24: 0 | L24: 0 | M24: 0 | N24: 0 | O24: 0 | P24: 0 | R24: 0 | S24: 0 | T24: 0 | U24: 0 | V24: 0 | W24: 0 | X24: 0 | Y24: 0 | Z24: 0 | AA24: 0 | AB24: 0.5 | AC24: 0 | AE24: -0.15 | AF24: 0 | AG24: 0 | AH24: 0.25 | AI24: 0 | AJ24: 0 | AK24: 0.05 | AL24: 0 | AM24: 0.05 | AN24: 0 | AO24: 0 | AP24: 0
A26: B - Pricing (excluding promotion programs)
A27: Store price | C27: Base \ Sale | D27: =SUMPRODUCT(D28:D29,D7:D8) -> 1510600000 | E27: =SUMPRODUCT(E28:E29,E7:E8) -> 0 | F27: =SUMPRODUCT(F28:F29,F7:F8) -> 0 | G27: =SUMPRODUCT(G28:G29,G7:G8) -> 0 | H27: =SUMPRODUCT(H28:H29,H7:H8) -> 0 | I27: =SUMPRODUCT(I28:I29,I7:I8) -> 0 | J27: =SUMPRODUCT(J28:J29,J7:J8) -> 0 | K27: =SUMPRODUCT(K28:K29,K7:K8) -> 0 | ... P27: =SUMPRODUCT(P28:P29,P7:P8) -> 645050000 | R27: =SUMPRODUCT(R28:R29,R7:R8) -> 434560000 | S27: =SUMPRODUCT(S28:S29,S7:S8) -> 434560000 | T27: =SUMPRODUCT(T28:T29,T7:T8) -> 434560000 | U27: =SUMPRODUCT(U28:U29,U7:U8) -> 651840000 | V27: =SUMPRODUCT(V28:V29,V7:V8) -> 651840000 | W27: =SUMPRODUCT(W28:W29,W7:W8) -> 651840000 | X27: =SUMPRODUCT(X28:X29,X7:X8) -> 624680000 | Y27: =SUMPRODUCT(Y28:Y29,Y7:Y8) -> 624680000 | ... AC27: =SUMPRODUCT(AC28:AC29,AC7:AC8) -> 726530000 | AE27: =SUMPRODUCT(AE28:AE29,AE7:AE8) -> 1381590000 | AF27: =SUMPRODUCT(AF28:AF29,AF7:AF8) -> 1201690000 | AG27: =SUMPRODUCT(AG28:AG29,AG7:AG8) -> 1201690000 | AH27: =SUMPRODUCT(AH28:AH29,AH7:AH8) -> 1715980000 | AI27: =SUMPRODUCT(AI28:AI29,AI7:AI8) -> 1715980000 | AJ27: =SUMPRODUCT(AJ28:AJ29,AJ7:AJ8) -> 1715980000 | AK27: =SUMPRODUCT(AK28:AK29,AK7:AK8) -> 1636880000 | AL27: =SUMPRODUCT(AL28:AL29,AL7:AL8) -> 1636880000 | ... AP27: =SUMPRODUCT(AP28:AP29,AP7:AP8) -> 1988910000
B28: Standard | C28: 6790000 | D28: =C28 -> 6790000 | E28: =$C28*(E34)+D28 -> 6790000 | F28: =$C28*(F34)+E28 -> 6790000 | G28: =$C28*(G34)+F28 -> 6790000 | H28: =$C28*(H34)+G28 -> 6790000 | I28: =$C28*(I34)+H28 -> 6790000 | J28: =$C28*(J34)+I28 -> 6790000 | K28: =$C28*(K34)+J28 -> 6790000 | L28: =$C28*(L34)+K28 -> 6790000 | ... P28: =$C28*(P34)+O28 -> 6790000 | R28: =$C28*(R34)+P28 -> 6790000 | S28: =$C28*(S34)+R28 -> 6790000 | T28: =$C28*(T34)+S28 -> 6790000 | U28: =$C28*(U34)+T28 -> 6790000 | V28: =$C28*(V34)+U28 -> 6790000 | W28: =$C28*(W34)+V28 -> 6790000 | X28: =$C28*(X34)+W28 -> 6790000 | Y28: =$C28*(Y34)+X28 -> 6790000 | Z28: =$C28*(Z34)+Y28 -> 6790000 | ... AC28: =$C28*(AC34)+AB28 -> 6790000 | AE28: =$C28*(AE34)+AC28 -> 6790000 | AF28: =$C28*(AF34)+AE28 -> 6790000 | AG28: =$C28*(AG34)+AF28 -> 6790000 | AH28: =$C28*(AH34)+AG28 -> 6790000 | AI28: =$C28*(AI34)+AH28 -> 6790000 | AJ28: =$C28*(AJ34)+AI28 -> 6790000 | AK28: =$C28*(AK34)+AJ28 -> 6790000 | AL28: =$C28*(AL34)+AK28 -> 6790000 | AM28: =$C28*(AM34)+AL28 -> 6790000 | ... AP28: =$C28*(AP34)+AO28 -> 6790000
B29: E-bike | C29: 17990000 | D29: =C29 -> 17990000 | E29: =$C29*(E35)+D29 -> 17990000 | F29: =$C29*(F35)+E29 -> 17990000 | G29: =$C29*(G35)+F29 -> 17990000 | H29: =$C29*(H35)+G29 -> 17990000 | I29: =$C29*(I35)+H29 -> 17990000 | J29: =$C29*(J35)+I29 -> 17990000 | K29: =$C29*(K35)+J29 -> 17990000 | L29: =$C29*(L35)+K29 -> 17990000 | ... P29: =$C29*(P35)+O29 -> 17990000 | R29: =$C29*(R35)+P29 -> 17990000 | S29: =$C29*(S35)+R29 -> 17990000 | T29: =$C29*(T35)+S29 -> 17990000 | U29: =$C29*(U35)+T29 -> 17990000 | V29: =$C29*(V35)+U29 -> 17990000 | W29: =$C29*(W35)+V29 -> 17990000 | X29: =$C29*(X35)+W29 -> 17990000 | Y29: =$C29*(Y35)+X29 -> 17990000 | Z29: =$C29*(Z35)+Y29 -> 17990000 | ... AC29: =$C29*(AC35)+AB29 -> 17990000 | AE29: =$C29*(AE35)+AC29 -> 17990000 | AF29: =$C29*(AF35)+AE29 -> 17990000 | AG29: =$C29*(AG35)+AF29 -> 17990000 | AH29: =$C29*(AH35)+AG29 -> 17990000 | AI29: =$C29*(AI35)+AH29 -> 17990000 | AJ29: =$C29*(AJ35)+AI29 -> 17990000 | AK29: =$C29*(AK35)+AJ29 -> 17990000 | AL29: =$C29*(AL35)+AK29 -> 17990000 | AM29: =$C29*(AM35)+AL29 -> 17990000 | ... AP29: =$C29*(AP35)+AO29 -> 17990000
A30: Store price - Accumulating %
A31: Chỉ để xem thôi | B31: Standard | E31: =D31+E34 -> 0 | F31: =E31+F34 -> 0 | G31: =F31+G34 -> 0 | H31: =G31+H34 -> 0 | I31: =H31+I34 -> 0 | J31: =I31+J34 -> 0 | K31: =J31+K34 -> 0 | L31: =K31+L34 -> 0 | ... AP31: =AO31+AP34 -> 0
B32: E-bike | E32: =D32+E35 -> 0 | F32: =E32+F35 -> 0 | G32: =F32+G35 -> 0 | H32: =G32+H35 -> 0 | I32: =H32+I35 -> 0 | J32: =I32+J35 -> 0 | K32: =J32+K35 -> 0 | L32: =K32+L35 -> 0 | ... AP32: =AO32+AP35 -> 0
A33: Store price adjustment
A34: Dự kiến tăng giảm giá cho store | B34: Standard
B35: E-bike
A37: Dis. price | C37: Base \ Sale | D37: =SUMPRODUCT(D38:D39,D17:D18) -> 18942000000 | E37: =SUMPRODUCT(E38:E39,E17:E18) -> 0 | F37: =SUMPRODUCT(F38:F39,F17:F18) -> 0 | G37: =SUMPRODUCT(G38:G39,G17:G18) -> 0 | H37: =SUMPRODUCT(H38:H39,H17:H18) -> 0 | I37: =SUMPRODUCT(I38:I39,I17:I18) -> 0 | J37: =SUMPRODUCT(J38:J39,J17:J18) -> 7333200000 | K37: =SUMPRODUCT(K38:K39,K17:K18) -> 7333200000 | ... P37: =SUMPRODUCT(P38:P39,P17:P18) -> 8066520000 | R37: =SUMPRODUCT(R38:R39,R17:R18) -> 6966540000 | S37: =SUMPRODUCT(S38:S39,S17:S18) -> 6966540000 | T37: =SUMPRODUCT(T38:T39,T17:T18) -> 6966540000 | U37: =SUMPRODUCT(U38:U39,U17:U18) -> 8433180000 | V37: =SUMPRODUCT(V38:V39,V17:V18) -> 8433180000 | W37: =SUMPRODUCT(W38:W39,W17:W18) -> 8433180000 | X37: =SUMPRODUCT(X38:X39,X17:X18) -> 8799840000 | Y37: =SUMPRODUCT(Y38:Y39,Y17:Y18) -> 8799840000 | ... AC37: =SUMPRODUCT(AC38:AC39,AC17:AC18) -> 14023800000 | AE37: =SUMPRODUCT(AE38:AE39,AE17:AE18) -> 11466630000 | AF37: =SUMPRODUCT(AF38:AF39,AF17:AF18) -> 11466630000 | AG37: =SUMPRODUCT(AG38:AG39,AG17:AG18) -> 11466630000 | AH37: =SUMPRODUCT(AH38:AH39,AH17:AH18) -> 14628600000 | AI37: =SUMPRODUCT(AI38:AI39,AI17:AI18) -> 14628600000 | AJ37: =SUMPRODUCT(AJ38:AJ39,AJ17:AJ18) -> 14628600000 | AK37: =SUMPRODUCT(AK38:AK39,AK17:AK18) -> 15480990000 | AL37: =SUMPRODUCT(AL38:AL39,AL17:AL18) -> 15480990000 | ... AP37: =SUMPRODUCT(AP38:AP39,AP17:AP18) -> 16333380000
B38: Standard | C38: =C28 -> 6790000 | D38: =C38 -> 6790000 | E38: =$C38*(E44)+D38 -> 6111000 | F38: =$C38*(F44)+E38 -> 6111000 | G38: =$C38*(G44)+F38 -> 6111000 | H38: =$C38*(H44)+G38 -> 6111000 | I38: =$C38*(I44)+H38 -> 6111000 | J38: =$C38*(J44)+I38 -> 6111000 | K38: =$C38*(K44)+J38 -> 6111000 | L38: =$C38*(L44)+K38 -> 6111000 | ... P38: =$C38*(P44)+O38 -> 6111000 | R38: =$C38*(R44)+P38 -> 6111000 | S38: =$C38*(S44)+R38 -> 6111000 | T38: =$C38*(T44)+S38 -> 6111000 | U38: =$C38*(U44)+T38 -> 6111000 | V38: =$C38*(V44)+U38 -> 6111000 | W38: =$C38*(W44)+V38 -> 6111000 | X38: =$C38*(X44)+W38 -> 6111000 | Y38: =$C38*(Y44)+X38 -> 6111000 | Z38: =$C38*(Z44)+Y38 -> 6111000 | ... AC38: =$C38*(AC44)+AB38 -> 6111000 | AE38: =$C38*(AE44)+AC38 -> 6111000 | AF38: =$C38*(AF44)+AE38 -> 6111000 | AG38: =$C38*(AG44)+AF38 -> 6111000 | AH38: =$C38*(AH44)+AG38 -> 6111000 | AI38: =$C38*(AI44)+AH38 -> 6111000 | AJ38: =$C38*(AJ44)+AI38 -> 6111000 | AK38: =$C38*(AK44)+AJ38 -> 6111000 | AL38: =$C38*(AL44)+AK38 -> 6111000 | AM38: =$C38*(AM44)+AL38 -> 6111000 | ... AP38: =$C38*(AP44)+AO38 -> 6111000
B39: E-bike | C39: =C29 -> 17990000 | D39: =C39 -> 17990000 | E39: =$C39*(E45)+D39 -> 16191000 | F39: =$C39*(F45)+E39 -> 16191000 | G39: =$C39*(G45)+F39 -> 16191000 | H39: =$C39*(H45)+G39 -> 16191000 | I39: =$C39*(I45)+H39 -> 16191000 | J39: =$C39*(J45)+I39 -> 16191000 | K39: =$C39*(K45)+J39 -> 16191000 | L39: =$C39*(L45)+K39 -> 16191000 | ... P39: =$C39*(P45)+O39 -> 16191000 | R39: =$C39*(R45)+P39 -> 16191000 | S39: =$C39*(S45)+R39 -> 16191000 | T39: =$C39*(T45)+S39 -> 16191000 | U39: =$C39*(U45)+T39 -> 16191000 | V39: =$C39*(V45)+U39 -> 16191000 | W39: =$C39*(W45)+V39 -> 16191000 | X39: =$C39*(X45)+W39 -> 16191000 | Y39: =$C39*(Y45)+X39 -> 16191000 | Z39: =$C39*(Z45)+Y39 -> 16191000 | ... AC39: =$C39*(AC45)+AB39 -> 16191000 | AE39: =$C39*(AE45)+AC39 -> 16191000 | AF39: =$C39*(AF45)+AE39 -> 16191000 | AG39: =$C39*(AG45)+AF39 -> 16191000 | AH39: =$C39*(AH45)+AG39 -> 16191000 | AI39: =$C39*(AI45)+AH39 -> 16191000 | AJ39: =$C39*(AJ45)+AI39 -> 16191000 | AK39: =$C39*(AK45)+AJ39 -> 16191000 | AL39: =$C39*(AL45)+AK39 -> 16191000 | AM39: =$C39*(AM45)+AL39 -> 16191000 | ... AP39: =$C39*(AP45)+AO39 -> 16191000
A40: Dis. price - Accumulating %
A41: Chỉ để xem thôi | B41: Standard | E41: =D41+E44 -> -0.1 | F41: =E41+F44 -> -0.1 | G41: =F41+G44 -> -0.1 | H41: =G41+H44 -> -0.1 | I41: =H41+I44 -> -0.1 | J41: =I41+J44 -> -0.1 | K41: =J41+K44 -> -0.1 | L41: =K41+L44 -> -0.1 | ... AP41: =AO41+AP44 -> -0.1
B42: E-bike | E42: =D42+E45 -> -0.1 | F42: =E42+F45 -> -0.1 | G42: =F42+G45 -> -0.1 | H42: =G42+H45 -> -0.1 | I42: =H42+I45 -> -0.1 | J42: =I42+J45 -> -0.1 | K42: =J42+K45 -> -0.1 | L42: =K42+L45 -> -0.1 | ... AP42: =AO42+AP45 -> -0.1
A43: Dis. price adjustment
A44: Dự kiến tăng giảm giá cho phân phối | B44: Standard | E44: -0.1
B45: E-bike | E45: -0.1
A47: C - Revenue
A48: Revenue | E48: =IF(NOT(SUM(E49:E50)=SUM(E37,E27)), "Error", SUM(E37,E27)) -> 0 | F48: =IF(NOT(SUM(F49:F50)=SUM(F37,F27)), "Error", SUM(F37,F27)) -> 0 | G48: =IF(NOT(SUM(G49:G50)=SUM(G37,G27)), "Error", SUM(G37,G27)) -> 0 | H48: =IF(NOT(SUM(H49:H50)=SUM(H37,H27)), "Error", SUM(H37,H27)) -> 0 | I48: =IF(NOT(SUM(I49:I50)=SUM(I37,I27)), "Error", SUM(I37,I27)) -> 0 | J48: =IF(NOT(SUM(J49:J50)=SUM(J37,J27)), "Error", SUM(J37,J27)) -> 7333200000 | K48: =IF(NOT(SUM(K49:K50)=SUM(K37,K27)), "Error", SUM(K37,K27)) -> 7333200000 | L48: =IF(NOT(SUM(L49:L50)=SUM(L37,L27)), "Error", SUM(L37,L27)) -> 8310960000 | ... P48: =IF(NOT(SUM(P49:P50)=SUM(P37,P27)), "Error", SUM(P37,P27)) -> 8711570000 | R48: =IF(NOT(SUM(R49:R50)=SUM(R37,R27)), "Error", SUM(R37,R27)) -> 7401100000 | S48: =IF(NOT(SUM(S49:S50)=SUM(S37,S27)), "Error", SUM(S37,S27)) -> 7401100000 | T48: =IF(NOT(SUM(T49:T50)=SUM(T37,T27)), "Error", SUM(T37,T27)) -> 7401100000 | U48: =IF(NOT(SUM(U49:U50)=SUM(U37,U27)), "Error", SUM(U37,U27)) -> 9085020000 | V48: =IF(NOT(SUM(V49:V50)=SUM(V37,V27)), "Error", SUM(V37,V27)) -> 9085020000 | W48: =IF(NOT(SUM(W49:W50)=SUM(W37,W27)), "Error", SUM(W37,W27)) -> 9085020000 | X48: =IF(NOT(SUM(X49:X50)=SUM(X37,X27)), "Error", SUM(X37,X27)) -> 9424520000 | Y48: =IF(NOT(SUM(Y49:Y50)=SUM(Y37,Y27)), "Error", SUM(Y37,Y27)) -> 9424520000 | ... AC48: =IF(NOT(SUM(AC49:AC50)=SUM(AC37,AC27)), "Error", SUM(AC37,AC27)) -> 14750330000 | AE48: =IF(NOT(SUM(AE49:AE50)=SUM(AE37,AE27)), "Error", SUM(AE37,AE27)) -> 12848220000 | AF48: =IF(NOT(SUM(AF49:AF50)=SUM(AF37,AF27)), "Error", SUM(AF37,AF27)) -> 12668320000 | AG48: =IF(NOT(SUM(AG49:AG50)=SUM(AG37,AG27)), "Error", SUM(AG37,AG27)) -> 12668320000 | AH48: =IF(NOT(SUM(AH49:AH50)=SUM(AH37,AH27)), "Error", SUM(AH37,AH27)) -> 16344580000 | AI48: =IF(NOT(SUM(AI49:AI50)=SUM(AI37,AI27)), "Error", SUM(AI37,AI27)) -> 16344580000 | AJ48: =IF(NOT(SUM(AJ49:AJ50)=SUM(AJ37,AJ27)), "Error", SUM(AJ37,AJ27)) -> 16344580000 | AK48: =IF(NOT(SUM(AK49:AK50)=SUM(AK37,AK27)), "Error", SUM(AK37,AK27)) -> 17117870000 | AL48: =IF(NOT(SUM(AL49:AL50)=SUM(AL37,AL27)), "Error", SUM(AL37,AL27)) -> 17117870000 | ... AP48: =IF(NOT(SUM(AP49:AP50)=SUM(AP37,AP27)), "Error", SUM(AP37,AP27)) -> 18322290000
B49: Standard | E49: =E7*E28+E17*E38 -> 0 | F49: =F7*F28+F17*F38 -> 0 | G49: =G7*G28+G17*G38 -> 0 | H49: =H7*H28+H17*H38 -> 0 | I49: =I7*I28+I17*I38 -> 0 | J49: =J7*J28+J17*J38 -> 7333200000 | K49: =K7*K28+K17*K38 -> 7333200000 | L49: =L7*L28+L17*L38 -> 8310960000 | ... P49: =P7*P28+P17*P38 -> 8711570000 | R49: =R7*R28+R17*R38 -> 7401100000 | S49: =S7*S28+S17*S38 -> 7401100000 | T49: =T7*T28+T17*T38 -> 7401100000 | U49: =U7*U28+U17*U38 -> 9085020000 | V49: =V7*V28+V17*V38 -> 9085020000 | W49: =W7*W28+W17*W38 -> 9085020000 | X49: =X7*X28+X17*X38 -> 9424520000 | Y49: =Y7*Y28+Y17*Y38 -> 9424520000 | ... AC49: =AC7*AC28+AC17*AC38 -> 9893030000 | AE49: =AE7*AE28+AE17*AE38 -> 8548610000 | AF49: =AF7*AF28+AF17*AF38 -> 8548610000 | AG49: =AG7*AG28+AG17*AG38 -> 8548610000 | AH49: =AH7*AH28+AH17*AH38 -> 9526370000 | AI49: =AI7*AI28+AI17*AI38 -> 9526370000 | AJ49: =AJ7*AJ28+AJ17*AJ38 -> 9526370000 | AK49: =AK7*AK28+AK17*AK38 -> 9831920000 | AL49: =AL7*AL28+AL17*AL38 -> 9831920000 | ... AP49: =AP7*AP28+AP17*AP38 -> 10388700000
B50: E-bike | E50: =E8*E29+E18*E39 -> 0 | F50: =F8*F29+F18*F39 -> 0 | G50: =G8*G29+G18*G39 -> 0 | H50: =H8*H29+H18*H39 -> 0 | I50: =I8*I29+I18*I39 -> 0 | J50: =J8*J29+J18*J39 -> 0 | K50: =K8*K29+K18*K39 -> 0 | L50: =L8*L29+L18*L39 -> 0 | ... P50: =P8*P29+P18*P39 -> 0 | R50: =R8*R29+R18*R39 -> 0 | S50: =S8*S29+S18*S39 -> 0 | T50: =T8*T29+T18*T39 -> 0 | U50: =U8*U29+U18*U39 -> 0 | V50: =V8*V29+V18*V39 -> 0 | W50: =W8*W29+W18*W39 -> 0 | X50: =X8*X29+X18*X39 -> 0 | Y50: =Y8*Y29+Y18*Y39 -> 0 | ... AC50: =AC8*AC29+AC18*AC39 -> 4857300000 | AE50: =AE8*AE29+AE18*AE39 -> 4299610000 | AF50: =AF8*AF29+AF18*AF39 -> 4119710000 | AG50: =AG8*AG29+AG18*AG39 -> 4119710000 | AH50: =AH8*AH29+AH18*AH39 -> 6818210000 | AI50: =AI8*AI29+AI18*AI39 -> 6818210000 | AJ50: =AJ8*AJ29+AJ18*AJ39 -> 6818210000 | AK50: =AK8*AK29+AK18*AK39 -> 7285950000 | AL50: =AL8*AL29+AL18*AL39 -> 7285950000 | ... AP50: =AP8*AP29+AP18*AP39 -> 7933590000
A53: T2. Production | E53: 2025 | R53: 2026 | AE53: 2027
E54: Q1 | H54: Q2 | K54: Q3 | N54: Q4 | R54: Q1 | U54: Q2 | X54: Q3 | AA54: Q4 | AE54: Q1 | AH54: Q2 | AK54: Q3 | AN54: Q4
D55: Buffer | E55: 1 | F55: 2 | G55: 3 | H55: 4 | I55: 5 | J55: 6 | K55: 7 | L55: 8 | M55: 9 | N55: 10 | O55: 11 | P55: 12 | R55: 1 | S55: 2 | T55: 3 | U55: 4 | V55: 5 | W55: 6 | X55: 7 | Y55: 8 | Z55: 9 | AA55: 10 | AB55: 11 | AC55: 12 | AE55: 1 | AF55: 2 | AG55: 3 | AH55: 4 | AI55: 5 | AJ55: 6 | AK55: 7 | AL55: 8 | AM55: 9 | AN55: 10 | AO55: 11 | AP55: 12
A57: A' - Sale volume
A58: Store sales estimation | C58: =C6 -> 140 | E58: =E6 -> 0 | F58: =F6 -> 0 | G58: =G6 -> 0 | H58: =H6 -> 0 | I58: =I6 -> 0 | J58: =J6 -> 0 | K58: =K6 -> 0 | L58: =L6 -> 90 | ... P58: =P6 -> 95 | R58: =R6 -> 64 | S58: =S6 -> 64 | T58: =T6 -> 64 | U58: =U6 -> 96 | V58: =V6 -> 96 | W58: =W6 -> 96 | X58: =X6 -> 92 | Y58: =Y6 -> 92 | ... AC58: =AC6 -> 107 | AE58: =AE6 -> 121 | AF58: =AF6 -> 111 | AG58: =AG6 -> 111 | AH58: =AH6 -> 162 | AI58: =AI6 -> 162 | AJ58: =AJ6 -> 162 | AK58: =AK6 -> 152 | AL58: =AL6 -> 152 | ... AP58: =AP6 -> 189
A59: Reference | B59: Standard | C59: =C7 -> 90 | E59: =E7 -> 0 | F59: =F7 -> 0 | G59: =G7 -> 0 | H59: =H7 -> 0 | I59: =I7 -> 0 | J59: =J7 -> 0 | K59: =K7 -> 0 | L59: =L7 -> 90 | ... P59: =P7 -> 95 | R59: =R7 -> 64 | S59: =S7 -> 64 | T59: =T7 -> 64 | U59: =U7 -> 96 | V59: =V7 -> 96 | W59: =W7 -> 96 | X59: =X7 -> 92 | Y59: =Y7 -> 92 | ... AC59: =AC7 -> 107 | AE59: =AE7 -> 71 | AF59: =AF7 -> 71 | AG59: =AG7 -> 71 | AH59: =AH7 -> 107 | AI59: =AI7 -> 107 | AJ59: =AJ7 -> 107 | AK59: =AK7 -> 98 | AL59: =AL7 -> 98 | ... AP59: =AP7 -> 126
B60: E-bike | C60: =C8 -> 50 | E60: =E8 -> 0 | F60: =F8 -> 0 | G60: =G8 -> 0 | H60: =H8 -> 0 | I60: =I8 -> 0 | J60: =J8 -> 0 | K60: =K8 -> 0 | L60: =L8 -> 0 | ... P60: =P8 -> 0 | R60: =R8 -> 0 | S60: =S8 -> 0 | T60: =T8 -> 0 | U60: =U8 -> 0 | V60: =V8 -> 0 | W60: =W8 -> 0 | X60: =X8 -> 0 | Y60: =Y8 -> 0 | ... AC60: =AC8 -> 0 | AE60: =AE8 -> 50 | AF60: =AF8 -> 40 | AG60: =AG8 -> 40 | AH60: =AH8 -> 55 | AI60: =AI8 -> 55 | AJ60: =AJ8 -> 55 | AK60: =AK8 -> 54 | AL60: =AL8 -> 54 | ... AP60: =AP8 -> 63
A61: Distributor vol. | B61: Bảo | C61: =C16 -> 1800 | E61: =E16 -> 0 | F61: =F16 -> 0 | G61: =G16 -> 0 | H61: =H16 -> 0 | I61: =I16 -> 0 | J61: =J16 -> 1200 | K61: =K16 -> 1200 | L61: =L16 -> 1260 | ... P61: =P16 -> 1320 | R61: =R16 -> 1140 | S61: =S16 -> 1140 | T61: =T16 -> 1140 | U61: =U16 -> 1380 | V61: =V16 -> 1380 | W61: =W16 -> 1380 | X61: =X16 -> 1440 | Y61: =Y16 -> 1440 | ... AC61: =AC16 -> 1800 | AE61: =AE16 -> 1530 | AF61: =AF16 -> 1530 | AG61: =AG16 -> 1530 | AH61: =AH16 -> 1800 | AI61: =AI16 -> 1800 | AJ61: =AJ16 -> 1800 | AK61: =AK16 -> 1890 | AL61: =AL16 -> 1890 | ... AP61: =AP16 -> 1980
A62: Reference | B62: Standard | C62: =C17 -> 1200 | E62: =E17 -> 0 | F62: =F17 -> 0 | G62: =G17 -> 0 | H62: =H17 -> 0 | I62: =I17 -> 0 | J62: =J17 -> 1200 | K62: =K17 -> 1200 | L62: =L17 -> 1260 | ... P62: =P17 -> 1320 | R62: =R17 -> 1140 | S62: =S17 -> 1140 | T62: =T17 -> 1140 | U62: =U17 -> 1380 | V62: =V17 -> 1380 | W62: =W17 -> 1380 | X62: =X17 -> 1440 | Y62: =Y17 -> 1440 | ... AC62: =AC17 -> 1500 | AE62: =AE17 -> 1320 | AF62: =AF17 -> 1320 | AG62: =AG17 -> 1320 | AH62: =AH17 -> 1440 | AI62: =AI17 -> 1440 | AJ62: =AJ17 -> 1440 | AK62: =AK17 -> 1500 | AL62: =AL17 -> 1500 | ... AP62: =AP17 -> 1560
B63: E-bike | C63: =C18 -> 600 | E63: =E18 -> 0 | F63: =F18 -> 0 | G63: =G18 -> 0 | H63: =H18 -> 0 | I63: =I18 -> 0 | J63: =J18 -> 0 | K63: =K18 -> 0 | L63: =L18 -> 0 | ... P63: =P18 -> 0 | R63: =R18 -> 0 | S63: =S18 -> 0 | T63: =T18 -> 0 | U63: =U18 -> 0 | V63: =V18 -> 0 | W63: =W18 -> 0 | X63: =X18 -> 0 | Y63: =Y18 -> 0 | ... AC63: =AC18 -> 300 | AE63: =AE18 -> 210 | AF63: =AF18 -> 210 | AG63: =AG18 -> 210 | AH63: =AH18 -> 360 | AI63: =AI18 -> 360 | AJ63: =AJ18 -> 360 | AK63: =AK18 -> 390 | AL63: =AL18 -> 390 | ... AP63: =AP18 -> 420
A65: D - Inventory difference
A66: Store preproduce | C66: % | E66: =SUM(E67:E68) -> 0 | F66: =SUM(F67:F68) -> 0 | G66: =SUM(G67:G68) -> 0 | H66: =SUM(H67:H68) -> 0 | I66: =SUM(I67:I68) -> 0 | J66: =SUM(J67:J68) -> 0 | K66: =SUM(K67:K68) -> 11 | L66: =SUM(L67:L68) -> 11 | ... P66: =SUM(P67:P68) -> 8 | R66: =SUM(R67:R68) -> 8 | S66: =SUM(S67:S68) -> 8 | T66: =SUM(T67:T68) -> 12 | U66: =SUM(U67:U68) -> 12 | V66: =SUM(V67:V68) -> 12 | W66: =SUM(W67:W68) -> 12 | X66: =SUM(X67:X68) -> 12 | Y66: =SUM(Y67:Y68) -> 12 | ... AC66: =SUM(AC67:AC68) -> 15 | AE66: =SUM(AE67:AE68) -> 14 | AF66: =SUM(AF67:AF68) -> 14 | AG66: =SUM(AG67:AG68) -> 20 | AH66: =SUM(AH67:AH68) -> 20 | AI66: =SUM(AI67:AI68) -> 20 | AJ66: =SUM(AJ67:AJ68) -> 19 | AK66: =SUM(AK67:AK68) -> 19 | AL66: =SUM(AL67:AL68) -> 19 | ... AP66: =SUM(AP67:AP68) -> 0
B67: Standard | C67: 0.12 | E67: 0 | F67: 0 | G67: 0 | H67: 0 | I67: 0 | J67: 0 | K67: 11 | L67: 11 | M67: 12 | N67: 12 | O67: 12 | P67: 8 | R67: 8 | S67: 8 | T67: 12 | U67: 12 | V67: 12 | W67: 12 | X67: 12 | Y67: 12 | Z67: 12 | AA67: 13 | AB67: 13 | AC67: 9 | AE67: 9 | AF67: 9 | AG67: 13 | AH67: 13 | AI67: 13 | AJ67: 12 | AK67: 12 | AL67: 12 | AM67: 14 | AN67: 15 | AO67: 16 | AP67: 0
B68: E-bike | C68: 0.12 | E68: 0 | F68: 0 | G68: 0 | H68: 0 | I68: 0 | J68: 0 | K68: 0 | L68: 0 | M68: 0 | N68: 0 | O68: 0 | P68: 0 | R68: 0 | S68: 0 | T68: 0 | U68: 0 | V68: 0 | W68: 0 | X68: 0 | Y68: 0 | Z68: 0 | AA68: 0 | AB68: 0 | AC68: 6 | AE68: 5 | AF68: 5 | AG68: 7 | AH68: 7 | AI68: 7 | AJ68: 7 | AK68: 7 | AL68: 7 | AM68: 7 | AN68: 8 | AO68: 8 | AP68: 0
A69: Dis. preproduce | C69: % | E69: =SUM(E70:E71) -> 0 | F69: =SUM(F70:F71) -> 0 | G69: =SUM(G70:G71) -> 0 | H69: =SUM(H70:H71) -> 0 | I69: =SUM(I70:I71) -> 144 | J69: =SUM(J70:J71) -> 144 | K69: =SUM(K70:K71) -> 152 | L69: =SUM(L70:L71) -> 152 | ... P69: =SUM(P70:P71) -> 137 | R69: =SUM(R70:R71) -> 137 | S69: =SUM(S70:S71) -> 137 | T69: =SUM(T70:T71) -> 166 | U69: =SUM(U70:U71) -> 166 | V69: =SUM(V70:V71) -> 166 | W69: =SUM(W70:W71) -> 173 | X69: =SUM(X70:X71) -> 173 | Y69: =SUM(Y70:Y71) -> 173 | ... AC69: =SUM(AC70:AC71) -> 185 | AE69: =SUM(AE70:AE71) -> 185 | AF69: =SUM(AF70:AF71) -> 185 | AG69: =SUM(AG70:AG71) -> 217 | AH69: =SUM(AH70:AH71) -> 217 | AI69: =SUM(AI70:AI71) -> 217 | AJ69: =SUM(AJ70:AJ71) -> 227 | AK69: =SUM(AK70:AK71) -> 227 | AL69: =SUM(AL70:AL71) -> 231 | ... AP69: =SUM(AP70:AP71) -> 0
B70: Standard | C70: 0.12 | E70: 0 | F70: 0 | G70: 0 | H70: 0 | I70: 144 | J70: 144 | K70: 152 | L70: 152 | M70: 159 | N70: 159 | O70: 159 | P70: 137 | R70: 137 | S70: 137 | T70: 166 | U70: 166 | V70: 166 | W70: 173 | X70: 173 | Y70: 173 | Z70: 180 | AA70: 180 | AB70: 180 | AC70: 159 | AE70: 159 | AF70: 159 | AG70: 173 | AH70: 173 | AI70: 173 | AJ70: 180 | AK70: 180 | AL70: 180 | AM70: 188 | AN70: 188 | AO70: 188 | AP70: 0
B71: E-bike | C71: 0.12 | E71: 0 | F71: 0 | G71: 0 | H71: 0 | I71: 0 | J71: 0 | K71: 0 | L71: 0 | M71: 0 | N71: 0 | O71: 0 | P71: 0 | R71: 0 | S71: 0 | T71: 0 | U71: 0 | V71: 0 | W71: 0 | X71: 0 | Y71: 0 | Z71: 0 | AA71: 36 | AB71: 36 | AC71: 26 | AE71: 26 | AF71: 26 | AG71: 44 | AH71: 44 | AI71: 44 | AJ71: 47 | AK71: 47 | AL71: 51 | AM71: 51 | AN71: 51 | AO71: 51 | AP71: 0
A72: Inv. vol Diff. | C72: =C100 -> 0 | E72: =E100 -> 0 | F72: =F100 -> 0 | G72: =G100 -> 0 | H72: =H100 -> 0 | I72: =I100 -> 274 | J72: =J100 -> 0 | K72: =K100 -> 19 | L72: =L100 -> 0 | ... P72: =P100 -> -26 | R72: =R100 -> 0 | S72: =S100 -> 0 | T72: =T100 -> 33 | U72: =U100 -> 0 | V72: =V100 -> 0 | W72: =W100 -> 7 | X72: =X100 -> 0 | Y72: =Y100 -> 0 | ... AC72: =AC100 -> -29 | AE72: =AE100 -> 0 | AF72: =AF100 -> 0 | AG72: =AG100 -> 38 | AH72: =AH100 -> 0 | AI72: =AI100 -> 0 | AJ72: =AJ100 -> 9 | AK72: =AK100 -> 0 | AL72: =AL100 -> 4 | ... AP72: =AP100 -> -263
A73: Reference | B73: Standard | C73: =C101 -> 0 | E73: =E101 -> 0 | F73: =F101 -> 0 | G73: =G101 -> 0 | H73: =H101 -> 0 | I73: =I101 -> 274 | J73: =J101 -> 0 | K73: =K101 -> 19 | L73: =L101 -> 0 | ... P73: =P101 -> -26 | R73: =R101 -> 0 | S73: =S101 -> 0 | T73: =T101 -> 33 | U73: =U101 -> 0 | V73: =V101 -> 0 | W73: =W101 -> 7 | X73: =X101 -> 0 | Y73: =Y101 -> 0 | ... AC73: =AC101 -> -25 | AE73: =AE101 -> 0 | AF73: =AF101 -> 0 | AG73: =AG101 -> 18 | AH73: =AH101 -> 0 | AI73: =AI101 -> 0 | AJ73: =AJ101 -> 6 | AK73: =AK101 -> 0 | AL73: =AL101 -> 0 | ... AP73: =AP101 -> -204
B74: E-bike | C74: =C102 -> 0 | E74: =E102 -> 0 | F74: =F102 -> 0 | G74: =G102 -> 0 | H74: =H102 -> 0 | I74: =I102 -> 0 | J74: =J102 -> 0 | K74: =K102 -> 0 | L74: =L102 -> 0 | ... P74: =P102 -> 0 | R74: =R102 -> 0 | S74: =S102 -> 0 | T74: =T102 -> 0 | U74: =U102 -> 0 | V74: =V102 -> 0 | W74: =W102 -> 0 | X74: =X102 -> 0 | Y74: =Y102 -> 0 | ... AC74: =AC102 -> -4 | AE74: =AE102 -> 0 | AF74: =AF102 -> 0 | AG74: =AG102 -> 20 | AH74: =AH102 -> 0 | AI74: =AI102 -> 0 | AJ74: =AJ102 -> 3 | AK74: =AK102 -> 0 | AL74: =AL102 -> 4 | ... AP74: =AP102 -> -59
A76: E - Production
A77: Production outputs | E77: =SUM(E78:E79) -> 0 | F77: =SUM(F78:F79) -> 0 | G77: =SUM(G78:G79) -> 0 | H77: =SUM(H78:H79) -> 0 | I77: =SUM(I78:I79) -> 274 | J77: =SUM(J78:J79) -> 1200 | K77: =SUM(K78:K79) -> 1219 | L77: =SUM(L78:L79) -> 1350 | ... P77: =SUM(P78:P79) -> 1389 | R77: =SUM(R78:R79) -> 1204 | S77: =SUM(S78:S79) -> 1204 | T77: =SUM(T78:T79) -> 1237 | U77: =SUM(U78:U79) -> 1476 | V77: =SUM(V78:V79) -> 1476 | W77: =SUM(W78:W79) -> 1483 | X77: =SUM(X78:X79) -> 1532 | Y77: =SUM(Y78:Y79) -> 1532 | ... AC77: =SUM(AC78:AC79) -> 1878 | AE77: =SUM(AE78:AE79) -> 1651 | AF77: =SUM(AF78:AF79) -> 1641 | AG77: =SUM(AG78:AG79) -> 1679 | AH77: =SUM(AH78:AH79) -> 1962 | AI77: =SUM(AI78:AI79) -> 1962 | AJ77: =SUM(AJ78:AJ79) -> 1971 | AK77: =SUM(AK78:AK79) -> 2042 | AL77: =SUM(AL78:AL79) -> 2046 | ... AP77: =SUM(AP78:AP79) -> 1906
B78: Standard | E78: =E59+E62+E73 -> 0 | F78: =F59+F62+F73 -> 0 | G78: =G59+G62+G73 -> 0 | H78: =H59+H62+H73 -> 0 | I78: =I59+I62+I73 -> 274 | J78: =J59+J62+J73 -> 1200 | K78: =K59+K62+K73 -> 1219 | L78: =L59+L62+L73 -> 1350 | ... P78: =P59+P62+P73 -> 1389 | R78: =R59+R62+R73 -> 1204 | S78: =S59+S62+S73 -> 1204 | T78: =T59+T62+T73 -> 1237 | U78: =U59+U62+U73 -> 1476 | V78: =V59+V62+V73 -> 1476 | W78: =W59+W62+W73 -> 1483 | X78: =X59+X62+X73 -> 1532 | Y78: =Y59+Y62+Y73 -> 1532 | ... AC78: =AC59+AC62+AC73 -> 1582 | AE78: =AE59+AE62+AE73 -> 1391 | AF78: =AF59+AF62+AF73 -> 1391 | AG78: =AG59+AG62+AG73 -> 1409 | AH78: =AH59+AH62+AH73 -> 1547 | AI78: =AI59+AI62+AI73 -> 1547 | AJ78: =AJ59+AJ62+AJ73 -> 1553 | AK78: =AK59+AK62+AK73 -> 1598 | AL78: =AL59+AL62+AL73 -> 1598 | ... AP78: =AP59+AP62+AP73 -> 1482
B79: E-bike | E79: =E60+E63+E74 -> 0 | F79: =F60+F63+F74 -> 0 | G79: =G60+G63+G74 -> 0 | H79: =H60+H63+H74 -> 0 | I79: =I60+I63+I74 -> 0 | J79: =J60+J63+J74 -> 0 | K79: =K60+K63+K74 -> 0 | L79: =L60+L63+L74 -> 0 | ... P79: =P60+P63+P74 -> 0 | R79: =R60+R63+R74 -> 0 | S79: =S60+S63+S74 -> 0 | T79: =T60+T63+T74 -> 0 | U79: =U60+U63+U74 -> 0 | V79: =V60+V63+V74 -> 0 | W79: =W60+W63+W74 -> 0 | X79: =X60+X63+X74 -> 0 | Y79: =Y60+Y63+Y74 -> 0 | ... AC79: =AC60+AC63+AC74 -> 296 | AE79: =AE60+AE63+AE74 -> 260 | AF79: =AF60+AF63+AF74 -> 250 | AG79: =AG60+AG63+AG74 -> 270 | AH79: =AH60+AH63+AH74 -> 415 | AI79: =AI60+AI63+AI74 -> 415 | AJ79: =AJ60+AJ63+AJ74 -> 418 | AK79: =AK60+AK63+AK74 -> 444 | AL79: =AL60+AL63+AL74 -> 448 | ... AP79: =AP60+AP63+AP74 -> 424
A82: T3. Inventory | E82: 2025 | R82: 2026 | AE82: 2027
E83: Q1 | H83: Q2 | K83: Q3 | N83: Q4 | R83: Q1 | U83: Q2 | X83: Q3 | AA83: Q4 | AE83: Q1 | AH83: Q2 | AK83: Q3 | AN83: Q4
E84: 1 | F84: 2 | G84: 3 | H84: 4 | I84: 5 | J84: 6 | K84: 7 | L84: 8 | M84: 9 | N84: 10 | O84: 11 | P84: 12 | R84: 1 | S84: 2 | T84: 3 | U84: 4 | V84: 5 | W84: 6 | X84: 7 | Y84: 8 | Z84: 9 | AA84: 10 | AB84: 11 | AC84: 12 | AE84: 1 | AF84: 2 | AG84: 3 | AH84: 4 | AI84: 5 | AJ84: 6 | AK84: 7 | AL84: 8 | AM84: 9 | AN84: 10 | AO84: 11 | AP84: 12
A85: Inventory | C85: Base Inv | E85: =SUM(E86:E87) -> 0 | F85: =SUM(F86:F87) -> 0 | G85: =SUM(G86:G87) -> 0 | H85: =SUM(H86:H87) -> 0 | I85: =SUM(I86:I87) -> 274 | J85: =SUM(J86:J87) -> 274 | K85: =SUM(K86:K87) -> 293 | L85: =SUM(L86:L87) -> 293 | ... P85: =SUM(P86:P87) -> 275 | R85: =SUM(R86:R87) -> 275 | S85: =SUM(S86:S87) -> 275 | T85: =SUM(T86:T87) -> 308 | U85: =SUM(U86:U87) -> 308 | V85: =SUM(V86:V87) -> 308 | W85: =SUM(W86:W87) -> 315 | X85: =SUM(X86:X87) -> 315 | Y85: =SUM(Y86:Y87) -> 315 | ... AC85: =SUM(AC86:AC87) -> 400 | AE85: =SUM(AE86:AE87) -> 400 | AF85: =SUM(AF86:AF87) -> 400 | AG85: =SUM(AG86:AG87) -> 438 | AH85: =SUM(AH86:AH87) -> 438 | AI85: =SUM(AI86:AI87) -> 438 | AJ85: =SUM(AJ86:AJ87) -> 447 | AK85: =SUM(AK86:AK87) -> 447 | AL85: =SUM(AL86:AL87) -> 451 | ... AP85: =SUM(AP86:AP87) -> 201
B86: Standard | C86: =ROUNDUP(Parameter!B70*(Parameter!B57+Parameter!B58),-1) -> 130 | D86: =C86 -> 130 | E86: 0 | F86: 0 | G86: 0 | H86: 0 | I86: 274 | J86: 274 | K86: 293 | L86: 293 | M86: 301 | N86: 301 | O86: 301 | P86: 275 | R86: 275 | S86: 275 | T86: 308 | U86: 308 | V86: 308 | W86: 315 | X86: 315 | Y86: 315 | Z86: 322 | AA86: 323 | AB86: 323 | AC86: 298 | AE86: 298 | AF86: 298 | AG86: 316 | AH86: 316 | AI86: 316 | AJ86: 322 | AK86: 322 | AL86: 322 | AM86: 332 | AN86: 333 | AO86: 334 | AP86: 130
B87: E-bike | C87: =ROUNDUP(Parameter!B70*(Parameter!B59+Parameter!B60),-1) -> 70 | D87: =C87 -> 70 | E87: 0 | F87: 0 | G87: 0 | H87: 0 | I87: 0 | J87: 0 | K87: 0 | L87: 0 | M87: 0 | N87: 0 | O87: 0 | P87: 0 | R87: 0 | S87: 0 | T87: 0 | U87: 0 | V87: 0 | W87: 0 | X87: 0 | Y87: 0 | Z87: 0 | AA87: 36 | AB87: 106 | AC87: 102 | AE87: 102 | AF87: 102 | AG87: 122 | AH87: 122 | AI87: 122 | AJ87: 125 | AK87: 125 | AL87: 129 | AM87: 129 | AN87: 130 | AO87: 130 | AP87: 71
A88: Base Inv. change - Accumulating %
B89: Standard | E89: =D89+E92 -> -1 | F89: =E89+F92 -> -1 | G89: =F89+G92 -> -1 | H89: =G89+H92 -> -1 | I89: =H89+I92 -> 0 | J89: =I89+J92 -> 0 | K89: =J89+K92 -> 0 | L89: =K89+L92 -> 0 | ... AP89: =AO89+AP92 -> 0
B90: E-bike | E90: =D90+E93 -> -1 | F90: =E90+F93 -> -1 | G90: =F90+G93 -> -1 | H90: =G90+H93 -> -1 | I90: =H90+I93 -> -1 | J90: =I90+J93 -> -1 | K90: =J90+K93 -> -1 | L90: =K90+L93 -> -1 | ... AP90: =AO90+AP93 -> 0
A91: Base Inv. change (NOT RECOMMEND) | C91: =C85 -> Base Inv
B92: Standard | C92: =C86 -> 130 | E92: -1 | I92: 1
B93: E-bike | C93: =C87 -> 70 | E93: -1 | AB93: 1
A94: Store preproduce | C94: =C66 -> % | D94: =D66 -> 0 | E94: =E66 -> 0 | F94: =F66 -> 0 | G94: =G66 -> 0 | H94: =H66 -> 0 | I94: =I66 -> 0 | J94: =J66 -> 0 | ... P94: =P66 -> 8 | R94: =R66 -> 8 | S94: =S66 -> 8 | T94: =T66 -> 12 | U94: =U66 -> 12 | V94: =V66 -> 12 | W94: =W66 -> 12 | X94: =X66 -> 12 | Y94: =Y66 -> 12 | ... AC94: =AC66 -> 15 | AE94: =AE66 -> 14 | AF94: =AF66 -> 14 | AG94: =AG66 -> 20 | AH94: =AH66 -> 20 | AI94: =AI66 -> 20 | AJ94: =AJ66 -> 19 | AK94: =AK66 -> 19 | AL94: =AL66 -> 19 | ... AP94: =AP66 -> 0
A95: Reference | B95: Standard | C95: =C67 -> 0.12 | D95: =D67 -> 0 | E95: =E67 -> 0 | F95: =F67 -> 0 | G95: =G67 -> 0 | H95: =H67 -> 0 | I95: =I67 -> 0 | J95: =J67 -> 0 | ... P95: =P67 -> 8 | R95: =R67 -> 8 | S95: =S67 -> 8 | T95: =T67 -> 12 | U95: =U67 -> 12 | V95: =V67 -> 12 | W95: =W67 -> 12 | X95: =X67 -> 12 | Y95: =Y67 -> 12 | ... AC95: =AC67 -> 9 | AE95: =AE67 -> 9 | AF95: =AF67 -> 9 | AG95: =AG67 -> 13 | AH95: =AH67 -> 13 | AI95: =AI67 -> 13 | AJ95: =AJ67 -> 12 | AK95: =AK67 -> 12 | AL95: =AL67 -> 12 | ... AP95: =AP67 -> 0
B96: E-bike | C96: =C68 -> 0.12 | D96: =D68 -> 0 | E96: =E68 -> 0 | F96: =F68 -> 0 | G96: =G68 -> 0 | H96: =H68 -> 0 | I96: =I68 -> 0 | J96: =J68 -> 0 | ... P96: =P68 -> 0 | R96: =R68 -> 0 | S96: =S68 -> 0 | T96: =T68 -> 0 | U96: =U68 -> 0 | V96: =V68 -> 0 | W96: =W68 -> 0 | X96: =X68 -> 0 | Y96: =Y68 -> 0 | ... AC96: =AC68 -> 6 | AE96: =AE68 -> 5 | AF96: =AF68 -> 5 | AG96: =AG68 -> 7 | AH96: =AH68 -> 7 | AI96: =AI68 -> 7 | AJ96: =AJ68 -> 7 | AK96: =AK68 -> 7 | AL96: =AL68 -> 7 | ... AP96: =AP68 -> 0
A97: Dis. preproduce | C97: =C69 -> % | D97: =D69 -> 0 | E97: =E69 -> 0 | F97: =F69 -> 0 | G97: =G69 -> 0 | H97: =H69 -> 0 | I97: =I69 -> 144 | J97: =J69 -> 144 | ... P97: =P69 -> 137 | R97: =R69 -> 137 | S97: =S69 -> 137 | T97: =T69 -> 166 | U97: =U69 -> 166 | V97: =V69 -> 166 | W97: =W69 -> 173 | X97: =X69 -> 173 | Y97: =Y69 -> 173 | ... AC97: =AC69 -> 185 | AE97: =AE69 -> 185 | AF97: =AF69 -> 185 | AG97: =AG69 -> 217 | AH97: =AH69 -> 217 | AI97: =AI69 -> 217 | AJ97: =AJ69 -> 227 | AK97: =AK69 -> 227 | AL97: =AL69 -> 231 | ... AP97: =AP69 -> 0
A98: Reference | B98: Standard | C98: =C70 -> 0.12 | D98: =D70 -> 0 | E98: =E70 -> 0 | F98: =F70 -> 0 | G98: =G70 -> 0 | H98: =H70 -> 0 | I98: =I70 -> 144 | J98: =J70 -> 144 | ... P98: =P70 -> 137 | R98: =R70 -> 137 | S98: =S70 -> 137 | T98: =T70 -> 166 | U98: =U70 -> 166 | V98: =V70 -> 166 | W98: =W70 -> 173 | X98: =X70 -> 173 | Y98: =Y70 -> 173 | ... AC98: =AC70 -> 159 | AE98: =AE70 -> 159 | AF98: =AF70 -> 159 | AG98: =AG70 -> 173 | AH98: =AH70 -> 173 | AI98: =AI70 -> 173 | AJ98: =AJ70 -> 180 | AK98: =AK70 -> 180 | AL98: =AL70 -> 180 | ... AP98: =AP70 -> 0
B99: E-bike | C99: =C71 -> 0.12 | D99: =D71 -> 0 | E99: =E71 -> 0 | F99: =F71 -> 0 | G99: =G71 -> 0 | H99: =H71 -> 0 | I99: =I71 -> 0 | J99: =J71 -> 0 | ... P99: =P71 -> 0 | R99: =R71 -> 0 | S99: =S71 -> 0 | T99: =T71 -> 0 | U99: =U71 -> 0 | V99: =V71 -> 0 | W99: =W71 -> 0 | X99: =X71 -> 0 | Y99: =Y71 -> 0 | ... AC99: =AC71 -> 26 | AE99: =AE71 -> 26 | AF99: =AF71 -> 26 | AG99: =AG71 -> 44 | AH99: =AH71 -> 44 | AI99: =AI71 -> 44 | AJ99: =AJ71 -> 47 | AK99: =AK71 -> 47 | AL99: =AL71 -> 51 | ... AP99: =AP71 -> 0
A100: Inv. vol Diff. | F100: =SUM(F101:F102) -> 0 | G100: =SUM(G101:G102) -> 0 | H100: =SUM(H101:H102) -> 0 | I100: =SUM(I101:I102) -> 274 | J100: =SUM(J101:J102) -> 0 | K100: =SUM(K101:K102) -> 19 | L100: =SUM(L101:L102) -> 0 | M100: =SUM(M101:M102) -> 8 | ... P100: =SUM(P101:P102) -> -26 | R100: =SUM(R101:R102) -> 0 | S100: =SUM(S101:S102) -> 0 | T100: =SUM(T101:T102) -> 33 | U100: =SUM(U101:U102) -> 0 | V100: =SUM(V101:V102) -> 0 | W100: =SUM(W101:W102) -> 7 | X100: =SUM(X101:X102) -> 0 | Y100: =SUM(Y101:Y102) -> 0 | ... AC100: =SUM(AC101:AC102) -> -29 | AE100: =SUM(AE101:AE102) -> 0 | AF100: =SUM(AF101:AF102) -> 0 | AG100: =SUM(AG101:AG102) -> 38 | AH100: =SUM(AH101:AH102) -> 0 | AI100: =SUM(AI101:AI102) -> 0 | AJ100: =SUM(AJ101:AJ102) -> 9 | AK100: =SUM(AK101:AK102) -> 0 | AL100: =SUM(AL101:AL102) -> 4 | ... AP100: =SUM(AP101:AP102) -> -263
B101: Standard | F101: =F86-E86 -> 0 | G101: =G86-F86 -> 0 | H101: =H86-G86 -> 0 | I101: =I86-H86 -> 274 | J101: =J86-I86 -> 0 | K101: =K86-J86 -> 19 | L101: =L86-K86 -> 0 | M101: =M86-L86 -> 8 | ... P101: =P86-O86 -> -26 | R101: =R86-P86 -> 0 | S101: =S86-R86 -> 0 | T101: =T86-S86 -> 33 | U101: =U86-T86 -> 0 | V101: =V86-U86 -> 0 | W101: =W86-V86 -> 7 | X101: =X86-W86 -> 0 | Y101: =Y86-X86 -> 0 | Z101: =Z86-Y86 -> 7 | ... AC101: =AC86-AB86 -> -25 | AE101: =AE86-AC86 -> 0 | AF101: =AF86-AE86 -> 0 | AG101: =AG86-AF86 -> 18 | AH101: =AH86-AG86 -> 0 | AI101: =AI86-AH86 -> 0 | AJ101: =AJ86-AI86 -> 6 | AK101: =AK86-AJ86 -> 0 | AL101: =AL86-AK86 -> 0 | AM101: =AM86-AL86 -> 10 | ... AP101: =AP86-AO86 -> -204
B102: E-bike | F102: =F87-E87 -> 0 | G102: =G87-F87 -> 0 | H102: =H87-G87 -> 0 | I102: =I87-H87 -> 0 | J102: =J87-I87 -> 0 | K102: =K87-J87 -> 0 | L102: =L87-K87 -> 0 | M102: =M87-L87 -> 0 | ... P102: =P87-O87 -> 0 | R102: =R87-P87 -> 0 | S102: =S87-R87 -> 0 | T102: =T87-S87 -> 0 | U102: =U87-T87 -> 0 | V102: =V87-U87 -> 0 | W102: =W87-V87 -> 0 | X102: =X87-W87 -> 0 | Y102: =Y87-X87 -> 0 | Z102: =Z87-Y87 -> 0 | ... AC102: =AC87-AB87 -> -4 | AE102: =AE87-AC87 -> 0 | AF102: =AF87-AE87 -> 0 | AG102: =AG87-AF87 -> 20 | AH102: =AH87-AG87 -> 0 | AI102: =AI87-AH87 -> 0 | AJ102: =AJ87-AI87 -> 3 | AK102: =AK87-AJ87 -> 0 | AL102: =AL87-AK87 -> 4 | AM102: =AM87-AL87 -> 0 | ... AP102: =AP87-AO87 -> -59
A103: Inv. in | E103: =SUM(E104:E105) -> 0 | F103: =SUM(F104:F105) -> 0 | G103: =SUM(G104:G105) -> 0 | H103: =SUM(H104:H105) -> 0 | I103: =SUM(I104:I105) -> 274 | J103: =SUM(J104:J105) -> 0 | K103: =SUM(K104:K105) -> 19 | L103: =SUM(L104:L105) -> 0 | ... AP103: =SUM(AP104:AP105) -> 0
B104: Standard | E104: =MAX(E101,0) -> 0 | F104: =MAX(F101,0) -> 0 | G104: =MAX(G101,0) -> 0 | H104: =MAX(H101,0) -> 0 | I104: =MAX(I101,0) -> 274 | J104: =MAX(J101,0) -> 0 | K104: =MAX(K101,0) -> 19 | L104: =MAX(L101,0) -> 0 | ... AP104: =MAX(AP101,0) -> 0
B105: E-bike | E105: =MAX(E102,0) -> 0 | F105: =MAX(F102,0) -> 0 | G105: =MAX(G102,0) -> 0 | H105: =MAX(H102,0) -> 0 | I105: =MAX(I102,0) -> 0 | J105: =MAX(J102,0) -> 0 | K105: =MAX(K102,0) -> 0 | L105: =MAX(L102,0) -> 0 | ... AP105: =MAX(AP102,0) -> 0
A106: Inv. Out | E106: =SUM(E107:E108) -> 0 | F106: =SUM(F107:F108) -> 0 | G106: =SUM(G107:G108) -> 0 | H106: =SUM(H107:H108) -> 0 | I106: =SUM(I107:I108) -> 0 | J106: =SUM(J107:J108) -> 0 | K106: =SUM(K107:K108) -> 0 | L106: =SUM(L107:L108) -> 0 | ... AP106: =SUM(AP107:AP108) -> -263
B107: Standard | E107: =MIN(E101,0) -> 0 | F107: =MIN(F101,0) -> 0 | G107: =MIN(G101,0) -> 0 | H107: =MIN(H101,0) -> 0 | I107: =MIN(I101,0) -> 0 | J107: =MIN(J101,0) -> 0 | K107: =MIN(K101,0) -> 0 | L107: =MIN(L101,0) -> 0 | ... AP107: =MIN(AP101,0) -> -204
B108: E-bike | E108: =MIN(E102,0) -> 0 | F108: =MIN(F102,0) -> 0 | G108: =MIN(G102,0) -> 0 | H108: =MIN(H102,0) -> 0 | I108: =MIN(I102,0) -> 0 | J108: =MIN(J102,0) -> 0 | K108: =MIN(K102,0) -> 0 | L108: =MIN(L102,0) -> 0 | ... AP108: =MIN(AP102,0) -> -59

Sheet Expenses
A1: Expenses | E1: 2025 | R1: 2026 | AE1: 2027
E2: Q1 | H2: Q2 | K2: Q3 | N2: Q4 | R2: Q1 | U2: Q2 | X2: Q3 | AA2: Q4 | AE2: Q1 | AH2: Q2 | AK2: Q3 | AN2: Q4
B3: Buffer | E3: 1 | F3: 2 | G3: 3 | H3: 4 | I3: 5 | J3: 6 | K3: 7 | L3: 8 | M3: 9 | N3: 10 | O3: 11 | P3: 12 | R3: 1 | S3: 2 | T3: 3 | U3: 4 | V3: 5 | W3: 6 | X3: 7 | Y3: 8 | Z3: 9 | AA3: 10 | AB3: 11 | AC3: 12 | AE3: 1 | AF3: 2 | AG3: 3 | AH3: 4 | AI3: 5 | AJ3: 6 | AK3: 7 | AL3: 8 | AM3: 9 | AN3: 10 | AO3: 11 | AP3: 12
A4: COST OF GOODS SOLD
A5: Material:
A6: Product 1: Standard | E6: =Parameter!$B$65*('Operations plan'!E59+'Operations plan'!E62) -> 0 | F6: =Parameter!$B$65*('Operations plan'!F59+'Operations plan'!F62) -> 0 | G6: =Parameter!$B$65*('Operations plan'!G59+'Operations plan'!G62) -> 0 | H6: =Parameter!$B$65*('Operations plan'!H59+'Operations plan'!H62) -> 0 | I6: =Parameter!$B$65*('Operations plan'!I59+'Operations plan'!I62) -> 0 | J6: =Parameter!$B$65*('Operations plan'!J59+'Operations plan'!J62) -> 4020000000 | K6: =Parameter!$B$65*('Operations plan'!K59+'Operations plan'!K62) -> 4020000000 | L6: =Parameter!$B$65*('Operations plan'!L59+'Operations plan'!L62) -> 4522500000 | ... P6: =Parameter!$B$65*('Operations plan'!P59+'Operations plan'!P62) -> 4740250000 | R6: =Parameter!$B$65*('Operations plan'!R59+'Operations plan'!R62) -> 4033400000 | S6: =Parameter!$B$65*('Operations plan'!S59+'Operations plan'!S62) -> 4033400000 | T6: =Parameter!$B$65*('Operations plan'!T59+'Operations plan'!T62) -> 4033400000 | U6: =Parameter!$B$65*('Operations plan'!U59+'Operations plan'!U62) -> 4944600000 | V6: =Parameter!$B$65*('Operations plan'!V59+'Operations plan'!V62) -> 4944600000 | W6: =Parameter!$B$65*('Operations plan'!W59+'Operations plan'!W62) -> 4944600000 | X6: =Parameter!$B$65*('Operations plan'!X59+'Operations plan'!X62) -> 5132200000 | Y6: =Parameter!$B$65*('Operations plan'!Y59+'Operations plan'!Y62) -> 5132200000 | ... AC6: =Parameter!$B$65*('Operations plan'!AC59+'Operations plan'!AC62) -> 5383450000 | AE6: =Parameter!$B$65*('Operations plan'!AE59+'Operations plan'!AE62) -> 4659850000 | AF6: =Parameter!$B$65*('Operations plan'!AF59+'Operations plan'!AF62) -> 4659850000 | AG6: =Parameter!$B$65*('Operations plan'!AG59+'Operations plan'!AG62) -> 4659850000 | AH6: =Parameter!$B$65*('Operations plan'!AH59+'Operations plan'!AH62) -> 5182450000 | AI6: =Parameter!$B$65*('Operations plan'!AI59+'Operations plan'!AI62) -> 5182450000 | AJ6: =Parameter!$B$65*('Operations plan'!AJ59+'Operations plan'!AJ62) -> 5182450000 | AK6: =Parameter!$B$65*('Operations plan'!AK59+'Operations plan'!AK62) -> 5353300000 | AL6: =Parameter!$B$65*('Operations plan'!AL59+'Operations plan'!AL62) -> 5353300000 | ... AP6: =Parameter!$B$65*('Operations plan'!AP59+'Operations plan'!AP62) -> 5648100000
A7: Product 2: E-bikes | E7: =Parameter!$B$66*('Operations plan'!E60+'Operations plan'!E63) -> 0 | F7: =Parameter!$B$66*('Operations plan'!F60+'Operations plan'!F63) -> 0 | G7: =Parameter!$B$66*('Operations plan'!G60+'Operations plan'!G63) -> 0 | H7: =Parameter!$B$66*('Operations plan'!H60+'Operations plan'!H63) -> 0 | I7: =Parameter!$B$66*('Operations plan'!I60+'Operations plan'!I63) -> 0 | J7: =Parameter!$B$66*('Operations plan'!J60+'Operations plan'!J63) -> 0 | K7: =Parameter!$B$66*('Operations plan'!K60+'Operations plan'!K63) -> 0 | L7: =Parameter!$B$66*('Operations plan'!L60+'Operations plan'!L63) -> 0 | ... P7: =Parameter!$B$66*('Operations plan'!P60+'Operations plan'!P63) -> 0 | R7: =Parameter!$B$66*('Operations plan'!R60+'Operations plan'!R63) -> 0 | S7: =Parameter!$B$66*('Operations plan'!S60+'Operations plan'!S63) -> 0 | T7: =Parameter!$B$66*('Operations plan'!T60+'Operations plan'!T63) -> 0 | U7: =Parameter!$B$66*('Operations plan'!U60+'Operations plan'!U63) -> 0 | V7: =Parameter!$B$66*('Operations plan'!V60+'Operations plan'!V63) -> 0 | W7: =Parameter!$B$66*('Operations plan'!W60+'Operations plan'!W63) -> 0 | X7: =Parameter!$B$66*('Operations plan'!X60+'Operations plan'!X63) -> 0 | Y7: =Parameter!$B$66*('Operations plan'!Y60+'Operations plan'!Y63) -> 0 | ... AC7: =Parameter!$B$66*('Operations plan'!AC60+'Operations plan'!AC63) -> 3240000000 | AE7: =Parameter!$B$66*('Operations plan'!AE60+'Operations plan'!AE63) -> 2808000000 | AF7: =Parameter!$B$66*('Operations plan'!AF60+'Operations plan'!AF63) -> 2700000000 | AG7: =Parameter!$B$66*('Operations plan'!AG60+'Operations plan'!AG63) -> 2700000000 | AH7: =Parameter!$B$66*('Operations plan'!AH60+'Operations plan'!AH63) -> 4482000000 | AI7: =Parameter!$B$66*('Operations plan'!AI60+'Operations plan'!AI63) -> 4482000000 | AJ7: =Parameter!$B$66*('Operations plan'!AJ60+'Operations plan'!AJ63) -> 4482000000 | AK7: =Parameter!$B$66*('Operations plan'!AK60+'Operations plan'!AK63) -> 4795200000 | AL7: =Parameter!$B$66*('Operations plan'!AL60+'Operations plan'!AL63) -> 4795200000 | ... AP7: =Parameter!$B$66*('Operations plan'!AP60+'Operations plan'!AP63) -> 5216400000
A8: Salaries-Direct | E8: ='Paycheck schedule'!J$6 -> 0 | F8: ='Paycheck schedule'!K$6 -> 4761904.8 | G8: ='Paycheck schedule'!L$6 -> 3.5181818e+08 | H8: ='Paycheck schedule'!M$6 -> 6.5234783e+08 | I8: ='Paycheck schedule'!N$6 -> 8.0304348e+08 | J8: ='Paycheck schedule'!O$6 -> 8.2157143e+08 | K8: ='Paycheck schedule'!P$6 -> 909875000 | L8: ='Paycheck schedule'!Q$6 -> 958000000 | ... P8: ='Paycheck schedule'!U$6 -> 968000000 | R8: ='Paycheck schedule'!W$6 -> 958000000 | S8: ='Paycheck schedule'!X$6 -> 988750000 | T8: ='Paycheck schedule'!Y$6 -> 1062000000 | U8: ='Paycheck schedule'!Z$6 -> 1062000000 | V8: ='Paycheck schedule'!AA$6 -> 1062000000 | W8: ='Paycheck schedule'!AB$6 -> 1062000000 | X8: ='Paycheck schedule'!AC$6 -> 1062000000 | Y8: ='Paycheck schedule'!AD$6 -> 1062000000 | ... AC8: ='Paycheck schedule'!AH$6 -> 1072000000 | AE8: ='Paycheck schedule'!AJ$6 -> 1062000000 | AF8: ='Paycheck schedule'!AK$6 -> 1062000000 | AG8: ='Paycheck schedule'!AL$6 -> 1062000000 | AH8: ='Paycheck schedule'!AM$6 -> 1062000000 | AI8: ='Paycheck schedule'!AN$6 -> 1062000000 | AJ8: ='Paycheck schedule'!AO$6 -> 1062000000 | AK8: ='Paycheck schedule'!AP$6 -> 1062000000 | AL8: ='Paycheck schedule'!AQ$6 -> 1062000000 | ... AP8: ='Paycheck schedule'!AU$6 -> 1062000000
A9: Factory rent | E9: 240000000 | F9: 240000000 | G9: 240000000 | H9: 240000000 | I9: 240000000 | J9: 240000000 | K9: 240000000 | L9: 240000000 | M9: 240000000 | N9: 240000000 | O9: 240000000 | P9: 240000000 | R9: 240000000 | S9: 240000000 | T9: 240000000 | U9: 240000000 | V9: 240000000 | W9: 240000000 | X9: 240000000 | Y9: 240000000 | Z9: 240000000 | AA9: 240000000 | AB9: 240000000 | AC9: 240000000 | AE9: 240000000 | AF9: 240000000 | AG9: 240000000 | AH9: 240000000 | AI9: 240000000 | AJ9: 240000000 | AK9: 240000000 | AL9: 240000000 | AM9: 240000000 | AN9: 240000000 | AO9: 240000000 | AP9: 240000000
A10: Depreciation-Direct | E10: ='Spending {supplement}'!F11 -> 0 | F10: ='Spending {supplement}'!G11 -> 2.209863e+08 | G10: ='Spending {supplement}'!H11 -> 2.6583914e+08 | H10: ='Spending {supplement}'!I11 -> 2.6222701e+08 | I10: ='Spending {supplement}'!J11 -> 2.7096791e+08 | J10: ='Spending {supplement}'!K11 -> 5.8534051e+08 | K10: ='Spending {supplement}'!L11 -> 6.2396145e+08 | L10: ='Spending {supplement}'!M11 -> 6.2396145e+08 | ... P10: ='Spending {supplement}'!Q11 -> 6.2396145e+08 | R10: ='Spending {supplement}'!S11 -> 6.2396145e+08 | S10: ='Spending {supplement}'!T11 -> 5.6357808e+08 | T10: ='Spending {supplement}'!U11 -> 6.2396145e+08 | U10: ='Spending {supplement}'!V11 -> 6.0383366e+08 | V10: ='Spending {supplement}'!W11 -> 6.2396145e+08 | W10: ='Spending {supplement}'!X11 -> 6.0383366e+08 | X10: ='Spending {supplement}'!Y11 -> 6.2396145e+08 | Y10: ='Spending {supplement}'!Z11 -> 6.2396145e+08 | ... AC10: ='Spending {supplement}'!AD11 -> 6.2396145e+08 | AE10: ='Spending {supplement}'!AF11 -> 6.2396145e+08 | AF10: ='Spending {supplement}'!AG11 -> 5.6357808e+08 | AG10: ='Spending {supplement}'!AH11 -> 6.2396145e+08 | AH10: ='Spending {supplement}'!AI11 -> 6.0383366e+08 | AI10: ='Spending {supplement}'!AJ11 -> 6.2396145e+08 | AJ10: ='Spending {supplement}'!AK11 -> 6.0383366e+08 | AK10: ='Spending {supplement}'!AL11 -> 6.2396145e+08 | AL10: ='Spending {supplement}'!AM11 -> 6.2396145e+08 | ... AP10: ='Spending {supplement}'!AQ11 -> 6.2396145e+08
A11: Other Direct Costs: Factory ultilities | E11: =Parameter!$B$81*'Operations plan'!E77 -> 0 | F11: =Parameter!$B$81*'Operations plan'!F77 -> 0 | G11: =Parameter!$B$81*'Operations plan'!G77 -> 0 | H11: =Parameter!$B$81*'Operations plan'!H77 -> 0 | I11: =Parameter!$B$81*'Operations plan'!I77 -> 19180000 | J11: =Parameter!$B$81*'Operations plan'!J77 -> 84000000 | K11: =Parameter!$B$81*'Operations plan'!K77 -> 85330000 | L11: =Parameter!$B$81*'Operations plan'!L77 -> 94500000 | ... P11: =Parameter!$B$81*'Operations plan'!P77 -> 97230000 | R11: =Parameter!$B$81*'Operations plan'!R77 -> 84280000 | S11: =Parameter!$B$81*'Operations plan'!S77 -> 84280000 | T11: =Parameter!$B$81*'Operations plan'!T77 -> 86590000 | U11: =Parameter!$B$81*'Operations plan'!U77 -> 103320000 | V11: =Parameter!$B$81*'Operations plan'!V77 -> 103320000 | W11: =Parameter!$B$81*'Operations plan'!W77 -> 103810000 | X11: =Parameter!$B$81*'Operations plan'!X77 -> 107240000 | Y11: =Parameter!$B$81*'Operations plan'!Y77 -> 107240000 | ... AC11: =Parameter!$B$81*'Operations plan'!AC77 -> 131460000 | AE11: =Parameter!$B$81*'Operations plan'!AE77 -> 115570000 | AF11: =Parameter!$B$81*'Operations plan'!AF77 -> 114870000 | AG11: =Parameter!$B$81*'Operations plan'!AG77 -> 117530000 | AH11: =Parameter!$B$81*'Operations plan'!AH77 -> 137340000 | AI11: =Parameter!$B$81*'Operations plan'!AI77 -> 137340000 | AJ11: =Parameter!$B$81*'Operations plan'!AJ77 -> 137970000 | AK11: =Parameter!$B$81*'Operations plan'!AK77 -> 142940000 | AL11: =Parameter!$B$81*'Operations plan'!AL77 -> 143220000 | ... AP11: =Parameter!$B$81*'Operations plan'!AP77 -> 133420000
A12: TOTAL COST OF GOODS SOLD | E12: =SUM(E6:E11) -> 240000000 | F12: =SUM(F6:F11) -> 4.6574821e+08 | G12: =SUM(G6:G11) -> 8.5765732e+08 | H12: =SUM(H6:H11) -> 1.1545748e+09 | I12: =SUM(I6:I11) -> 1.3331914e+09 | J12: =SUM(J6:J11) -> 5.7509119e+09 | K12: =SUM(K6:K11) -> 5.8791664e+09 | L12: =SUM(L6:L11) -> 6.4389614e+09 | ... P12: =SUM(P6:P11) -> 6.6694414e+09 | R12: =SUM(R6:R11) -> 5.9396414e+09 | S12: =SUM(S6:S11) -> 5.9100081e+09 | T12: =SUM(T6:T11) -> 6.0459514e+09 | U12: =SUM(U6:U11) -> 6.9537537e+09 | V12: =SUM(V6:V11) -> 6.9738814e+09 | W12: =SUM(W6:W11) -> 6.9542437e+09 | X12: =SUM(X6:X11) -> 7.1654014e+09 | Y12: =SUM(Y6:Y11) -> 7.1654014e+09 | ... AC12: =SUM(AC6:AC11) -> 1.0690871e+10 | AE12: =SUM(AE6:AE11) -> 9.5093814e+09 | AF12: =SUM(AF6:AF11) -> 9.3402981e+09 | AG12: =SUM(AG6:AG11) -> 9.4033414e+09 | AH12: =SUM(AH6:AH11) -> 1.1707624e+10 | AI12: =SUM(AI6:AI11) -> 1.1727751e+10 | AJ12: =SUM(AJ6:AJ11) -> 1.1708254e+10 | AK12: =SUM(AK6:AK11) -> 1.2217401e+10 | AL12: =SUM(AL6:AL11) -> 1.2217681e+10 | ... AP12: =SUM(AP6:AP11) -> 1.2923881e+10
A14: OPERATING EXPENSES
A15: Automobile/Transportation
A16: Bank Service Charges
A17: Business Licenses and Permits
A18: Computer and Internet
A19: Dues and Subscriptions
A20: Insurance | E20: =IFERROR(__xludf.DUMMYFUNCTION("Parameter!$B$89*Parameter!$B$90*(COUNTIF('Paycheck schedule'!J7:J83, "">""&0)-COUNT(FILTER('Paycheck schedule'!$A7:$A83, 'Paycheck schedule'!$A7:$A83 <= 'Paycheck schedule'!J4, NETWORKDAYS('Paycheck schedule'!$A7:$A83,'Paycheck schedule'!J4) < 15)))"),0) -> 0 | F20: =IFERROR(__xludf.DUMMYFUNCTION("Parameter!$B$89*Parameter!$B$90*(COUNTIF('Paycheck schedule'!K7:K83, "">""&0)-COUNT(FILTER('Paycheck schedule'!$A7:$A83, 'Paycheck schedule'!$A7:$A83 <= 'Paycheck schedule'!K4, NETWORKDAYS('Paycheck schedule'!$A7:$A83,'Paycheck schedule'!K4) < 15)))"),0) -> 0 | G20: =IFERROR(__xludf.DUMMYFUNCTION("Parameter!$B$89*Parameter!$B$90*(COUNTIF('Paycheck schedule'!L7:L83, "">""&0)-COUNT(FILTER('Paycheck schedule'!$A7:$A83, 'Paycheck schedule'!$A7:$A83 <= 'Paycheck schedule'!L4, NETWORKDAYS('Paycheck schedule'!$A7:$A83,'Paycheck schedule'!L4) < 15)))"),6656000) -> 6656000 | H20: =IFERROR(__xludf.DUMMYFUNCTION("Parameter!$B$89*Parameter!$B$90*(COUNTIF('Paycheck schedule'!M7:M83, "">""&0)-COUNT(FILTER('Paycheck schedule'!$A7:$A83, 'Paycheck schedule'!$A7:$A83 <= 'Paycheck schedule'!M4, NETWORKDAYS('Paycheck schedule'!$A7:$A83,'Paycheck schedule'!M4) < 15)))"),19968000) -> 19968000 | I20: =IFERROR(__xludf.DUMMYFUNCTION("Parameter!$B$89*Parameter!$B$90*(COUNTIF('Paycheck schedule'!N7:N83, "">""&0)-COUNT(FILTER('Paycheck schedule'!$A7:$A83, 'Paycheck schedule'!$A7:$A83 <= 'Paycheck schedule'!N4, NETWORKDAYS('Paycheck schedule'!$A7:$A83,'Paycheck schedule'!N4) < 15)))"),31616000) -> 31616000 | J20: =IFERROR(__xludf.DUMMYFUNCTION("Parameter!$B$89*Parameter!$B$90*(COUNTIF('Paycheck schedule'!O7:O83, "">""&0)-COUNT(FILTER('Paycheck schedule'!$A7:$A83, 'Paycheck schedule'!$A7:$A83 <= 'Paycheck schedule'!O4, NETWORKDAYS('Paycheck schedule'!$A7:$A83,'Paycheck schedule'!O4) < 15)))"),33280000) -> 33280000 | K20: =IFERROR(__xludf.DUMMYFUNCTION("Parameter!$B$89*Parameter!$B$90*(COUNTIF('Paycheck schedule'!P7:P83, "">""&0)-COUNT(FILTER('Paycheck schedule'!$A7:$A83, 'Paycheck schedule'!$A7:$A83 <= 'Paycheck schedule'!P4, NETWORKDAYS('Paycheck schedule'!$A7:$A83,'Paycheck schedule'!P4) < 15)))"),34944000) -> 34944000 | L20: =IFERROR(__xludf.DUMMYFUNCTION("Parameter!$B$89*Parameter!$B$90*(COUNTIF('Paycheck schedule'!Q7:Q83, "">""&0)-COUNT(FILTER('Paycheck schedule'!$A7:$A83, 'Paycheck schedule'!$A7:$A83 <= 'Paycheck schedule'!Q4, NETWORKDAYS('Paycheck schedule'!$A7:$A83,'Paycheck schedule'!Q4) < 15)))"),38272000) -> 38272000 | M20: =IFERROR(__xludf.DUMMYFUNCTION("Parameter!$B$89*Parameter!$B$90*(COUNTIF('Paycheck schedule'!R7:R83, "">""&0)-COUNT(FILTER('Paycheck schedule'!$A7:$A83, 'Paycheck schedule'!$A7:$A83 <= 'Paycheck schedule'!R4, NETWORKDAYS('Paycheck schedule'!$A7:$A83,'Paycheck schedule'!R4) < 15)))"),38272000) -> 38272000 | N20: =IFERROR(__xludf.DUMMYFUNCTION("Parameter!$B$89*Parameter!$B$90*(COUNTIF('Paycheck schedule'!S7:S83, "">""&0)-COUNT(FILTER('Paycheck schedule'!$A7:$A83, 'Paycheck schedule'!$A7:$A83 <= 'Paycheck schedule'!S4, NETWORKDAYS('Paycheck schedule'!$A7:$A83,'Paycheck schedule'!S4) < 15)))"),38272000) -> 38272000 | O20: =IFERROR(__xludf.DUMMYFUNCTION("Parameter!$B$89*Parameter!$B$90*(COUNTIF('Paycheck schedule'!T7:T83, "">""&0)-COUNT(FILTER('Paycheck schedule'!$A7:$A83, 'Paycheck schedule'!$A7:$A83 <= 'Paycheck schedule'!T4, NETWORKDAYS('Paycheck schedule'!$A7:$A83,'Paycheck schedule'!T4) < 15)))"),38272000) -> 38272000 | P20: =IFERROR(__xludf.DUMMYFUNCTION("Parameter!$B$89*Parameter!$B$90*(COUNTIF('Paycheck schedule'!U7:U83, "">""&0)-COUNT(FILTER('Paycheck schedule'!$A7:$A83, 'Paycheck schedule'!$A7:$A83 <= 'Paycheck schedule'!U4, NETWORKDAYS('Paycheck schedule'!$A7:$A83,'Paycheck schedule'!U4) < 15)))"),38272000) -> 38272000 | R20: =IFERROR(__xludf.DUMMYFUNCTION("Parameter!$B$89*Parameter!$B$90*(COUNTIF('Paycheck schedule'!W7:W83, "">""&0)-COUNT(FILTER('Paycheck schedule'!$A7:$A83, 'Paycheck schedule'!$A7:$A83 <= 'Paycheck schedule'!W4, NETWORKDAYS('Paycheck schedule'!$A7:$A83,'Paycheck schedule'!W4) < 15)))"),38272000) -> 38272000 | S20: =IFERROR(__xludf.DUMMYFUNCTION("Parameter!$B$89*Parameter!$B$90*(COUNTIF('Paycheck schedule'!X7:X83, "">""&0)-COUNT(FILTER('Paycheck schedule'!$A7:$A83, 'Paycheck schedule'!$A7:$A83 <= 'Paycheck schedule'!X4, NETWORKDAYS('Paycheck schedule'!$A7:$A83,'Paycheck schedule'!X4) < 15)))"),38272000) -> 38272000 | T20: =IFERROR(__xludf.DUMMYFUNCTION("Parameter!$B$89*Parameter!$B$90*(COUNTIF('Paycheck schedule'!Y7:Y83, "">""&0)-COUNT(FILTER('Paycheck schedule'!$A7:$A83, 'Paycheck schedule'!$A7:$A83 <= 'Paycheck schedule'!Y4, NETWORKDAYS('Paycheck schedule'!$A7:$A83,'Paycheck schedule'!Y4) < 15)))"),46592000) -> 46592000 | U20: =IFERROR(__xludf.DUMMYFUNCTION("Parameter!$B$89*Parameter!$B$90*(COUNTIF('Paycheck schedule'!Z7:Z83, "">""&0)-COUNT(FILTER('Paycheck schedule'!$A7:$A83, 'Paycheck schedule'!$A7:$A83 <= 'Paycheck schedule'!Z4, NETWORKDAYS('Paycheck schedule'!$A7:$A83,'Paycheck schedule'!Z4) < 15)))"),46592000) -> 46592000 | V20: =IFERROR(__xludf.DUMMYFUNCTION("Parameter!$B$89*Parameter!$B$90*(COUNTIF('Paycheck schedule'!AA7:AA83, "">""&0)-COUNT(FILTER('Paycheck schedule'!$A7:$A83, 'Paycheck schedule'!$A7:$A83 <= 'Paycheck schedule'!AA4, NETWORKDAYS('Paycheck schedule'!$A7:$A83,'Paycheck schedule'!AA4) < 15)))"),46592000) -> 46592000 | W20: =IFERROR(__xludf.DUMMYFUNCTION("Parameter!$B$89*Parameter!$B$90*(COUNTIF('Paycheck schedule'!AB7:AB83, "">""&0)-COUNT(FILTER('Paycheck schedule'!$A7:$A83, 'Paycheck schedule'!$A7:$A83 <= 'Paycheck schedule'!AB4, NETWORKDAYS('Paycheck schedule'!$A7:$A83,'Paycheck schedule'!AB4) < 15)))"),46592000) -> 46592000 | X20: =IFERROR(__xludf.DUMMYFUNCTION("Parameter!$B$89*Parameter!$B$90*(COUNTIF('Paycheck schedule'!AC7:AC83, "">""&0)-COUNT(FILTER('Paycheck schedule'!$A7:$A83, 'Paycheck schedule'!$A7:$A83 <= 'Paycheck schedule'!AC4, NETWORKDAYS('Paycheck schedule'!$A7:$A83,'Paycheck schedule'!AC4) < 15)))"),46592000) -> 46592000 | Y20: =IFERROR(__xludf.DUMMYFUNCTION("Parameter!$B$89*Parameter!$B$90*(COUNTIF('Paycheck schedule'!AD7:AD83, "">""&0)-COUNT(FILTER('Paycheck schedule'!$A7:$A83, 'Paycheck schedule'!$A7:$A83 <= 'Paycheck schedule'!AD4, NETWORKDAYS('Paycheck schedule'!$A7:$A83,'Paycheck schedule'!AD4) < 15)))"),46592000) -> 46592000 | Z20: =IFERROR(__xludf.DUMMYFUNCTION("Parameter!$B$89*Parameter!$B$90*(COUNTIF('Paycheck schedule'!AE7:AE83, "">""&0)-COUNT(FILTER('Paycheck schedule'!$A7:$A83, 'Paycheck schedule'!$A7:$A83 <= 'Paycheck schedule'!AE4, NETWORKDAYS('Paycheck schedule'!$A7:$A83,'Paycheck schedule'!AE4) < 15)))"),46592000) -> 46592000 | AA20: =IFERROR(__xludf.DUMMYFUNCTION("Parameter!$B$89*Parameter!$B$90*(COUNTIF('Paycheck schedule'!AF7:AF83, "">""&0)-COUNT(FILTER('Paycheck schedule'!$A7:$A83, 'Paycheck schedule'!$A7:$A83 <= 'Paycheck schedule'!AF4, NETWORKDAYS('Paycheck schedule'!$A7:$A83,'Paycheck schedule'!AF4) < 15)))"),46592000) -> 46592000 | AB20: =IFERROR(__xludf.DUMMYFUNCTION("Parameter!$B$89*Parameter!$B$90*(COUNTIF('Paycheck schedule'!AG7:AG83, "">""&0)-COUNT(FILTER('Paycheck schedule'!$A7:$A83, 'Paycheck schedule'!$A7:$A83 <= 'Paycheck schedule'!AG4, NETWORKDAYS('Paycheck schedule'!$A7:$A83,'Paycheck schedule'!AG4) < 15)))"),46592000) -> 46592000 | AC20: =IFERROR(__xludf.DUMMYFUNCTION("Parameter!$B$89*Parameter!$B$90*(COUNTIF('Paycheck schedule'!AH7:AH83, "">""&0)-COUNT(FILTER('Paycheck schedule'!$A7:$A83, 'Paycheck schedule'!$A7:$A83 <= 'Paycheck schedule'!AH4, NETWORKDAYS('Paycheck schedule'!$A7:$A83,'Paycheck schedule'!AH4) < 15)))"),46592000) -> 46592000 | AE20: =IFERROR(__xludf.DUMMYFUNCTION("Parameter!$B$89*Parameter!$B$90*(COUNTIF('Paycheck schedule'!AJ7:AJ83, "">""&0)-COUNT(FILTER('Paycheck schedule'!$A7:$A83, 'Paycheck schedule'!$A7:$A83 <= 'Paycheck schedule'!AJ4, NETWORKDAYS('Paycheck schedule'!$A7:$A83,'Paycheck schedule'!AJ4) < 15)))"),46592000) -> 46592000 | AF20: =IFERROR(__xludf.DUMMYFUNCTION("Parameter!$B$89*Parameter!$B$90*(COUNTIF('Paycheck schedule'!AK7:AK83, "">""&0)-COUNT(FILTER('Paycheck schedule'!$A7:$A83, 'Paycheck schedule'!$A7:$A83 <= 'Paycheck schedule'!AK4, NETWORKDAYS('Paycheck schedule'!$A7:$A83,'Paycheck schedule'!AK4) < 15)))"),46592000) -> 46592000 | AG20: =IFERROR(__xludf.DUMMYFUNCTION("Parameter!$B$89*Parameter!$B$90*(COUNTIF('Paycheck schedule'!AL7:AL83, "">""&0)-COUNT(FILTER('Paycheck schedule'!$A7:$A83, 'Paycheck schedule'!$A7:$A83 <= 'Paycheck schedule'!AL4, NETWORKDAYS('Paycheck schedule'!$A7:$A83,'Paycheck schedule'!AL4) < 15)))"),46592000) -> 46592000 | AH20: =IFERROR(__xludf.DUMMYFUNCTION("Parameter!$B$89*Parameter!$B$90*(COUNTIF('Paycheck schedule'!AM7:AM83, "">""&0)-COUNT(FILTER('Paycheck schedule'!$A7:$A83, 'Paycheck schedule'!$A7:$A83 <= 'Paycheck schedule'!AM4, NETWORKDAYS('Paycheck schedule'!$A7:$A83,'Paycheck schedule'!AM4) < 15)))"),46592000) -> 46592000 | AI20: =IFERROR(__xludf.DUMMYFUNCTION("Parameter!$B$89*Parameter!$B$90*(COUNTIF('Paycheck schedule'!AN7:AN83, "">""&0)-COUNT(FILTER('Paycheck schedule'!$A7:$A83, 'Paycheck schedule'!$A7:$A83 <= 'Paycheck schedule'!AN4, NETWORKDAYS('Paycheck schedule'!$A7:$A83,'Paycheck schedule'!AN4) < 15)))"),46592000) -> 46592000 | AJ20: =IFERROR(__xludf.DUMMYFUNCTION("Parameter!$B$89*Parameter!$B$90*(COUNTIF('Paycheck schedule'!AO7:AO83, "">""&0)-COUNT(FILTER('Paycheck schedule'!$A7:$A83, 'Paycheck schedule'!$A7:$A83 <= 'Paycheck schedule'!AO4, NETWORKDAYS('Paycheck schedule'!$A7:$A83,'Paycheck schedule'!AO4) < 15)))"),46592000) -> 46592000 | AK20: =IFERROR(__xludf.DUMMYFUNCTION("Parameter!$B$89*Parameter!$B$90*(COUNTIF('Paycheck schedule'!AP7:AP83, "">""&0)-COUNT(FILTER('Paycheck schedule'!$A7:$A83, 'Paycheck schedule'!$A7:$A83 <= 'Paycheck schedule'!AP4, NETWORKDAYS('Paycheck schedule'!$A7:$A83,'Paycheck schedule'!AP4) < 15)))"),46592000) -> 46592000 | AL20: =IFERROR(__xludf.DUMMYFUNCTION("Parameter!$B$89*Parameter!$B$90*(COUNTIF('Paycheck schedule'!AQ7:AQ83, "">""&0)-COUNT(FILTER('Paycheck schedule'!$A7:$A83, 'Paycheck schedule'!$A7:$A83 <= 'Paycheck schedule'!AQ4, NETWORKDAYS('Paycheck schedule'!$A7:$A83,'Paycheck schedule'!AQ4) < 15)))"),46592000) -> 46592000 | AM20: =IFERROR(__xludf.DUMMYFUNCTION("Parameter!$B$89*Parameter!$B$90*(COUNTIF('Paycheck schedule'!AR7:AR83, "">""&0)-COUNT(FILTER('Paycheck schedule'!$A7:$A83, 'Paycheck schedule'!$A7:$A83 <= 'Paycheck schedule'!AR4, NETWORKDAYS('Paycheck schedule'!$A7:$A83,'Paycheck schedule'!AR4) < 15)))"),46592000) -> 46592000 | AN20: =IFERROR(__xludf.DUMMYFUNCTION("Parameter!$B$89*Parameter!$B$90*(COUNTIF('Paycheck schedule'!AS7:AS83, "">""&0)-COUNT(FILTER('Paycheck schedule'!$A7:$A83, 'Paycheck schedule'!$A7:$A83 <= 'Paycheck schedule'!AS4, NETWORKDAYS('Paycheck schedule'!$A7:$A83,'Paycheck schedule'!AS4) < 15)))"),46592000) -> 46592000 | AO20: =IFERROR(__xludf.DUMMYFUNCTION("Parameter!$B$89*Parameter!$B$90*(COUNTIF('Paycheck schedule'!AT7:AT83, "">""&0)-COUNT(FILTER('Paycheck schedule'!$A7:$A83, 'Paycheck schedule'!$A7:$A83 <= 'Paycheck schedule'!AT4, NETWORKDAYS('Paycheck schedule'!$A7:$A83,'Paycheck schedule'!AT4) < 15)))"),46592000) -> 46592000 | AP20: =IFERROR(__xludf.DUMMYFUNCTION("Parameter!$B$89*Parameter!$B$90*(COUNTIF('Paycheck schedule'!AU7:AU83, "">""&0)-COUNT(FILTER('Paycheck schedule'!$A7:$A83, 'Paycheck schedule'!$A7:$A83 <= 'Paycheck schedule'!AU4, NETWORKDAYS('Paycheck schedule'!$A7:$A83,'Paycheck schedule'!AU4) < 15)))"),46592000) -> 46592000
A21: Marketing | E21: ='Marketing plan'!E40 -> 61250000 | F21: ='Marketing plan'!F40 -> 61250000 | G21: ='Marketing plan'!G40 -> 61250000 | H21: ='Marketing plan'!H40 -> 58750000 | I21: ='Marketing plan'!I40 -> 69750000 | J21: ='Marketing plan'!J40 -> 323190000 | K21: ='Marketing plan'!K40 -> 311690000 | L21: ='Marketing plan'!L40 -> 160750000 | ... P21: ='Marketing plan'!P40 -> 675018000 | R21: ='Marketing plan'!R40 -> 150001600 | S21: ='Marketing plan'!S40 -> 382219600 | T21: ='Marketing plan'!T40 -> 151001600 | U21: ='Marketing plan'!U40 -> 57250000 | V21: ='Marketing plan'!V40 -> 285440800 | W21: ='Marketing plan'!W40 -> 359606000 | X21: ='Marketing plan'!X40 -> 484350800 | Y21: ='Marketing plan'!Y40 -> 192022800 | ... AC21: ='Marketing plan'!AC40 -> 1112420000 | AE21: ='Marketing plan'!AE40 -> 635943900 | AF21: ='Marketing plan'!AF40 -> 608644900 | AG21: ='Marketing plan'!AG40 -> 227423900 | AH21: ='Marketing plan'!AH40 -> 173500000 | AI21: ='Marketing plan'!AI40 -> 893299200 | AJ21: ='Marketing plan'!AJ40 -> 661120000 | AK21: ='Marketing plan'!AK40 -> 533396300 | AL21: ='Marketing plan'!AL40 -> 276379800 | ... AP21: ='Marketing plan'!AP40 -> 1263392000
A22: Meals and Entertainment
A23: Merchant Account Fees
A24: Miscellaneous Expense
A25: Occupancy
A26: Office Supplies | E26: 0 | F26: 0 | G26: 3500000 | H26: 3500000 | I26: 3500000 | J26: 5000000 | K26: 5000000 | L26: 5000000 | M26: 5000000 | N26: 5000000 | O26: 5000000 | P26: 5000000 | R26: 5000000 | S26: 5000000 | T26: 5000000 | U26: 5000000 | V26: 5000000 | W26: 5000000 | X26: 5000000 | Y26: 5000000 | Z26: 5000000 | AA26: 5500000 | AB26: 5500000 | AC26: 5500000 | AE26: 5500000 | AF26: 5500000 | AG26: 5500000 | AH26: 5500000 | AI26: 5500000 | AJ26: 5500000 | AK26: 5500000 | AL26: 5500000 | AM26: 5500000 | AN26: 5500000 | AO26: 5500000 | AP26: 5500000
A27: Postage and Delivery
A28: Printing and Reproduction
A29: Professional Services - Legal, Accounting
A30: Rental Payments | E30: ='Spending {supplement}'!F8 -> 0 | F30: ='Spending {supplement}'!G8 -> 50000000 | G30: ='Spending {supplement}'!H8 -> 50000000 | H30: ='Spending {supplement}'!I8 -> 50000000 | I30: ='Spending {supplement}'!J8 -> 50000000 | J30: ='Spending {supplement}'!K8 -> 170000000 | K30: ='Spending {supplement}'!L8 -> 170000000 | L30: ='Spending {supplement}'!M8 -> 170000000 | ... P30: ='Spending {supplement}'!Q8 -> 170000000 | R30: ='Spending {supplement}'!S8 -> 170000000 | S30: ='Spending {supplement}'!T8 -> 170000000 | T30: ='Spending {supplement}'!U8 -> 170000000 | U30: ='Spending {supplement}'!V8 -> 170000000 | V30: ='Spending {supplement}'!W8 -> 170000000 | W30: ='Spending {supplement}'!X8 -> 170000000 | X30: ='Spending {supplement}'!Y8 -> 170000000 | Y30: ='Spending {supplement}'!Z8 -> 170000000 | ... AC30: ='Spending {supplement}'!AD8 -> 170000000 | AE30: ='Spending {supplement}'!AF8 -> 170000000 | AF30: ='Spending {supplement}'!AG8 -> 170000000 | AG30: ='Spending {supplement}'!AH8 -> 170000000 | AH30: ='Spending {supplement}'!AI8 -> 170000000 | AI30: ='Spending {supplement}'!AJ8 -> 170000000 | AJ30: ='Spending {supplement}'!AK8 -> 170000000 | AK30: ='Spending {supplement}'!AL8 -> 170000000 | AL30: ='Spending {supplement}'!AM8 -> 170000000 | ... AP30: ='Spending {supplement}'!AQ8 -> 170000000
A31: Salaries-Indirect | E31: ='Paycheck schedule'!J$5 -> 0 | F31: ='Paycheck schedule'!K$5 -> 0 | G31: ='Paycheck schedule'!L$5 -> 0 | H31: ='Paycheck schedule'!M$5 -> 0 | I31: ='Paycheck schedule'!N$5 -> 0 | J31: ='Paycheck schedule'!O$5 -> 439992000 | K31: ='Paycheck schedule'!P$5 -> 439992000 | L31: ='Paycheck schedule'!Q$5 -> 498657600 | ... P31: ='Paycheck schedule'!U$5 -> 522694200 | R31: ='Paycheck schedule'!W$5 -> 1053066000 | S31: ='Paycheck schedule'!X$5 -> 444066000 | T31: ='Paycheck schedule'!Y$5 -> 444066000 | U31: ='Paycheck schedule'!Z$5 -> 545101200 | V31: ='Paycheck schedule'!AA$5 -> 545101200 | W31: ='Paycheck schedule'!AB$5 -> 545101200 | X31: ='Paycheck schedule'!AC$5 -> 565471200 | Y31: ='Paycheck schedule'!AD$5 -> 565471200 | ... AC31: ='Paycheck schedule'!AH$5 -> 885019800 | AE31: ='Paycheck schedule'!AJ$5 -> 1483893200 | AF31: ='Paycheck schedule'!AK$5 -> 760099200 | AG31: ='Paycheck schedule'!AL$5 -> 760099200 | AH31: ='Paycheck schedule'!AM$5 -> 980674800 | AI31: ='Paycheck schedule'!AN$5 -> 980674800 | AJ31: ='Paycheck schedule'!AO$5 -> 980674800 | AK31: ='Paycheck schedule'!AP$5 -> 1027072200 | AL31: ='Paycheck schedule'!AQ$5 -> 1027072200 | ... AP31: ='Paycheck schedule'!AU$5 -> 1099337400
A32: Subcontractor | E32: 350000000 | G32: 80000000 | J32: 180000000
A33: Telephone
A34: Travel
A35: Utilities | E35: =Parameter!$B$82+Parameter!$B$83 -> 11000000 | F35: =Parameter!$B$82+Parameter!$B$83 -> 11000000 | G35: =Parameter!$B$82+Parameter!$B$83 -> 11000000 | H35: =Parameter!$B$82+Parameter!$B$83 -> 11000000 | I35: =Parameter!$B$82+Parameter!$B$83 -> 11000000 | J35: =Parameter!$B$82+Parameter!$B$83 -> 11000000 | K35: =Parameter!$B$82+Parameter!$B$83 -> 11000000 | L35: =Parameter!$B$82+Parameter!$B$83 -> 11000000 | ... P35: =Parameter!$B$82+Parameter!$B$83 -> 11000000 | R35: =Parameter!$B$82+Parameter!$B$83 -> 11000000 | S35: =Parameter!$B$82+Parameter!$B$83 -> 11000000 | T35: =Parameter!$B$82+Parameter!$B$83 -> 11000000 | U35: =Parameter!$B$82+Parameter!$B$83 -> 11000000 | V35: =Parameter!$B$82+Parameter!$B$83 -> 11000000 | W35: =Parameter!$B$82+Parameter!$B$83 -> 11000000 | X35: =Parameter!$B$82+Parameter!$B$83 -> 11000000 | Y35: =Parameter!$B$82+Parameter!$B$83 -> 11000000 | ... AC35: =Parameter!$B$82+Parameter!$B$83 -> 11000000 | AE35: =Parameter!$B$82+Parameter!$B$83 -> 11000000 | AF35: =Parameter!$B$82+Parameter!$B$83 -> 11000000 | AG35: =Parameter!$B$82+Parameter!$B$83 -> 11000000 | AH35: =Parameter!$B$82+Parameter!$B$83 -> 11000000 | AI35: =Parameter!$B$82+Parameter!$B$83 -> 11000000 | AJ35: =Parameter!$B$82+Parameter!$B$83 -> 11000000 | AK35: =Parameter!$B$82+Parameter!$B$83 -> 11000000 | AL35: =Parameter!$B$82+Parameter!$B$83 -> 11000000 | ... AP35: =Parameter!$B$82+Parameter!$B$83 -> 11000000
A36: Website Development | E36: 10000000 | F36: 10000000 | G36: 10000000 | H36: 10000000 | I36: 10000000
A37: Other: | E37: ='Spending {supplement}'!F14 -> 0 | F37: ='Spending {supplement}'!G14 -> 0 | G37: ='Spending {supplement}'!H14 -> 8500000 | H37: ='Spending {supplement}'!I14 -> 19000000 | I37: ='Spending {supplement}'!J14 -> 7600000 | J37: ='Spending {supplement}'!K14 -> 0 | K37: ='Spending {supplement}'!L14 -> 10200000 | L37: ='Spending {supplement}'!M14 -> 0 | ... P37: ='Spending {supplement}'!Q14 -> 0 | R37: ='Spending {supplement}'!S14 -> 0 | S37: ='Spending {supplement}'!T14 -> 5500000 | T37: ='Spending {supplement}'!U14 -> 0 | U37: ='Spending {supplement}'!V14 -> 0 | V37: ='Spending {supplement}'!W14 -> 0 | W37: ='Spending {supplement}'!X14 -> 0 | X37: ='Spending {supplement}'!Y14 -> 0 | Y37: ='Spending {supplement}'!Z14 -> 0 | ... AC37: ='Spending {supplement}'!AD14 -> 4000000 | AE37: ='Spending {supplement}'!AF14 -> 0 | AF37: ='Spending {supplement}'!AG14 -> 0 | AG37: ='Spending {supplement}'!AH14 -> 0 | AH37: ='Spending {supplement}'!AI14 -> 0 | AI37: ='Spending {supplement}'!AJ14 -> 0 | AJ37: ='Spending {supplement}'!AK14 -> 0 | AK37: ='Spending {supplement}'!AL14 -> 0 | AL37: ='Spending {supplement}'!AM14 -> 0 | ... AP37: ='Spending {supplement}'!AQ14 -> 0
A38: TOTAL OPERATING EXPENSES | E38: =SUM(E15:E37) -> 432250000 | F38: =SUM(F15:F37) -> 132250000 | G38: =SUM(G15:G37) -> 230906000 | H38: =SUM(H15:H37) -> 172218000 | I38: =SUM(I15:I37) -> 183466000 | J38: =SUM(J15:J37) -> 1162462000 | K38: =SUM(K15:K37) -> 982826000 | L38: =SUM(L15:L37) -> 883679600 | ... P38: =SUM(P15:P37) -> 1421984200 | R38: =SUM(R15:R37) -> 1427339600 | S38: =SUM(S15:S37) -> 1056057600 | T38: =SUM(T15:T37) -> 827659600 | U38: =SUM(U15:U37) -> 834943200 | V38: =SUM(V15:V37) -> 1063134000 | W38: =SUM(W15:W37) -> 1137299200 | X38: =SUM(X15:X37) -> 1282414000 | Y38: =SUM(Y15:Y37) -> 990086000 | ... AC38: =SUM(AC15:AC37) -> 2234531800 | AE38: =SUM(AE15:AE37) -> 2352929100 | AF38: =SUM(AF15:AF37) -> 1601836100 | AG38: =SUM(AG15:AG37) -> 1220615100 | AH38: =SUM(AH15:AH37) -> 1387266800 | AI38: =SUM(AI15:AI37) -> 2107066000 | AJ38: =SUM(AJ15:AJ37) -> 1874886800 | AK38: =SUM(AK15:AK37) -> 1793560500 | AL38: =SUM(AL15:AL37) -> 1536544000 | ... AP38: =SUM(AP15:AP37) -> 2595821400
A42: V2 - Real | E42: 2025 | R42: 2026 | AE42: 2027
E43: Q1 | H43: Q2 | K43: Q3 | N43: Q4 | R43: Q1 | U43: Q2 | X43: Q3 | AA43: Q4 | AE43: Q1 | AH43: Q2 | AK43: Q3 | AN43: Q4
B44: Buffer | E44: 1 | F44: 2 | G44: 3 | H44: 4 | I44: 5 | J44: 6 | K44: 7 | L44: 8 | M44: 9 | N44: 10 | O44: 11 | P44: 12 | R44: 1 | S44: 2 | T44: 3 | U44: 4 | V44: 5 | W44: 6 | X44: 7 | Y44: 8 | Z44: 9 | AA44: 10 | AB44: 11 | AC44: 12 | AE44: 1 | AF44: 2 | AG44: 3 | AH44: 4 | AI44: 5 | AJ44: 6 | AK44: 7 | AL44: 8 | AM44: 9 | AN44: 10 | AO44: 11 | AP44: 12
A45: Factory rent | E45: =E9 -> 240000000 | F45: =F9 -> 240000000 | G45: =G9 -> 240000000 | H45: =H9 -> 240000000 | I45: =I9 -> 240000000 | J45: =J9 -> 240000000 | K45: =K9 -> 240000000 | L45: =L9 -> 240000000 | ... AP45: =AP9 -> 240000000
A46: Insurance | E46: =E20 -> 0 | F46: =F20 -> 0 | G46: =G20 -> 6656000 | H46: =H20 -> 19968000 | I46: =I20 -> 31616000 | J46: =J20 -> 33280000 | K46: =K20 -> 34944000 | L46: =L20 -> 38272000 | ... AP46: =AP20 -> 46592000
A47: Marketing | E47: =E21 -> 61250000 | F47: =F21 -> 61250000 | G47: =G21 -> 61250000 | H47: =H21 -> 58750000 | I47: =I21 -> 69750000 | J47: =J21 -> 323190000 | K47: =K21 -> 311690000 | L47: =L21 -> 160750000 | ... AP47: =AP21 -> 1263392000
A48: Office Supplies | E48: =E26 -> 0 | F48: =F26 -> 0 | G48: =G26 -> 3500000 | H48: =H26 -> 3500000 | I48: =I26 -> 3500000 | J48: =J26 -> 5000000 | K48: =K26 -> 5000000 | L48: =L26 -> 5000000 | ... AP48: =AP26 -> 5500000
A49: Rental Payments | E49: =E30 -> 0 | F49: =F30 -> 50000000 | G49: =G30 -> 50000000 | H49: =H30 -> 50000000 | I49: =I30 -> 50000000 | J49: =J30 -> 170000000 | K49: =K30 -> 170000000 | L49: =L30 -> 170000000 | ... AP49: =AP30 -> 170000000
A50: Salaries-Direct | E50: =E8 -> 0 | F50: =F8 -> 4761904.8 | G50: =G8 -> 3.5181818e+08 | H50: =H8 -> 6.5234783e+08 | I50: =I8 -> 8.0304348e+08 | J50: =J8 -> 8.2157143e+08 | K50: =K8 -> 909875000 | L50: =L8 -> 958000000 | ... AP50: =AP8 -> 1062000000
A51: Salaries-Indirect | E51: =E31 -> 0 | F51: =F31 -> 0 | G51: =G31 -> 0 | H51: =H31 -> 0 | I51: =I31 -> 0 | J51: =J31 -> 439992000 | K51: =K31 -> 439992000 | L51: =L31 -> 498657600 | ... AP51: =AP31 -> 1099337400
A52: Subcontractor | E52: =E32 -> 350000000 | F52: =F32 -> 0 | G52: =G32 -> 80000000 | H52: =H32 -> 0 | I52: =I32 -> 0 | J52: =J32 -> 180000000 | K52: =K32 -> 0 | L52: =L32 -> 0 | ... AP52: =AP32 -> 0
A53: Utilities | E53: =E35 -> 11000000 | F53: =F35 -> 11000000 | G53: =G35 -> 11000000 | H53: =H35 -> 11000000 | I53: =I35 -> 11000000 | J53: =J35 -> 11000000 | K53: =K35 -> 11000000 | L53: =L35 -> 11000000 | ... AP53: =AP35 -> 11000000
A54: Website Development | E54: =E36 -> 10000000 | F54: =F36 -> 10000000 | G54: =G36 -> 10000000 | H54: =H36 -> 10000000 | I54: =I36 -> 10000000 | J54: =J36 -> 0 | K54: =K36 -> 0 | L54: =L36 -> 0 | ... AP54: =AP36 -> 0
A55: Other Direct Costs: Factory ultilities | E55: =E11 -> 0 | F55: =F11 -> 0 | G55: =G11 -> 0 | H55: =H11 -> 0 | I55: =I11 -> 19180000 | J55: =J11 -> 84000000 | K55: =K11 -> 85330000 | L55: =L11 -> 94500000 | ... AP55: =AP11 -> 133420000
A56: Other: | E56: =E37 -> 0 | F56: =F37 -> 0 | G56: =G37 -> 8500000 | H56: =H37 -> 19000000 | I56: =I37 -> 7600000 | J56: =J37 -> 0 | K56: =K37 -> 10200000 | L56: =L37 -> 0 | ... AP56: =AP37 -> 0
A57: TOTAL EXPENSES | E57: =SUM(E45:E56) -> 672250000 | F57: =SUM(F45:F56) -> 3.770119e+08 | G57: =SUM(G45:G56) -> 8.2272418e+08 | H57: =SUM(H45:H56) -> 1.0645658e+09 | I57: =SUM(I45:I56) -> 1.2456895e+09 | J57: =SUM(J45:J56) -> 2.3080334e+09 | K57: =SUM(K45:K56) -> 2218031000 | L57: =SUM(L45:L56) -> 2176179600 | ... AP57: =SUM(AP45:AP56) -> 4031241400
A61: V2 - Year
B63: Buffer | E63: 2025 | F63: 2026 | G63: 2027
A64: Factory rent | E64: =SUM(E45:P45) -> 2880000000 | F64: =SUM(R45:AC45) -> 2880000000 | G64: =SUM(AE45:AP45) -> 2880000000
A65: Insurance | E65: =SUM(E46:P46) -> 317824000 | F65: =SUM(R46:AC46) -> 542464000 | G65: =SUM(AE46:AP46) -> 559104000
A66: Marketing | E66: =SUM(E47:P47) -> 2773672000 | F66: =SUM(R47:AC47) -> 5291383900 | G66: =SUM(AE47:AP47) -> 7951329300
A67: Office Supplies | E67: =SUM(E48:P48) -> 45500000 | F67: =SUM(R48:AC48) -> 61500000 | G67: =SUM(AE48:AP48) -> 66000000
A68: Rental Payments | E68: =SUM(E49:P49) -> 1390000000 | F68: =SUM(R49:AC49) -> 2040000000 | G68: =SUM(AE49:AP49) -> 2040000000
A69: Salaries-Direct | E69: =SUM(E50:P50) -> 8.3434178e+09 | F69: =SUM(R50:AC50) -> 12576750000 | G69: =SUM(AE50:AP50) -> 12744000000
A70: Salaries-Indirect | E70: =SUM(E51:P51) -> 3445381800 | F70: =SUM(R51:AC51) -> 7630425600 | G70: =SUM(AE51:AP51) -> 12338663000
A71: Subcontractor | E71: =SUM(E52:P52) -> 610000000 | F71: =SUM(R52:AC52) -> 0 | G71: =SUM(AE52:AP52) -> 0
A72: Utilities | E72: =SUM(E53:P53) -> 132000000 | F72: =SUM(R53:AC53) -> 132000000 | G72: =SUM(AE53:AP53) -> 132000000
A73: Website Development | E73: =SUM(E54:P54) -> 50000000 | F73: =SUM(R54:AC54) -> 0 | G73: =SUM(AE54:AP54) -> 0
A74: Other Direct Costs: Factory ultilities | E74: =SUM(E55:P55) -> 673400000 | F74: =SUM(R55:AC55) -> 1271690000 | G74: =SUM(AE55:AP55) -> 1628130000
A75: Other: | E75: =SUM(E56:P56) -> 45300000 | F75: =SUM(R56:AC56) -> 9500000 | G75: =SUM(AE56:AP56) -> 0
A76: TOTAL EXPENSES | E76: =SUM(E57:P57) -> 2.0706496e+10 | F76: =SUM(R57:AC57) -> 32435713500 | G76: =SUM(AE57:AP57) -> 40339226300

Sheet OP
A1: CHANGE LIST | D1: Note lại ở cột này nha còn lại t lock hết r
A2: STT | B2: Current arguement | C2: Pending resolvement | D2: Suggested arguement | E2: Disapproved | F2: Why (Optional)
C3: =COUNTIF(C4:C252,"No") -> 3 | E3: =COUNTIF(E4:E252,"Denied") -> 1
A4: 1 | B4: Material cost chưa rõ - Standard: 4,500,000 ₫ - Advanced: 6,000,000 ₫ - E-bike: 12,000,000 ₫ | C4: NO | D4: 5500000 | E4: Denied | F4: Còn e bike nữa vs lại nên chờ xong bảng cost r ms bik
A5: 2 | B5: Nhà máy - Giá thuê: chưa có - Chi phí sửa chữa: chưa có | C5: NO | D5: =80000000 -> 80000000 | E5: Approved
A6: 3 | B6: Nhà máy - Diện tích: 1100 m^2 | C6: NO | E6: FALSE
A7: 4 | C7: FALSE | D7: Bắt đầu từ đây đi | E7: FALSE
A8: 6 | B8: Office trước t3 khoảng 1-2 tuần | C8: YES | E8: FALSE
A9: 7 | B9: Xưởng trước t5 | C9: YES | E9: FALSE
A10: 8 | C10: FALSE | E10: FALSE
A11: 9 | C11: FALSE | E11: FALSE
A12: 10 | C12: FALSE | E12: FALSE
A13: 11 | C13: FALSE | E13: FALSE
A14: 12 | C14: FALSE | E14: FALSE
A15: 13 | C15: FALSE | E15: FALSE
A16: 14 | C16: FALSE | E16: FALSE
A17: 15 | C17: FALSE | E17: FALSE
A18: 16 | C18: FALSE | E18: FALSE
A19: 17 | C19: FALSE | E19: FALSE
A20: 18 | C20: FALSE | E20: FALSE
A21: 19 | C21: FALSE | E21: FALSE
... A202: 200 | C202: FALSE | E202: FALSE

Sheet FINAL BACKUP OPs PLAN
A1: tham khảo hàm (chắc chắn là có sai): | B1: BP-Financial plan.xlsx
A2: T1. SALE PLAN | B2: Bài có 3 năm khác nhau đừng có làm cho mỗi 2025 thôi nha
E3: 2025 | Q3: 2026 | AC3: 2027
E4: Q1 | H4: Q2 | K4: Q3 | N4: Q4 | Q4: Q1 | T4: Q2 | W4: Q3 | Z4: Q4 | AC4: Q1 | AF4: Q2 | AI4: Q3 | AL4: Q4
A5: Bảo | E5: 1 | F5: 2 | G5: 3 | H5: 4 | I5: 5 | J5: 6 | K5: 7 | L5: 8 | M5: 9 | N5: 10 | O5: 11 | P5: 12 | Q5: 1 | R5: 2 | S5: 3 | T5: 4 | U5: 5 | V5: 6 | W5: 7 | X5: 8 | Y5: 9 | Z5: 10 | AA5: 11 | AB5: 12 | AC5: 1 | AD5: 2 | AE5: 3 | AF5: 4 | AG5: 5 | AH5: 6 | AI5: 7 | AJ5: 8 | AK5: 9 | AL5: 10 | AM5: 11 | AN5: 12
A6: Store sales estimation | C6: =SUM(C7:C8) -> 0 | E6: =SUM(E7:E8) -> 0 | F6: =SUM(F7:F8) -> 0 | G6: =SUM(G7:G8) -> 0 | H6: =SUM(H7:H8) -> 0 | I6: =SUM(I7:I8) -> 0 | J6: =SUM(J7:J8) -> 0 | K6: =SUM(K7:K8) -> 0 | L6: =SUM(L7:L8) -> 0 | ... AN6: =SUM(AN7:AN8) -> 0
A7: Conversion Rate: | B7: Standard | D7: =C7 -> 0 | E7: 0 | F7: 0 | G7: 0 | H7: 0 | I7: 0 | J7: 0 | K7: 0 | L7: 0 | M7: 0 | N7: 0 | O7: 0 | P7: 0 | Q7: 0 | R7: 0 | S7: 0 | T7: 0 | U7: 0 | V7: 0 | W7: 0 | X7: 0 | Y7: 0 | Z7: 0 | AA7: 0 | AB7: 0 | AC7: 0 | AD7: 0 | AE7: 0 | AF7: 0 | AG7: 0 | AH7: 0 | AI7: 0 | AJ7: 0 | AK7: 0 | AL7: 0 | AM7: 0 | AN7: 0
B8: E-bike | C8: 0 | D8: =C8 -> 0 | E8: 0 | F8: 0 | G8: 0 | H8: 0 | I8: 0 | J8: 0 | K8: 0 | L8: 0 | M8: 0 | N8: 0 | O8: 0 | P8: 0 | Q8: 0 | R8: 0 | S8: 0 | T8: 0 | U8: 0 | V8: 0 | W8: 0 | X8: 0 | Y8: 0 | Z8: 0 | AA8: 0 | AB8: 0 | AC8: 0 | AD8: 0 | AE8: 0 | AF8: 0 | AG8: 0 | AH8: 0 | AI8: 0 | AJ8: 0 | AK8: 0 | AL8: 0 | AM8: 0 | AN8: 0
A9: Store vol. - Accumulating %
A10: Chỉ để xem thôi | B10: Standard | E10: =D10+E13 -> -1 | F10: =E10+F13 -> -1 | G10: =F10+G13 -> -1 | H10: =G10+H13 -> -1 | I10: =H10+I13 -> -1 | J10: =I10+J13 -> -1 | K10: =J10+K13 -> -1 | L10: =K10+L13 -> -1 | ... AN10: =AM10+AN13 -> -1
B11: E-bike | E11: =D11+E14 -> -1 | F11: =E11+F14 -> -1 | G11: =F11+G14 -> -1 | H11: =G11+H14 -> -1 | I11: =H11+I14 -> -1 | J11: =I11+J14 -> -1 | K11: =J11+K14 -> -1 | L11: =K11+L14 -> -1 | ... AN11: =AM11+AN14 -> -1
A12: Store sales adjustment
A13: Dự kiến tăng giảm store sale | B13: Standard | E13: -1
B14: E-bike | E14: -1
A15: Distributor vol. | B15: Bảo | C15: =SUM(C16:C17) -> 0 | E15: =SUM(E16:E17) -> 0 | F15: =SUM(F16:F17) -> 0 | G15: =SUM(G16:G17) -> 0 | H15: =SUM(H16:H17) -> 0 | I15: =SUM(I16:I17) -> 0 | J15: =SUM(J16:J17) -> 0 | K15: =SUM(K16:K17) -> 0 | L15: =SUM(L16:L17) -> 0 | ... AN15: =SUM(AN16:AN17) -> 0
B16: Standard | D16: =C16 -> 0 | E16: 0 | F16: 0 | G16: 0 | H16: 0 | I16: 0 | J16: 0 | K16: 0 | L16: 0 | M16: 0 | N16: 0 | O16: 0 | P16: 0 | Q16: 0 | R16: 0 | S16: 0 | T16: 0 | U16: 0 | V16: 0 | W16: 0 | X16: 0 | Y16: 0 | Z16: 0 | AA16: 0 | AB16: 0 | AC16: 0 | AD16: 0 | AE16: 0 | AF16: 0 | AG16: 0 | AH16: 0 | AI16: 0 | AJ16: 0 | AK16: 0 | AL16: 0 | AM16: 0 | AN16: 0
B17: E-bike | C17: 0 | D17: =C17 -> 0 | E17: 0 | F17: 0 | G17: 0 | H17: 0 | I17: 0 | J17: 0 | K17: 0 | L17: 0 | M17: 0 | N17: 0 | O17: 0 | P17: 0 | Q17: 0 | R17: 0 | S17: 0 | T17: 0 | U17: 0 | V17: 0 | W17: 0 | X17: 0 | Y17: 0 | Z17: 0 | AA17: 0 | AB17: 0 | AC17: 0 | AD17: 0 | AE17: 0 | AF17: 0 | AG17: 0 | AH17: 0 | AI17: 0 | AJ17: 0 | AK17: 0 | AL17: 0 | AM17: 0 | AN17: 0
A18: Dis vol. - Accumulating %
A19: Chỉ để xem thôi | B19: Standard | E19: =D19+E22 -> -1 | F19: =E19+F22 -> -1 | G19: =F19+G22 -> -1 | H19: =G19+H22 -> -1 | I19: =H19+I22 -> -1 | J19: =I19+J22 -> -1 | K19: =J19+K22 -> -1 | L19: =K19+L22 -> -1 | ... AN19: =AM19+AN22 -> -1
B20: E-bike | E20: =D20+E23 -> -1 | F20: =E20+F23 -> -1 | G20: =F20+G23 -> -1 | H20: =G20+H23 -> -1 | I20: =H20+I23 -> -1 | J20: =I20+J23 -> -1 | K20: =J20+K23 -> -1 | L20: =K20+L23 -> -1 | ... AN20: =AM20+AN23 -> -1
A21: Dis. vol. adjustment
A22: Dự kiến tăng giảm cung cho phân phối | B22: Standard | E22: -1
B23: E-bike | E23: -1
A24: Store price | C24: Base \ Sale | D24: =SUMPRODUCT(D25:D26,D7:D8) -> 0 | E24: =SUMPRODUCT(E25:E26,E7:E8) -> 0 | F24: =SUMPRODUCT(F25:F26,F7:F8) -> 0 | G24: =SUMPRODUCT(G25:G26,G7:G8) -> 0 | H24: =SUMPRODUCT(H25:H26,H7:H8) -> 0 | I24: =SUMPRODUCT(I25:I26,I7:I8) -> 0 | J24: =SUMPRODUCT(J25:J26,J7:J8) -> 0 | K24: =SUMPRODUCT(K25:K26,K7:K8) -> 0 | ... AN24: =SUMPRODUCT(AN25:AN26,AN7:AN8) -> 0
B25: Standard | D25: =C25 -> 0 | E25: =$C25*(E31)+D25 -> 0 | F25: =$C25*(F31)+E25 -> 0 | G25: =$C25*(G31)+F25 -> 0 | H25: =$C25*(H31)+G25 -> 0 | I25: =$C25*(I31)+H25 -> 0 | J25: =$C25*(J31)+I25 -> 0 | K25: =$C25*(K31)+J25 -> 0 | L25: =$C25*(L31)+K25 -> 0 | ... AN25: =$C25*(AN31)+AM25 -> 0
B26: E-bike | C26: 0 | D26: =C26 -> 0 | E26: =$C26*(E32)+D26 -> 0 | F26: =$C26*(F32)+E26 -> 0 | G26: =$C26*(G32)+F26 -> 0 | H26: =$C26*(H32)+G26 -> 0 | I26: =$C26*(I32)+H26 -> 0 | J26: =$C26*(J32)+I26 -> 0 | K26: =$C26*(K32)+J26 -> 0 | L26: =$C26*(L32)+K26 -> 0 | ... AN26: =$C26*(AN32)+AM26 -> 0
A27: Store price - Accumulating %
A28: Chỉ để xem thôi | B28: Standard | E28: =D28+E31 -> 0 | F28: =E28+F31 -> 0 | G28: =F28+G31 -> 0 | H28: =G28+H31 -> 0 | I28: =H28+I31 -> 0 | J28: =I28+J31 -> 0 | K28: =J28+K31 -> 0 | L28: =K28+L31 -> 0 | ... AM28: =AL28+AM31 -> 0
B29: E-bike | E29: =D29+E32 -> 0 | F29: =E29+F32 -> 0 | G29: =F29+G32 -> 0 | H29: =G29+H32 -> 0 | I29: =H29+I32 -> 0 | J29: =I29+J32 -> 0 | K29: =J29+K32 -> 0 | L29: =K29+L32 -> 0 | ... AM29: =AL29+AM32 -> 0
A30: Store price adjustment
A31: Dự kiến tăng giảm giá cho store | B31: Standard
B32: E-bike
A33: Dis. price | C33: Base \ Sale | D33: =SUMPRODUCT(D34:D35,D16:D17) -> 0 | E33: =SUMPRODUCT(E34:E35,E16:E17) -> 0 | F33: =SUMPRODUCT(F34:F35,F16:F17) -> 0 | G33: =SUMPRODUCT(G34:G35,G16:G17) -> 0 | H33: =SUMPRODUCT(H34:H35,H16:H17) -> 0 | I33: =SUMPRODUCT(I34:I35,I16:I17) -> 0 | J33: =SUMPRODUCT(J34:J35,J16:J17) -> 0 | K33: =SUMPRODUCT(K34:K35,K16:K17) -> 0 | ... AN33: =SUMPRODUCT(AN34:AN35,AN16:AN17) -> 0
B34: Standard | D34: =C34 -> 0 | E34: =$C34*(E40)+D34 -> 0 | F34: =$C34*(F40)+E34 -> 0 | G34: =$C34*(G40)+F34 -> 0 | H34: =$C34*(H40)+G34 -> 0 | I34: =$C34*(I40)+H34 -> 0 | J34: =$C34*(J40)+I34 -> 0 | K34: =$C34*(K40)+J34 -> 0 | L34: =$C34*(L40)+K34 -> 0 | ... AN34: =$C34*(AN40)+AM34 -> 0
B35: E-bike | C35: 0 | D35: =C35 -> 0 | E35: =$C35*(E41)+D35 -> 0 | F35: =$C35*(F41)+E35 -> 0 | G35: =$C35*(G41)+F35 -> 0 | H35: =$C35*(H41)+G35 -> 0 | I35: =$C35*(I41)+H35 -> 0 | J35: =$C35*(J41)+I35 -> 0 | K35: =$C35*(K41)+J35 -> 0 | L35: =$C35*(L41)+K35 -> 0 | ... AN35: =$C35*(AN41)+AM35 -> 0
A36: Dis. price - Accumulating %
A37: Chỉ để xem thôi | B37: Standard | E37: =D37+E40 -> 0 | F37: =E37+F40 -> 0 | G37: =F37+G40 -> 0 | H37: =G37+H40 -> 0 | I37: =H37+I40 -> 0 | J37: =I37+J40 -> 0 | K37: =J37+K40 -> 0 | L37: =K37+L40 -> 0 | ... AM37: =AL37+AM40 -> 0
B38: E-bike | E38: =D38+E41 -> 0 | F38: =E38+F41 -> 0 | G38: =F38+G41 -> 0 | H38: =G38+H41 -> 0 | I38: =H38+I41 -> 0 | J38: =I38+J41 -> 0 | K38: =J38+K41 -> 0 | L38: =K38+L41 -> 0 | ... AM38: =AL38+AM41 -> 0
A39: Dis. price adjustment
A40: Dự kiến tăng giảm giá cho phân phối | B40: Standard
B41: E-bike
A42: Revenue | E42: =IF(NOT(SUM(E43:E44)=SUM(E33,E24)), "Error", SUM(E33,E24)) -> 0 | F42: =IF(NOT(SUM(F43:F44)=SUM(F33,F24)), "Error", SUM(F33,F24)) -> 0 | G42: =IF(NOT(SUM(G43:G44)=SUM(G33,G24)), "Error", SUM(G33,G24)) -> 0 | H42: =IF(NOT(SUM(H43:H44)=SUM(H33,H24)), "Error", SUM(H33,H24)) -> 0 | I42: =IF(NOT(SUM(I43:I44)=SUM(I33,I24)), "Error", SUM(I33,I24)) -> 0 | J42: =IF(NOT(SUM(J43:J44)=SUM(J33,J24)), "Error", SUM(J33,J24)) -> 0 | K42: =IF(NOT(SUM(K43:K44)=SUM(K33,K24)), "Error", SUM(K33,K24)) -> 0 | L42: =IF(NOT(SUM(L43:L44)=SUM(L33,L24)), "Error", SUM(L33,L24)) -> 0 | ... AN42: =IF(NOT(SUM(AN43:AN44)=SUM(AN33,AN24)), "Error", SUM(AN33,AN24)) -> 0
B43: Standard | E43: =E7*E25+E16*E34 -> 0 | F43: =F7*F25+F16*F34 -> 0 | G43: =G7*G25+G16*G34 -> 0 | H43: =H7*H25+H16*H34 -> 0 | I43: =I7*I25+I16*I34 -> 0 | J43: =J7*J25+J16*J34 -> 0 | K43: =K7*K25+K16*K34 -> 0 | L43: =L7*L25+L16*L34 -> 0 | ... AN43: =AN7*AN25+AN16*AN34 -> 0
B44: E-bike | E44: =E8*E26+E17*E35 -> 0 | F44: =F8*F26+F17*F35 -> 0 | G44: =G8*G26+G17*G35 -> 0 | H44: =H8*H26+H17*H35 -> 0 | I44: =I8*I26+I17*I35 -> 0 | J44: =J8*J26+J17*J35 -> 0 | K44: =K8*K26+K17*K35 -> 0 | L44: =L8*L26+L17*L35 -> 0 | ... AN44: =AN8*AN26+AN17*AN35 -> 0
A47: T2. PRODUCTION PLAN
E48: 2025 | Q48: 2026 | AC48: 2027
E49: Q1 | H49: Q2 | K49: Q3 | N49: Q4 | Q49: Q1 | T49: Q2 | W49: Q3 | Z49: Q4 | AC49: Q1 | AF49: Q2 | AI49: Q3 | AL49: Q4
C50: Default | D50: Buffer | E50: 1 | F50: 2 | G50: 3 | H50: 4 | I50: 5 | J50: 6 | K50: 7 | L50: 8 | M50: 9 | N50: 10 | O50: 11 | P50: 12 | Q50: 1 | R50: 2 | S50: 3 | T50: 4 | U50: 5 | V50: 6 | W50: 7 | X50: 8 | Y50: 9 | Z50: 10 | AA50: 11 | AB50: 12 | AC50: 1 | AD50: 2 | AE50: 3 | AF50: 4 | AG50: 5 | AH50: 6 | AI50: 7 | AJ50: 8 | AK50: 9 | AL50: 10 | AM50: 11 | AN50: 12
A51: Store sales estimation | C51: =C6 -> 0 | E51: =E6 -> 0 | F51: =F6 -> 0 | G51: =G6 -> 0 | H51: =H6 -> 0 | I51: =I6 -> 0 | J51: =J6 -> 0 | K51: =K6 -> 0 | L51: =L6 -> 0 | ... AN51: =AN6 -> 0
A52: Chỉnh ở trên | B52: Standard | C52: =C7 -> 0 | E52: =E7 -> 0 | F52: =F7 -> 0 | G52: =G7 -> 0 | H52: =H7 -> 0 | I52: =I7 -> 0 | J52: =J7 -> 0 | K52: =K7 -> 0 | L52: =L7 -> 0 | ... AN52: =AN7 -> 0
B53: E-bike | C53: =C8 -> 0 | E53: =E8 -> 0 | F53: =F8 -> 0 | G53: =G8 -> 0 | H53: =H8 -> 0 | I53: =I8 -> 0 | J53: =J8 -> 0 | K53: =K8 -> 0 | L53: =L8 -> 0 | ... AN53: =AN8 -> 0
A54: Distributor vol. | B54: Bảo | C54: =C15 -> 0 | E54: =E15 -> 0 | F54: =F15 -> 0 | G54: =G15 -> 0 | H54: =H15 -> 0 | I54: =I15 -> 0 | J54: =J15 -> 0 | K54: =K15 -> 0 | L54: =L15 -> 0 | ... AN54: =AN15 -> 0
A55: Chỉnh ở trên | B55: Standard | C55: =C16 -> 0 | E55: =E16 -> 0 | F55: =F16 -> 0 | G55: =G16 -> 0 | H55: =H16 -> 0 | I55: =I16 -> 0 | J55: =J16 -> 0 | K55: =K16 -> 0 | L55: =L16 -> 0 | ... AN55: =AN16 -> 0
B56: E-bike | C56: =C17 -> 0 | E56: =E17 -> 0 | F56: =F17 -> 0 | G56: =G17 -> 0 | H56: =H17 -> 0 | I56: =I17 -> 0 | J56: =J17 -> 0 | K56: =K17 -> 0 | L56: =L17 -> 0 | ... AN56: =AN17 -> 0
A57: Store preproduce | C57: % | E57: =SUM(E58:E59) -> 0 | F57: =SUM(F58:F59) -> 0 | G57: =SUM(G58:G59) -> 0 | H57: =SUM(H58:H59) -> 0 | I57: =SUM(I58:I59) -> 0 | J57: =SUM(J58:J59) -> 0 | K57: =SUM(K58:K59) -> 0 | L57: =SUM(L58:L59) -> 0 | ... AN57: =SUM(AN58:AN59) -> 0
B58: Standard | E58: 0 | F58: 0 | G58: 0 | H58: 0 | I58: 0 | J58: 0 | K58: 0 | L58: 0 | M58: 0 | N58: 0 | O58: 0 | P58: 0 | Q58: 0 | R58: 0 | S58: 0 | T58: 0 | U58: 0 | V58: 0 | W58: 0 | X58: 0 | Y58: 0 | Z58: 0 | AA58: 0 | AB58: 0 | AC58: 0 | AD58: 0 | AE58: 0 | AF58: 0 | AG58: 0 | AH58: 0 | AI58: 0 | AJ58: 0 | AK58: 0 | AL58: 0 | AM58: 0 | AN58: 0
B59: E-bike | C59: 0 | E59: 0 | F59: 0 | G59: 0 | H59: 0 | I59: 0 | J59: 0 | K59: 0 | L59: 0 | M59: 0 | N59: 0 | O59: 0 | P59: 0 | Q59: 0 | R59: 0 | S59: 0 | T59: 0 | U59: 0 | V59: 0 | W59: 0 | X59: 0 | Y59: 0 | Z59: 0 | AA59: 0 | AB59: 0 | AC59: 0 | AD59: 0 | AE59: 0 | AF59: 0 | AG59: 0 | AH59: 0 | AI59: 0 | AJ59: 0 | AK59: 0 | AL59: 0 | AM59: 0 | AN59: 0
A60: Dis. preproduce | C60: % | E60: =SUM(E61:E62) -> 0 | F60: =SUM(F61:F62) -> 0 | G60: =SUM(G61:G62) -> 0 | H60: =SUM(H61:H62) -> 0 | I60: =SUM(I61:I62) -> 0 | J60: =SUM(J61:J62) -> 0 | K60: =SUM(K61:K62) -> 0 | L60: =SUM(L61:L62) -> 0 | ... AN60: =SUM(AN61:AN62) -> 0
B61: Standard | E61: 0 | F61: 0 | G61: 0 | H61: 0 | I61: 0 | J61: 0 | K61: 0 | L61: 0 | M61: 0 | N61: 0 | O61: 0 | P61: 0 | Q61: 0 | R61: 0 | S61: 0 | T61: 0 | U61: 0 | V61: 0 | W61: 0 | X61: 0 | Y61: 0 | Z61: 0 | AA61: 0 | AB61: 0 | AC61: 0 | AD61: 0 | AE61: 0 | AF61: 0 | AG61: 0 | AH61: 0 | AI61: 0 | AJ61: 0 | AK61: 0 | AL61: 0 | AM61: 0 | AN61: 0
B62: E-bike | C62: 0 | E62: 0 | F62: 0 | G62: 0 | H62: 0 | I62: 0 | J62: 0 | K62: 0 | L62: 0 | M62: 0 | N62: 0 | O62: 0 | P62: 0 | Q62: 0 | R62: 0 | S62: 0 | T62: 0 | U62: 0 | V62: 0 | W62: 0 | X62: 0 | Y62: 0 | Z62: 0 | AA62: 0 | AB62: 0 | AC62: 0 | AD62: 0 | AE62: 0 | AF62: 0 | AG62: 0 | AH62: 0 | AI62: 0 | AJ62: 0 | AK62: 0 | AL62: 0 | AM62: 0 | AN62: 0
A63: Inv. vol Diff. | C63: =C90 -> 0 | E63: =E90 -> 0 | F63: =F90 -> 0 | G63: =G90 -> 0 | H63: =H90 -> 0 | I63: =I90 -> 0 | J63: =J90 -> 0 | K63: =K90 -> 0 | L63: =L90 -> 0 | ... AN63: =AN90 -> 0
B64: Standard | C64: =C91 -> 0 | E64: =E91 -> 0 | F64: =F91 -> 0 | G64: =G91 -> 0 | H64: =H91 -> 0 | I64: =I91 -> 0 | J64: =J91 -> 0 | K64: =K91 -> 0 | L64: =L91 -> 0 | ... AN64: =AN91 -> 0
B65: E-bike | C65: =C92 -> 0 | E65: =E92 -> 0 | F65: =F92 -> 0 | G65: =G92 -> 0 | H65: =H92 -> 0 | I65: =I92 -> 0 | J65: =J92 -> 0 | K65: =K92 -> 0 | L65: =L92 -> 0 | ... AN65: =AN92 -> 0
A66: Production outputs | E66: =SUM(E67:E68) -> 0 | F66: =SUM(F67:F68) -> 0 | G66: =SUM(G67:G68) -> 0 | H66: =SUM(H67:H68) -> 0 | I66: =SUM(I67:I68) -> 0 | J66: =SUM(J67:J68) -> 0 | K66: =SUM(K67:K68) -> 0 | L66: =SUM(L67:L68) -> 0 | ... AN66: =SUM(AN67:AN68) -> 0
B67: Standard | E67: =E52+E55+E64 -> 0 | F67: =F52+F55+F64 -> 0 | G67: =G52+G55+G64 -> 0 | H67: =H52+H55+H64 -> 0 | I67: =I52+I55+I64 -> 0 | J67: =J52+J55+J64 -> 0 | K67: =K52+K55+K64 -> 0 | L67: =L52+L55+L64 -> 0 | ... AN67: =AN52+AN55+AN64 -> 0
B68: E-bike | E68: =E53+E56+E65 -> 0 | F68: =F53+F56+F65 -> 0 | G68: =G53+G56+G65 -> 0 | H68: =H53+H56+H65 -> 0 | I68: =I53+I56+I65 -> 0 | J68: =J53+J56+J65 -> 0 | K68: =K53+K56+K65 -> 0 | L68: =L53+L56+L65 -> 0 | ... AN68: =AN53+AN56+AN65 -> 0
A71: T3. INVENTORY PLAN - FIFO
E72: 2025 | Q72: 2026 | AC72: 2027
E73: Q1 | H73: Q2 | K73: Q3 | N73: Q4 | Q73: Q1 | T73: Q2 | W73: Q3 | Z73: Q4 | AC73: Q1 | AF73: Q2 | AI73: Q3 | AL73: Q4
E74: 1 | F74: 2 | G74: 3 | H74: 4 | I74: 5 | J74: 6 | K74: 7 | L74: 8 | M74: 9 | N74: 10 | O74: 11 | P74: 12 | Q74: 1 | R74: 2 | S74: 3 | T74: 4 | U74: 5 | V74: 6 | W74: 7 | X74: 8 | Y74: 9 | Z74: 10 | AA74: 11 | AB74: 12 | AC74: 1 | AD74: 2 | AE74: 3 | AF74: 4 | AG74: 5 | AH74: 6 | AI74: 7 | AJ74: 8 | AK74: 9 | AL74: 10 | AM74: 11 | AN74: 12
A75: Inventory | C75: Base Inv | E75: =SUM(E76:E77) -> 0 | F75: =SUM(F76:F77) -> 0 | G75: =SUM(G76:G77) -> 0 | H75: =SUM(H76:H77) -> 0 | I75: =SUM(I76:I77) -> 0 | J75: =SUM(J76:J77) -> 0 | K75: =SUM(K76:K77) -> 0 | L75: =SUM(L76:L77) -> 0 | ... AN75: =SUM(AN76:AN77) -> 0
B76: Standard | D76: =C76 -> 0 | E76: 0 | F76: 0 | G76: 0 | H76: 0 | I76: 0 | J76: 0 | K76: 0 | L76: 0 | M76: 0 | N76: 0 | O76: 0 | P76: 0 | Q76: 0 | R76: 0 | S76: 0 | T76: 0 | U76: 0 | V76: 0 | W76: 0 | X76: 0 | Y76: 0 | Z76: 0 | AA76: 0 | AB76: 0 | AC76: 0 | AD76: 0 | AE76: 0 | AF76: 0 | AG76: 0 | AH76: 0 | AI76: 0 | AJ76: 0 | AK76: 0 | AL76: 0 | AM76: 0 | AN76: 0
B77: E-bike | D77: =C77 -> 0 | E77: 0 | F77: 0 | G77: 0 | H77: 0 | I77: 0 | J77: 0 | K77: 0 | L77: 0 | M77: 0 | N77: 0 | O77: 0 | P77: 0 | Q77: 0 | R77: 0 | S77: 0 | T77: 0 | U77: 0 | V77: 0 | W77: 0 | X77: 0 | Y77: 0 | Z77: 0 | AA77: 0 | AB77: 0 | AC77: 0 | AD77: 0 | AE77: 0 | AF77: 0 | AG77: 0 | AH77: 0 | AI77: 0 | AJ77: 0 | AK77: 0 | AL77: 0 | AM77: 0 | AN77: 0
A78: Base Inv. change - Accumulating %
A79: Chỉ để xem thôi | B79: Standard | E79: =D79+E82 -> -1 | F79: =E79+F82 -> -0.9 | G79: =F79+G82 -> -0.8 | H79: =G79+H82 -> -0.7 | I79: =H79+I82 -> -0.6 | J79: =I79+J82 -> 0.4 | K79: =J79+K82 -> 0.5 | L79: =K79+L82 -> 0 | ... AN79: =AM79+AN82 -> 2.8
B80: E-bike | E80: =D80+E83 -> -1 | F80: =E80+F83 -> -1 | G80: =F80+G83 -> -1 | H80: =G80+H83 -> -1 | I80: =H80+I83 -> -1 | J80: =I80+J83 -> 0 | K80: =J80+K83 -> 0 | L80: =K80+L83 -> -0.5 | ... AN80: =AM80+AN83 -> 0.8
A81: Base Inv. change (NOT RECOMMEND) | C81: =C75 -> Base Inv
A82: Dùng để xác định bao giờ có tồn kho là chủ yếu. Cũng có thể dùng để tăng tồn kho nhma ko yêu cầu | B82: Standard | C82: =C76 -> 0 | E82: -1 | F82: 0.1 | G82: 0.1 | H82: 0.1 | I82: 0.1 | J82: 1 | K82: 0.1 | L82: -0.5 | M82: 0.1 | N82: 0.1 | O82: 0.1 | P82: 0.1 | Q82: 0.1 | R82: 0.1 | S82: 0.1 | T82: 0.1 | U82: 0.1 | V82: 0.1 | W82: 0.1 | X82: 0.1 | Y82: 0.1 | Z82: 0.1 | AA82: 0.1 | AB82: 0.1 | AC82: 0.1 | AD82: 0.1 | AE82: 0.1 | AF82: 0.1 | AG82: 0.1 | AH82: 0.1 | AI82: 0.1 | AJ82: 0.1 | AK82: 0.1 | AL82: 0.1 | AM82: 0.1 | AN82: 0.1
B83: E-bike | C83: =C77 -> 0 | E83: -1 | J83: 1 | L83: -0.5 | AC83: 1 | AL83: 0.1 | AM83: 0.1 | AN83: 0.1
A84: Store preproduce | C84: =C57 -> % | D84: =D57 -> 0 | E84: =E57 -> 0 | F84: =F57 -> 0 | G84: =G57 -> 0 | H84: =H57 -> 0 | I84: =I57 -> 0 | J84: =J57 -> 0 | ... AN84: =AN57 -> 0
A85: Chỉnh ở trên | B85: Standard | C85: =C58 -> 0 | D85: =D58 -> 0 | E85: =E58 -> 0 | F85: =F58 -> 0 | G85: =G58 -> 0 | H85: =H58 -> 0 | I85: =I58 -> 0 | J85: =J58 -> 0 | ... AN85: =AN58 -> 0
B86: E-bike | C86: =C59 -> 0 | D86: =D59 -> 0 | E86: =E59 -> 0 | F86: =F59 -> 0 | G86: =G59 -> 0 | H86: =H59 -> 0 | I86: =I59 -> 0 | J86: =J59 -> 0 | ... AN86: =AN59 -> 0
A87: Dis. preproduce | C87: =C60 -> % | D87: =D60 -> 0 | E87: =E60 -> 0 | F87: =F60 -> 0 | G87: =G60 -> 0 | H87: =H60 -> 0 | I87: =I60 -> 0 | J87: =J60 -> 0 | ... AN87: =AN60 -> 0
A88: Chỉnh ở trên | B88: Standard | C88: =C61 -> 0 | D88: =D61 -> 0 | E88: =E61 -> 0 | F88: =F61 -> 0 | G88: =G61 -> 0 | H88: =H61 -> 0 | I88: =I61 -> 0 | J88: =J61 -> 0 | ... AN88: =AN61 -> 0
B89: E-bike | C89: =C62 -> 0 | D89: =D62 -> 0 | E89: =E62 -> 0 | F89: =F62 -> 0 | G89: =G62 -> 0 | H89: =H62 -> 0 | I89: =I62 -> 0 | J89: =J62 -> 0 | ... AN89: =AN62 -> 0
A90: Inv. vol Diff. | F90: =SUM(F91:F92) -> 0 | G90: =SUM(G91:G92) -> 0 | H90: =SUM(H91:H92) -> 0 | I90: =SUM(I91:I92) -> 0 | J90: =SUM(J91:J92) -> 0 | K90: =SUM(K91:K92) -> 0 | L90: =SUM(L91:L92) -> 0 | M90: =SUM(M91:M92) -> 0 | ... AN90: =SUM(AN91:AN92) -> 0
A91: Ko chỉnh bất kì thứ gì ở mục này | B91: Standard | F91: =F76-E76 -> 0 | G91: =G76-F76 -> 0 | H91: =H76-G76 -> 0 | I91: =I76-H76 -> 0 | J91: =J76-I76 -> 0 | K91: =K76-J76 -> 0 | L91: =L76-K76 -> 0 | M91: =M76-L76 -> 0 | ... AN91: =AN76-AM76 -> 0
B92: E-bike | F92: =F77-E77 -> 0 | G92: =G77-F77 -> 0 | H92: =H77-G77 -> 0 | I92: =I77-H77 -> 0 | J92: =J77-I77 -> 0 | K92: =K77-J77 -> 0 | L92: =L77-K77 -> 0 | M92: =M77-L77 -> 0 | ... AN92: =AN77-AM77 -> 0

Sheet Item list
A1: Long-term assets depreciation plan | M1: Depreciation Expense | N1: Accumulated Depreciation, beginning | O1: Accumulated Depreciation, ending | R1: Depreciation Expense | S1: Accumulated Depreciation, beginning | T1: Accumulated Depreciation, ending | W1: Depreciation Expense | X1: Accumulated Depreciation, beginning | Y1: Accumulated Depreciation, ending | AB1: Depreciation Expense | AC1: Accumulated Depreciation, beginning | AD1: Accumulated Depreciation, ending
F2: Building | G2: =SUMIF($C$18:$C96,$F2,D$18:D96) -> 9340000000 | M2: =SUMIF($C$18:$C96,$F2,N$18:N96) -> 2.7531648e+09 | N2: =SUMIF($C$18:$C96,$F2,J$18:J96) -> 0 | O2: =SUMIF($C$18:$C96,$F2,O$18:O96) -> 2.7531648e+09 | R2: =SUMIF($C$18:$C96,$F2,S$18:S96) -> 3.0294286e+09 | S2: =SUMIF($C$18:$C96,$F2,O$18:O96) -> 2.7531648e+09 | T2: =SUMIF($C$18:$C96,$F2,T$18:T96) -> 5.7825933e+09 | W2: =SUMIF($C$18:$C96,$F2,X$18:X96) -> 3.0294286e+09 | X2: =SUMIF($C$18:$C96,$F2,T$18:T96) -> 5.7825933e+09 | Y2: =SUMIF($C$18:$C96,$F2,Y$18:Y96) -> 8.8120219e+09 | AB2: =SUMIF($C$18:$C96,$F2,AC$18:AC96) -> 0 | AC2: =SUMIF($C$18:$C96,$F2,Y$18:Y96) -> 8.8120219e+09 | AD2: =SUMIF($C$18:$C96,$F2,AD$18:AD96) -> 0
F3: Computer Hardware | G3: =SUMIF($C$18:$C97,$F3,D$18:D97) -> 440000000 | M3: =SUMIF($C$18:$C97,$F3,N$18:N97) -> 70400000 | N3: =SUMIF($C$18:$C97,$F3,J$18:J97) -> 0 | O3: =SUMIF($C$18:$C97,$F3,O$18:O97) -> 70400000 | R3: =SUMIF($C$18:$C97,$F3,S$18:S97) -> 88000000 | S3: =SUMIF($C$18:$C97,$F3,O$18:O97) -> 70400000 | T3: =SUMIF($C$18:$C97,$F3,T$18:T97) -> 158400000 | W3: =SUMIF($C$18:$C97,$F3,X$18:X97) -> 88000000 | X3: =SUMIF($C$18:$C97,$F3,T$18:T97) -> 158400000 | Y3: =SUMIF($C$18:$C97,$F3,Y$18:Y97) -> 246400000 | AB3: =SUMIF($C$18:$C97,$F3,AC$18:AC97) -> 0 | AC3: =SUMIF($C$18:$C97,$F3,Y$18:Y97) -> 246400000 | AD3: =SUMIF($C$18:$C97,$F3,AD$18:AD97) -> 0
F4: Computer Software | G4: =SUMIF($C$18:$C98,$F4,D$18:D98) -> 60000000 | M4: =SUMIF($C$18:$C98,$F4,N$18:N98) -> 16000000 | N4: =SUMIF($C$18:$C98,$F4,J$18:J98) -> 0 | O4: =SUMIF($C$18:$C98,$F4,O$18:O98) -> 16000000 | R4: =SUMIF($C$18:$C98,$F4,S$18:S98) -> 20000000 | S4: =SUMIF($C$18:$C98,$F4,O$18:O98) -> 16000000 | T4: =SUMIF($C$18:$C98,$F4,T$18:T98) -> 36000000 | W4: =SUMIF($C$18:$C98,$F4,X$18:X98) -> 20000000 | X4: =SUMIF($C$18:$C98,$F4,T$18:T98) -> 36000000 | Y4: =SUMIF($C$18:$C98,$F4,Y$18:Y98) -> 56000000 | AB4: =SUMIF($C$18:$C98,$F4,AC$18:AC98) -> 0 | AC4: =SUMIF($C$18:$C98,$F4,Y$18:Y98) -> 56000000 | AD4: =SUMIF($C$18:$C98,$F4,AD$18:AD98) -> 0
F5: Factory Equipment | G5: =SUMIF($C$18:$C99,$F5,D$18:D99) -> 12600000000 | M5: =SUMIF($C$18:$C99,$F5,N$18:N99) -> 6.830411e+08 | N5: =SUMIF($C$18:$C99,$F5,J$18:J99) -> 0 | O5: =SUMIF($C$18:$C99,$F5,O$18:O99) -> 6.830411e+08 | R5: =SUMIF($C$18:$C99,$F5,S$18:S99) -> 1165000000 | S5: =SUMIF($C$18:$C99,$F5,O$18:O99) -> 6.830411e+08 | T5: =SUMIF($C$18:$C99,$F5,T$18:T99) -> 1.8480411e+09 | W5: =SUMIF($C$18:$C99,$F5,X$18:X99) -> 1165000000 | X5: =SUMIF($C$18:$C99,$F5,T$18:T99) -> 1.8480411e+09 | Y5: =SUMIF($C$18:$C99,$F5,Y$18:Y99) -> 3.0130411e+09 | AB5: =SUMIF($C$18:$C99,$F5,AC$18:AC99) -> 0 | AC5: =SUMIF($C$18:$C99,$F5,Y$18:Y99) -> 3.0130411e+09 | AD5: =SUMIF($C$18:$C99,$F5,AD$18:AD99) -> 0
F6: Furnitures & Fixtures | G6: =SUMIF($C$18:$C100,$F6,D$18:D100) -> 1080000000 | M6: =SUMIF($C$18:$C100,$F6,N$18:N100) -> 84896282 | N6: =SUMIF($C$18:$C100,$F6,J$18:J100) -> 0 | O6: =SUMIF($C$18:$C100,$F6,O$18:O100) -> 84896282 | R6: =SUMIF($C$18:$C100,$F6,S$18:S100) -> 1.2928571e+08 | S6: =SUMIF($C$18:$C100,$F6,O$18:O100) -> 84896282 | T6: =SUMIF($C$18:$C100,$F6,T$18:T100) -> 2.14182e+08 | W6: =SUMIF($C$18:$C100,$F6,X$18:X100) -> 1.2928571e+08 | X6: =SUMIF($C$18:$C100,$F6,T$18:T100) -> 2.14182e+08 | Y6: =SUMIF($C$18:$C100,$F6,Y$18:Y100) -> 3.4346771e+08 | AB6: =SUMIF($C$18:$C100,$F6,AC$18:AC100) -> 0 | AC6: =SUMIF($C$18:$C100,$F6,Y$18:Y100) -> 3.4346771e+08 | AD6: =SUMIF($C$18:$C100,$F6,AD$18:AD100) -> 0
F7: Machinery | G7: =SUMIF($C$18:$C101,$F7,D$18:D101) -> 14400000000 | M7: =SUMIF($C$18:$C101,$F7,N$18:N101) -> 6.8010959e+08 | N7: =SUMIF($C$18:$C101,$F7,J$18:J101) -> 0 | O7: =SUMIF($C$18:$C101,$F7,O$18:O101) -> 6.8010959e+08 | R7: =SUMIF($C$18:$C101,$F7,S$18:S101) -> 1160000000 | S7: =SUMIF($C$18:$C101,$F7,O$18:O101) -> 6.8010959e+08 | T7: =SUMIF($C$18:$C101,$F7,T$18:T101) -> 1.8401096e+09 | W7: =SUMIF($C$18:$C101,$F7,X$18:X101) -> 1160000000 | X7: =SUMIF($C$18:$C101,$F7,T$18:T101) -> 1.8401096e+09 | Y7: =SUMIF($C$18:$C101,$F7,Y$18:Y101) -> 3.0001096e+09 | AB7: =SUMIF($C$18:$C101,$F7,AC$18:AC101) -> 0 | AC7: =SUMIF($C$18:$C101,$F7,Y$18:Y101) -> 3.0001096e+09 | AD7: =SUMIF($C$18:$C101,$F7,AD$18:AD101) -> 0
F8: Office Equipment | G8: =SUMIF($C$18:$C102,$F8,D$18:D102) -> 158000000 | M8: =SUMIF($C$18:$C102,$F8,N$18:N102) -> 37808219 | N8: =SUMIF($C$18:$C102,$F8,J$18:J102) -> 0 | O8: =SUMIF($C$18:$C102,$F8,O$18:O102) -> 37808219 | R8: =SUMIF($C$18:$C102,$F8,S$18:S102) -> 46000000 | S8: =SUMIF($C$18:$C102,$F8,O$18:O102) -> 37808219 | T8: =SUMIF($C$18:$C102,$F8,T$18:T102) -> 83808219 | W8: =SUMIF($C$18:$C102,$F8,X$18:X102) -> 46000000 | X8: =SUMIF($C$18:$C102,$F8,T$18:T102) -> 83808219 | Y8: =SUMIF($C$18:$C102,$F8,Y$18:Y102) -> 1.2980822e+08 | AB8: =SUMIF($C$18:$C102,$F8,AC$18:AC102) -> 0 | AC8: =SUMIF($C$18:$C102,$F8,Y$18:Y102) -> 1.2980822e+08 | AD8: =SUMIF($C$18:$C102,$F8,AD$18:AD102) -> 0
F9: Other Fixed Assets | G9: =SUMIF($C$18:$C103,$F9,D$18:D103) -> 0 | M9: =SUMIF($C$18:$C103,$F9,N$18:N103) -> 0 | N9: =SUMIF($C$18:$C103,$F9,J$18:J103) -> 0 | O9: =SUMIF($C$18:$C103,$F9,O$18:O103) -> 0 | R9: =SUMIF($C$18:$C103,$F9,S$18:S103) -> 0 | S9: =SUMIF($C$18:$C103,$F9,O$18:O103) -> 0 | T9: =SUMIF($C$18:$C103,$F9,T$18:T103) -> 0 | W9: =SUMIF($C$18:$C103,$F9,X$18:X103) -> 0 | X9: =SUMIF($C$18:$C103,$F9,T$18:T103) -> 0 | Y9: =SUMIF($C$18:$C103,$F9,Y$18:Y103) -> 0 | AB9: =SUMIF($C$18:$C103,$F9,AC$18:AC103) -> 0 | AC9: =SUMIF($C$18:$C103,$F9,Y$18:Y103) -> 0 | AD9: =SUMIF($C$18:$C103,$F9,AD$18:AD103) -> 0
F10: Vehicles | G10: =SUMIF($C$18:$C104,$F10,D$18:D104) -> 13500000000 | M10: =SUMIF($C$18:$C104,$F10,N$18:N104) -> 9.8345401e+08 | N10: =SUMIF($C$18:$C104,$F10,J$18:J104) -> 0 | O10: =SUMIF($C$18:$C104,$F10,O$18:O104) -> 9.8345401e+08 | R10: =SUMIF($C$18:$C104,$F10,S$18:S104) -> 1.7089286e+09 | S10: =SUMIF($C$18:$C104,$F10,O$18:O104) -> 9.8345401e+08 | T10: =SUMIF($C$18:$C104,$F10,T$18:T104) -> 2.6923826e+09 | W10: =SUMIF($C$18:$C104,$F10,X$18:X104) -> 1.7089286e+09 | X10: =SUMIF($C$18:$C104,$F10,T$18:T104) -> 2.6923826e+09 | Y10: =SUMIF($C$18:$C104,$F10,Y$18:Y104) -> 4.4013112e+09 | AB10: =SUMIF($C$18:$C104,$F10,AC$18:AC104) -> 0 | AC10: =SUMIF($C$18:$C104,$F10,Y$18:Y104) -> 4.4013112e+09 | AD10: =SUMIF($C$18:$C104,$F10,AD$18:AD104) -> 0
F11: TOTAL | G11: =SUM(G2:G10) -> 51578000000 | M11: =SUM(M2:M10) -> 5.308874e+09 | N11: =SUM(N2:N10) -> 0 | O11: =SUM(O2:O10) -> 5.308874e+09 | P11: =SUM(P2:P10) -> 0 | Q11: =SUM(Q2:Q10) -> 0 | R11: =SUM(R2:R10) -> 7.3466429e+09 | S11: =SUM(S2:S10) -> 5.308874e+09 | T11: =SUM(T2:T10) -> 1.2655517e+10 | ... Y11: =SUM(Y2:Y10) -> 2.000216e+10
A13: Depreciation schedule
H16: 45657 | M16: 46022 | R16: 46387 | W16: 46752 | AB16: 47118
A17: Date acquired | B17: Amount x Item | C17: Category | D17: Total cost | E17: Useful span | F17: Date of usage | G17: Depreciation method | H17: Useful time (days) | I17: Amnt | J17: Cum A/D | K17: DDM value | L17: Useful day remaining | M17: Useful time (days) | N17: Amnt | O17: Cum A/D | P17: Net Val | Q17: Useful day remaining | R17: # mo | S17: Amnt | T17: Cum A/D | U17: Net Val | V17: Useful day remaining | W17: # mo | X17: Amnt | Y17: Cum A/D | Z17: Net Val | AA17: Useful day remaining | AB17: # mo | AC17: Amnt | AD17: Cum A/D | AE17: Net Val | AF17: Useful day remaining
A19: 45792 | B19: 6 CNC machine | C19: Machinery | D19: =1600000000*3 -> 4800000000 | E19: 15 | F19: 45809 | G19: SLN | H19: =IF(DATEDIF($F19,H$16,"D")+1<#REF!*365, IF(DATEDIF($F19,H$16,"D")+1<0, "Not yet", IF(DATEDIF($F19,H$16,"D")+1<365, DATEDIF($F19,H$16,"D")+1,365)), IF(DATEDIF($M$16,H$16,"D")+DATEDIF(D$16,H$16,"D")-(DATEDIF($F19,H$16,"D")+1)>0, DATEDIF($M$16,H$16,"D")+DATEDIF(D$16,H$16,"D")-(DATEDIF($F19,H$16,"D")+1), "Expired" )) -> #NUM! | L19: =E19*365 -> 5475 | M19: =IFERROR( IF( DATEDIF($F19, M$16, "D") + 1 < 0, "Not yet", IF( DATEDIF($F19,M$16,"D") < DATEDIF(H$16,M$16,"D"), DATEDIF($F19,M$16,"D") + 1, DATEDIF(H$16,M$16,"D") + MIN(0,L19-DATEDIF(H$16,M$16,"D")))),0) -> 214 | N19: =O19-J19 -> 1.8761644e+08 | O19: =IF(NOT(L19=0), IFERROR(_xlfn.SWITCH( $G19, "SLN", SLN($D19,, $E19*365) * ($L19-Q19), "DDB", SUM(DDB($D19,, $E19*365, SEQUENCE(DATEDIF($F20,M$16,"D")+1), IF($E19<=4,1.5,2))), "" ), ""), "--") -> 1.8761644e+08 | Q19: =IFERROR(L19-M19,$L19) -> 5261 | R19: =IFERROR( IF( DATEDIF($F19, R$16, "D") + 1 < 0, "Not yet", IF( DATEDIF($F19,R$16,"D") < DATEDIF(M$16,R$16,"D"), DATEDIF($F19,R$16,"D") + 1, DATEDIF(M$16,R$16,"D") + MIN(0,Q19-DATEDIF(M$16,R$16,"D")))),0) -> 365 | S19: =T19-O19 -> 320000000 | T19: =IF(NOT(Q19=0), IFERROR(_xlfn.SWITCH( $G19, "SLN", SLN($D19,, $E19*365) * ($L19-V19), "DDB", SUM(DDB($D19,, $E19*365, SEQUENCE(DATEDIF($F20,R$16,"D")+1), IF($E19<=4,1.5,2))), "" ), ""), "--") -> 5.0761644e+08 | V19: =Q19-R19 -> 4896 | W19: =IFERROR( IF( DATEDIF($F19, W$16, "D") + 1 < 0, "Not yet", IF( DATEDIF($F19,W$16,"D") < DATEDIF(R$16,W$16,"D"), DATEDIF($F19,W$16,"D") + 1, DATEDIF(R$16,W$16,"D") + MIN(0,V19-DATEDIF(R$16,W$16,"D")))),0) -> 365 | X19: =Y19-T19 -> 3.2e+08 | Y19: =IF(NOT(V19=0), IFERROR(_xlfn.SWITCH( $G19, "SLN", SLN($D19,, $E19*365) * ($L19-AA19), "DDB", SUM(DDB($D19,, $E19*365, SEQUENCE(DATEDIF($F20,W$16,"D")+1), IF($E19<=4,1.5,2))), "" ), ""), "--") -> 8.2761644e+08 | AA19: =V19-W19 -> 4531
A20: 45792 | B20: 3 Laser cutting machine | C20: Machinery | D20: =1200000000*3 -> 3600000000 | E20: 15 | F20: 45809 | G20: SLN | H20: =IF(DATEDIF($F20,H$16,"D")+1<#REF!*365, IF(DATEDIF($F20,H$16,"D")+1<0, "Not yet", IF(DATEDIF($F20,H$16,"D")+1<365, DATEDIF($F20,H$16,"D")+1,365)), IF(DATEDIF($M$16,H$16,"D")+DATEDIF(D$16,H$16,"D")-(DATEDIF($F20,H$16,"D")+1)>0, DATEDIF($M$16,H$16,"D")+DATEDIF(D$16,H$16,"D")-(DATEDIF($F20,H$16,"D")+1), "Expired" )) -> #NUM! | L20: =E20*365 -> 5475 | M20: =IFERROR( IF( DATEDIF($F20, M$16, "D") + 1 < 0, "Not yet", IF( DATEDIF($F20,M$16,"D") < DATEDIF(H$16,M$16,"D"), DATEDIF($F20,M$16,"D") + 1, DATEDIF(H$16,M$16,"D") + MIN(0,L20-DATEDIF(H$16,M$16,"D")))),0) -> 214 | N20: =O20-J20 -> 1.4071233e+08 | O20: =IF(NOT(L20=0), IFERROR(_xlfn.SWITCH( $G20, "SLN", SLN($D20,, $E20*365) * ($L20-Q20), "DDB", SUM(DDB($D20,, $E20*365, SEQUENCE(DATEDIF($F21,M$16,"D")+1), IF($E20<=4,1.5,2))), "" ), ""), "--") -> 1.4071233e+08 | Q20: =IFERROR(L20-M20,$L20) -> 5261 | R20: =IFERROR( IF( DATEDIF($F20, R$16, "D") + 1 < 0, "Not yet", IF( DATEDIF($F20,R$16,"D") < DATEDIF(M$16,R$16,"D"), DATEDIF($F20,R$16,"D") + 1, DATEDIF(M$16,R$16,"D") + MIN(0,Q20-DATEDIF(M$16,R$16,"D")))),0) -> 365 | S20: =T20-O20 -> 240000000 | T20: =IF(NOT(Q20=0), IFERROR(_xlfn.SWITCH( $G20, "SLN", SLN($D20,, $E20*365) * ($L20-V20), "DDB", SUM(DDB($D20,, $E20*365, SEQUENCE(DATEDIF($F21,R$16,"D")+1), IF($E20<=4,1.5,2))), "" ), ""), "--") -> 3.8071233e+08 | V20: =Q20-R20 -> 4896 | W20: =IFERROR( IF( DATEDIF($F20, W$16, "D") + 1 < 0, "Not yet", IF( DATEDIF($F20,W$16,"D") < DATEDIF(R$16,W$16,"D"), DATEDIF($F20,W$16,"D") + 1, DATEDIF(R$16,W$16,"D") + MIN(0,V20-DATEDIF(R$16,W$16,"D")))),0) -> 365 | X20: =Y20-T20 -> 2.4e+08 | Y20: =IF(NOT(V20=0), IFERROR(_xlfn.SWITCH( $G20, "SLN", SLN($D20,, $E20*365) * ($L20-AA20), "DDB", SUM(DDB($D20,, $E20*365, SEQUENCE(DATEDIF($F21,W$16,"D")+1), IF($E20<=4,1.5,2))), "" ), ""), "--") -> 6.2071233e+08 | AA20: =V20-W20 -> 4531
A21: 45792 | B21: 6 Welding robots | C21: Machinery | D21: 6000000000 | E21: 10 | F21: 45809 | G21: SLN | H21: =IF(DATEDIF($F21,H$16,"D")+1<#REF!*365, IF(DATEDIF($F21,H$16,"D")+1<0, "Not yet", IF(DATEDIF($F21,H$16,"D")+1<365, DATEDIF($F21,H$16,"D")+1,365)), IF(DATEDIF($M$16,H$16,"D")+DATEDIF(D$16,H$16,"D")-(DATEDIF($F21,H$16,"D")+1)>0, DATEDIF($M$16,H$16,"D")+DATEDIF(D$16,H$16,"D")-(DATEDIF($F21,H$16,"D")+1), "Expired" )) -> #NUM! | L21: =E21*365 -> 3650 | M21: =IFERROR( IF( DATEDIF($F21, M$16, "D") + 1 < 0, "Not yet", IF( DATEDIF($F21,M$16,"D") < DATEDIF(H$16,M$16,"D"), DATEDIF($F21,M$16,"D") + 1, DATEDIF(H$16,M$16,"D") + MIN(0,L21-DATEDIF(H$16,M$16,"D")))),0) -> 214 | N21: =O21-J21 -> 3.5178082e+08 | O21: =IF(NOT(L21=0), IFERROR(_xlfn.SWITCH( $G21, "SLN", SLN($D21,, $E21*365) * ($L21-Q21), "DDB", SUM(DDB($D21,, $E21*365, SEQUENCE(DATEDIF($F22,M$16,"D")+1), IF($E21<=4,1.5,2))), "" ), ""), "--") -> 3.5178082e+08 | Q21: =IFERROR(L21-M21,$L21) -> 3436 | R21: =IFERROR( IF( DATEDIF($F21, R$16, "D") + 1 < 0, "Not yet", IF( DATEDIF($F21,R$16,"D") < DATEDIF(M$16,R$16,"D"), DATEDIF($F21,R$16,"D") + 1, DATEDIF(M$16,R$16,"D") + MIN(0,Q21-DATEDIF(M$16,R$16,"D")))),0) -> 365 | S21: =T21-O21 -> 600000000 | T21: =IF(NOT(Q21=0), IFERROR(_xlfn.SWITCH( $G21, "SLN", SLN($D21,, $E21*365) * ($L21-V21), "DDB", SUM(DDB($D21,, $E21*365, SEQUENCE(DATEDIF($F22,R$16,"D")+1), IF($E21<=4,1.5,2))), "" ), ""), "--") -> 9.5178082e+08 | V21: =Q21-R21 -> 3071 | W21: =IFERROR( IF( DATEDIF($F21, W$16, "D") + 1 < 0, "Not yet", IF( DATEDIF($F21,W$16,"D") < DATEDIF(R$16,W$16,"D"), DATEDIF($F21,W$16,"D") + 1, DATEDIF(R$16,W$16,"D") + MIN(0,V21-DATEDIF(R$16,W$16,"D")))),0) -> 365 | X21: =Y21-T21 -> 600000000 | Y21: =IF(NOT(V21=0), IFERROR(_xlfn.SWITCH( $G21, "SLN", SLN($D21,, $E21*365) * ($L21-AA21), "DDB", SUM(DDB($D21,, $E21*365, SEQUENCE(DATEDIF($F22,W$16,"D")+1), IF($E21<=4,1.5,2))), "" ), ""), "--") -> 1.5517808e+09 | AA21: =V21-W21 -> 2706
A22: 45792 | B22: 3 Assembly line equipment | C22: Factory Equipment | D22: =2500000000*3 -> 7500000000 | E22: 12 | F22: 45809 | G22: SLN | H22: =IF(DATEDIF($F22,H$16,"D")+1<#REF!*365, IF(DATEDIF($F22,H$16,"D")+1<0, "Not yet", IF(DATEDIF($F22,H$16,"D")+1<365, DATEDIF($F22,H$16,"D")+1,365)), IF(DATEDIF($M$16,H$16,"D")+DATEDIF(D$16,H$16,"D")-(DATEDIF($F22,H$16,"D")+1)>0, DATEDIF($M$16,H$16,"D")+DATEDIF(D$16,H$16,"D")-(DATEDIF($F22,H$16,"D")+1), "Expired" )) -> #NUM! | L22: =E22*365 -> 4380 | M22: =IFERROR( IF( DATEDIF($F22, M$16, "D") + 1 < 0, "Not yet", IF( DATEDIF($F22,M$16,"D") < DATEDIF(H$16,M$16,"D"), DATEDIF($F22,M$16,"D") + 1, DATEDIF(H$16,M$16,"D") + MIN(0,L22-DATEDIF(H$16,M$16,"D")))),0) -> 214 | N22: =O22-J22 -> 3.6643836e+08 | O22: =IF(NOT(L22=0), IFERROR(_xlfn.SWITCH( $G22, "SLN", SLN($D22,, $E22*365) * ($L22-Q22), "DDB", SUM(DDB($D22,, $E22*365, SEQUENCE(DATEDIF($F23,M$16,"D")+1), IF($E22<=4,1.5,2))), "" ), ""), "--") -> 3.6643836e+08 | Q22: =IFERROR(L22-M22,$L22) -> 4166 | R22: =IFERROR( IF( DATEDIF($F22, R$16, "D") + 1 < 0, "Not yet", IF( DATEDIF($F22,R$16,"D") < DATEDIF(M$16,R$16,"D"), DATEDIF($F22,R$16,"D") + 1, DATEDIF(M$16,R$16,"D") + MIN(0,Q22-DATEDIF(M$16,R$16,"D")))),0) -> 365 | S22: =T22-O22 -> 625000000 | T22: =IF(NOT(Q22=0), IFERROR(_xlfn.SWITCH( $G22, "SLN", SLN($D22,, $E22*365) * ($L22-V22), "DDB", SUM(DDB($D22,, $E22*365, SEQUENCE(DATEDIF($F23,R$16,"D")+1), IF($E22<=4,1.5,2))), "" ), ""), "--") -> 9.9143836e+08 | V22: =Q22-R22 -> 3801 | W22: =IFERROR( IF( DATEDIF($F22, W$16, "D") + 1 < 0, "Not yet", IF( DATEDIF($F22,W$16,"D") < DATEDIF(R$16,W$16,"D"), DATEDIF($F22,W$16,"D") + 1, DATEDIF(R$16,W$16,"D") + MIN(0,V22-DATEDIF(R$16,W$16,"D")))),0) -> 365 | X22: =Y22-T22 -> 625000000 | Y22: =IF(NOT(V22=0), IFERROR(_xlfn.SWITCH( $G22, "SLN", SLN($D22,, $E22*365) * ($L22-AA22), "DDB", SUM(DDB($D22,, $E22*365, SEQUENCE(DATEDIF($F23,W$16,"D")+1), IF($E22<=4,1.5,2))), "" ), ""), "--") -> 1.6164384e+09 | AA22: =V22-W22 -> 3436
A23: 45792 | B23: 3 Painting booth | C23: Factory Equipment | D23: =700000000*3 -> 2100000000 | E23: 10 | F23: 45809 | G23: SLN | H23: =IF(DATEDIF($F23,H$16,"D")+1<#REF!*365, IF(DATEDIF($F23,H$16,"D")+1<0, "Not yet", IF(DATEDIF($F23,H$16,"D")+1<365, DATEDIF($F23,H$16,"D")+1,365)), IF(DATEDIF($M$16,H$16,"D")+DATEDIF(D$16,H$16,"D")-(DATEDIF($F23,H$16,"D")+1)>0, DATEDIF($M$16,H$16,"D")+DATEDIF(D$16,H$16,"D")-(DATEDIF($F23,H$16,"D")+1), "Expired" )) -> #NUM! | L23: =E23*365 -> 3650 | M23: =IFERROR( IF( DATEDIF($F23, M$16, "D") + 1 < 0, "Not yet", IF( DATEDIF($F23,M$16,"D") < DATEDIF(H$16,M$16,"D"), DATEDIF($F23,M$16,"D") + 1, DATEDIF(H$16,M$16,"D") + MIN(0,L23-DATEDIF(H$16,M$16,"D")))),0) -> 214 | N23: =O23-J23 -> 1.2312329e+08 | O23: =IF(NOT(L23=0), IFERROR(_xlfn.SWITCH( $G23, "SLN", SLN($D23,, $E23*365) * ($L23-Q23), "DDB", SUM(DDB($D23,, $E23*365, SEQUENCE(DATEDIF($F24,M$16,"D")+1), IF($E23<=4,1.5,2))), "" ), ""), "--") -> 1.2312329e+08 | Q23: =IFERROR(L23-M23,$L23) -> 3436 | R23: =IFERROR( IF( DATEDIF($F23, R$16, "D") + 1 < 0, "Not yet", IF( DATEDIF($F23,R$16,"D") < DATEDIF(M$16,R$16,"D"), DATEDIF($F23,R$16,"D") + 1, DATEDIF(M$16,R$16,"D") + MIN(0,Q23-DATEDIF(M$16,R$16,"D")))),0) -> 365 | S23: =T23-O23 -> 210000000 | T23: =IF(NOT(Q23=0), IFERROR(_xlfn.SWITCH( $G23, "SLN", SLN($D23,, $E23*365) * ($L23-V23), "DDB", SUM(DDB($D23,, $E23*365, SEQUENCE(DATEDIF($F24,R$16,"D")+1), IF($E23<=4,1.5,2))), "" ), ""), "--") -> 3.3312329e+08 | V23: =Q23-R23 -> 3071 | W23: =IFERROR( IF( DATEDIF($F23, W$16, "D") + 1 < 0, "Not yet", IF( DATEDIF($F23,W$16,"D") < DATEDIF(R$16,W$16,"D"), DATEDIF($F23,W$16,"D") + 1, DATEDIF(R$16,W$16,"D") + MIN(0,V23-DATEDIF(R$16,W$16,"D")))),0) -> 365 | X23: =Y23-T23 -> 2.1e+08 | Y23: =IF(NOT(V23=0), IFERROR(_xlfn.SWITCH( $G23, "SLN", SLN($D23,, $E23*365) * ($L23-AA23), "DDB", SUM(DDB($D23,, $E23*365, SEQUENCE(DATEDIF($F24,W$16,"D")+1), IF($E23<=4,1.5,2))), "" ), ""), "--") -> 5.4312329e+08 | AA23: =V23-W23 -> 2706
A24: 45792 | B24: 3 Material handling system | C24: Factory Equipment | D24: =600000000*3 -> 1800000000 | E24: 10 | F24: 45809 | G24: SLN | H24: =IF(DATEDIF($F24,H$16,"D")+1<#REF!*365, IF(DATEDIF($F24,H$16,"D")+1<0, "Not yet", IF(DATEDIF($F24,H$16,"D")+1<365, DATEDIF($F24,H$16,"D")+1,365)), IF(DATEDIF($M$16,H$16,"D")+DATEDIF(D$16,H$16,"D")-(DATEDIF($F24,H$16,"D")+1)>0, DATEDIF($M$16,H$16,"D")+DATEDIF(D$16,H$16,"D")-(DATEDIF($F24,H$16,"D")+1), "Expired" )) -> #NUM! | L24: =E24*365 -> 3650 | M24: =IFERROR( IF( DATEDIF($F24, M$16, "D") + 1 < 0, "Not yet", IF( DATEDIF($F24,M$16,"D") < DATEDIF(H$16,M$16,"D"), DATEDIF($F24,M$16,"D") + 1, DATEDIF(H$16,M$16,"D") + MIN(0,L24-DATEDIF(H$16,M$16,"D")))),0) -> 214 | N24: =O24-J24 -> 1.0553425e+08 | O24: =IF(NOT(L24=0), IFERROR(_xlfn.SWITCH( $G24, "SLN", SLN($D24,, $E24*365) * ($L24-Q24), "DDB", SUM(DDB($D24,, $E24*365, SEQUENCE(DATEDIF($F25,M$16,"D")+1), IF($E24<=4,1.5,2))), "" ), ""), "--") -> 1.0553425e+08 | Q24: =IFERROR(L24-M24,$L24) -> 3436 | R24: =IFERROR( IF( DATEDIF($F24, R$16, "D") + 1 < 0, "Not yet", IF( DATEDIF($F24,R$16,"D") < DATEDIF(M$16,R$16,"D"), DATEDIF($F24,R$16,"D") + 1, DATEDIF(M$16,R$16,"D") + MIN(0,Q24-DATEDIF(M$16,R$16,"D")))),0) -> 365 | S24: =T24-O24 -> 180000000 | T24: =IF(NOT(Q24=0), IFERROR(_xlfn.SWITCH( $G24, "SLN", SLN($D24,, $E24*365) * ($L24-V24), "DDB", SUM(DDB($D24,, $E24*365, SEQUENCE(DATEDIF($F25,R$16,"D")+1), IF($E24<=4,1.5,2))), "" ), ""), "--") -> 2.8553425e+08 | V24: =Q24-R24 -> 3071 | W24: =IFERROR( IF( DATEDIF($F24, W$16, "D") + 1 < 0, "Not yet", IF( DATEDIF($F24,W$16,"D") < DATEDIF(R$16,W$16,"D"), DATEDIF($F24,W$16,"D") + 1, DATEDIF(R$16,W$16,"D") + MIN(0,V24-DATEDIF(R$16,W$16,"D")))),0) -> 365 | X24: =Y24-T24 -> 180000000 | Y24: =IF(NOT(V24=0), IFERROR(_xlfn.SWITCH( $G24, "SLN", SLN($D24,, $E24*365) * ($L24-AA24), "DDB", SUM(DDB($D24,, $E24*365, SEQUENCE(DATEDIF($F25,W$16,"D")+1), IF($E24<=4,1.5,2))), "" ), ""), "--") -> 4.6553425e+08 | AA24: =V24-W24 -> 2706
A25: 45708 | B25: 22 Office computers | C25: Computer Hardware | D25: 440000000 | E25: 5 | F25: 45731 | G25: SLN | H25: =IF(DATEDIF($F25,H$16,"D")+1<#REF!*365, IF(DATEDIF($F25,H$16,"D")+1<0, "Not yet", IF(DATEDIF($F25,H$16,"D")+1<365, DATEDIF($F25,H$16,"D")+1,365)), IF(DATEDIF($M$16,H$16,"D")+DATEDIF(D$16,H$16,"D")-(DATEDIF($F25,H$16,"D")+1)>0, DATEDIF($M$16,H$16,"D")+DATEDIF(D$16,H$16,"D")-(DATEDIF($F25,H$16,"D")+1), "Expired" )) -> #NUM! | L25: =E25*365 -> 1825 | M25: =IFERROR( IF( DATEDIF($F25, M$16, "D") + 1 < 0, "Not yet", IF( DATEDIF($F25,M$16,"D") < DATEDIF(H$16,M$16,"D"), DATEDIF($F25,M$16,"D") + 1, DATEDIF(H$16,M$16,"D") + MIN(0,L25-DATEDIF(H$16,M$16,"D")))),0) -> 292 | N25: =O25-J25 -> 70400000 | O25: =IF(NOT(L25=0), IFERROR(_xlfn.SWITCH( $G25, "SLN", SLN($D25,, $E25*365) * ($L25-Q25), "DDB", SUM(DDB($D25,, $E25*365, SEQUENCE(DATEDIF($F26,M$16,"D")+1), IF($E25<=4,1.5,2))), "" ), ""), "--") -> 70400000 | Q25: =IFERROR(L25-M25,$L25) -> 1533 | R25: =IFERROR( IF( DATEDIF($F25, R$16, "D") + 1 < 0, "Not yet", IF( DATEDIF($F25,R$16,"D") < DATEDIF(M$16,R$16,"D"), DATEDIF($F25,R$16,"D") + 1, DATEDIF(M$16,R$16,"D") + MIN(0,Q25-DATEDIF(M$16,R$16,"D")))),0) -> 365 | S25: =T25-O25 -> 88000000 | T25: =IF(NOT(Q25=0), IFERROR(_xlfn.SWITCH( $G25, "SLN", SLN($D25,, $E25*365) * ($L25-V25), "DDB", SUM(DDB($D25,, $E25*365, SEQUENCE(DATEDIF($F26,R$16,"D")+1), IF($E25<=4,1.5,2))), "" ), ""), "--") -> 158400000 | V25: =Q25-R25 -> 1168 | W25: =IFERROR( IF( DATEDIF($F25, W$16, "D") + 1 < 0, "Not yet", IF( DATEDIF($F25,W$16,"D") < DATEDIF(R$16,W$16,"D"), DATEDIF($F25,W$16,"D") + 1, DATEDIF(R$16,W$16,"D") + MIN(0,V25-DATEDIF(R$16,W$16,"D")))),0) -> 365 | X25: =Y25-T25 -> 88000000 | Y25: =IF(NOT(V25=0), IFERROR(_xlfn.SWITCH( $G25, "SLN", SLN($D25,, $E25*365) * ($L25-AA25), "DDB", SUM(DDB($D25,, $E25*365, SEQUENCE(DATEDIF($F26,W$16,"D")+1), IF($E25<=4,1.5,2))), "" ), ""), "--") -> 246400000 | AA25: =V25-W25 -> 803
A26: 45716 | B26: 3 Design software | C26: Computer Software | D26: 60000000 | E26: 3 | F26: 45731 | G26: SLN | H26: =IF(DATEDIF($F26,H$16,"D")+1<#REF!*365, IF(DATEDIF($F26,H$16,"D")+1<0, "Not yet", IF(DATEDIF($F26,H$16,"D")+1<365, DATEDIF($F26,H$16,"D")+1,365)), IF(DATEDIF($M$16,H$16,"D")+DATEDIF(D$16,H$16,"D")-(DATEDIF($F26,H$16,"D")+1)>0, DATEDIF($M$16,H$16,"D")+DATEDIF(D$16,H$16,"D")-(DATEDIF($F26,H$16,"D")+1), "Expired" )) -> #NUM! | L26: =E26*365 -> 1095 | M26: =IFERROR( IF( DATEDIF($F26, M$16, "D") + 1 < 0, "Not yet", IF( DATEDIF($F26,M$16,"D") < DATEDIF(H$16,M$16,"D"), DATEDIF($F26,M$16,"D") + 1, DATEDIF(H$16,M$16,"D") + MIN(0,L26-DATEDIF(H$16,M$16,"D")))),0) -> 292 | N26: =O26-J26 -> 16000000 | O26: =IF(NOT(L26=0), IFERROR(_xlfn.SWITCH( $G26, "SLN", SLN($D26,, $E26*365) * ($L26-Q26), "DDB", SUM(DDB($D26,, $E26*365, SEQUENCE(DATEDIF($F27,M$16,"D")+1), IF($E26<=4,1.5,2))), "" ), ""), "--") -> 16000000 | Q26: =IFERROR(L26-M26,$L26) -> 803 | R26: =IFERROR( IF( DATEDIF($F26, R$16, "D") + 1 < 0, "Not yet", IF( DATEDIF($F26,R$16,"D") < DATEDIF(M$16,R$16,"D"), DATEDIF($F26,R$16,"D") + 1, DATEDIF(M$16,R$16,"D") + MIN(0,Q26-DATEDIF(M$16,R$16,"D")))),0) -> 365 | S26: =T26-O26 -> 20000000 | T26: =IF(NOT(Q26=0), IFERROR(_xlfn.SWITCH( $G26, "SLN", SLN($D26,, $E26*365) * ($L26-V26), "DDB", SUM(DDB($D26,, $E26*365, SEQUENCE(DATEDIF($F27,R$16,"D")+1), IF($E26<=4,1.5,2))), "" ), ""), "--") -> 36000000 | V26: =Q26-R26 -> 438 | W26: =IFERROR( IF( DATEDIF($F26, W$16, "D") + 1 < 0, "Not yet", IF( DATEDIF($F26,W$16,"D") < DATEDIF(R$16,W$16,"D"), DATEDIF($F26,W$16,"D") + 1, DATEDIF(R$16,W$16,"D") + MIN(0,V26-DATEDIF(R$16,W$16,"D")))),0) -> 365 | X26: =Y26-T26 -> 20000000 | Y26: =IF(NOT(V26=0), IFERROR(_xlfn.SWITCH( $G26, "SLN", SLN($D26,, $E26*365) * ($L26-AA26), "DDB", SUM(DDB($D26,, $E26*365, SEQUENCE(DATEDIF($F27,W$16,"D")+1), IF($E26<=4,1.5,2))), "" ), ""), "--") -> 56000000 | AA26: =V26-W26 -> 73
A27: 45708 | B27: 40 Desks & Chairs | C27: Furnitures & Fixtures | D27: 200000000 | E27: 5 | F27: 45726 | G27: SLN | H27: =IF(DATEDIF($F27,H$16,"D")+1<#REF!*365, IF(DATEDIF($F27,H$16,"D")+1<0, "Not yet", IF(DATEDIF($F27,H$16,"D")+1<365, DATEDIF($F27,H$16,"D")+1,365)), IF(DATEDIF($M$16,H$16,"D")+DATEDIF(D$16,H$16,"D")-(DATEDIF($F27,H$16,"D")+1)>0, DATEDIF($M$16,H$16,"D")+DATEDIF(D$16,H$16,"D")-(DATEDIF($F27,H$16,"D")+1), "Expired" )) -> #NUM! | L27: =E27*365 -> 1825 | M27: =IFERROR( IF( DATEDIF($F27, M$16, "D") + 1 < 0, "Not yet", IF( DATEDIF($F27,M$16,"D") < DATEDIF(H$16,M$16,"D"), DATEDIF($F27,M$16,"D") + 1, DATEDIF(H$16,M$16,"D") + MIN(0,L27-DATEDIF(H$16,M$16,"D")))),0) -> 297 | N27: =O27-J27 -> 32547945 | O27: =IF(NOT(L27=0), IFERROR(_xlfn.SWITCH( $G27, "SLN", SLN($D27,, $E27*365) * ($L27-Q27), "DDB", SUM(DDB($D27,, $E27*365, SEQUENCE(DATEDIF($F28,M$16,"D")+1), IF($E27<=4,1.5,2))), "" ), ""), "--") -> 32547945 | Q27: =IFERROR(L27-M27,$L27) -> 1528 | R27: =IFERROR( IF( DATEDIF($F27, R$16, "D") + 1 < 0, "Not yet", IF( DATEDIF($F27,R$16,"D") < DATEDIF(M$16,R$16,"D"), DATEDIF($F27,R$16,"D") + 1, DATEDIF(M$16,R$16,"D") + MIN(0,Q27-DATEDIF(M$16,R$16,"D")))),0) -> 365 | S27: =T27-O27 -> 40000000 | T27: =IF(NOT(Q27=0), IFERROR(_xlfn.SWITCH( $G27, "SLN", SLN($D27,, $E27*365) * ($L27-V27), "DDB", SUM(DDB($D27,, $E27*365, SEQUENCE(DATEDIF($F28,R$16,"D")+1), IF($E27<=4,1.5,2))), "" ), ""), "--") -> 72547945 | V27: =Q27-R27 -> 1163 | W27: =IFERROR( IF( DATEDIF($F27, W$16, "D") + 1 < 0, "Not yet", IF( DATEDIF($F27,W$16,"D") < DATEDIF(R$16,W$16,"D"), DATEDIF($F27,W$16,"D") + 1, DATEDIF(R$16,W$16,"D") + MIN(0,V27-DATEDIF(R$16,W$16,"D")))),0) -> 365 | X27: =Y27-T27 -> 40000000 | Y27: =IF(NOT(V27=0), IFERROR(_xlfn.SWITCH( $G27, "SLN", SLN($D27,, $E27*365) * ($L27-AA27), "DDB", SUM(DDB($D27,, $E27*365, SEQUENCE(DATEDIF($F28,W$16,"D")+1), IF($E27<=4,1.5,2))), "" ), ""), "--") -> 1.1254795e+08 | AA27: =V27-W27 -> 798
A28: 45708 | B28: 10 Filling cabinets | C28: Furnitures & Fixtures | D28: 30000000 | E28: 7 | F28: 45809 | G28: SLN | H28: =IF(DATEDIF($F28,H$16,"D")+1<#REF!*365, IF(DATEDIF($F28,H$16,"D")+1<0, "Not yet", IF(DATEDIF($F28,H$16,"D")+1<365, DATEDIF($F28,H$16,"D")+1,365)), IF(DATEDIF($M$16,H$16,"D")+DATEDIF(D$16,H$16,"D")-(DATEDIF($F28,H$16,"D")+1)>0, DATEDIF($M$16,H$16,"D")+DATEDIF(D$16,H$16,"D")-(DATEDIF($F28,H$16,"D")+1), "Expired" )) -> #NUM! | L28: =E28*365 -> 2555 | M28: =IFERROR( IF( DATEDIF($F28, M$16, "D") + 1 < 0, "Not yet", IF( DATEDIF($F28,M$16,"D") < DATEDIF(H$16,M$16,"D"), DATEDIF($F28,M$16,"D") + 1, DATEDIF(H$16,M$16,"D") + MIN(0,L28-DATEDIF(H$16,M$16,"D")))),0) -> 214 | N28: =O28-J28 -> 2512720.2 | O28: =IF(NOT(L28=0), IFERROR(_xlfn.SWITCH( $G28, "SLN", SLN($D28,, $E28*365) * ($L28-Q28), "DDB", SUM(DDB($D28,, $E28*365, SEQUENCE(DATEDIF($F29,M$16,"D")+1), IF($E28<=4,1.5,2))), "" ), ""), "--") -> 2512720.2 | Q28: =IFERROR(L28-M28,$L28) -> 2341 | R28: =IFERROR( IF( DATEDIF($F28, R$16, "D") + 1 < 0, "Not yet", IF( DATEDIF($F28,R$16,"D") < DATEDIF(M$16,R$16,"D"), DATEDIF($F28,R$16,"D") + 1, DATEDIF(M$16,R$16,"D") + MIN(0,Q28-DATEDIF(M$16,R$16,"D")))),0) -> 365 | S28: =T28-O28 -> 4285714.3 | T28: =IF(NOT(Q28=0), IFERROR(_xlfn.SWITCH( $G28, "SLN", SLN($D28,, $E28*365) * ($L28-V28), "DDB", SUM(DDB($D28,, $E28*365, SEQUENCE(DATEDIF($F29,R$16,"D")+1), IF($E28<=4,1.5,2))), "" ), ""), "--") -> 6798434.4 | V28: =Q28-R28 -> 1976 | W28: =IFERROR( IF( DATEDIF($F28, W$16, "D") + 1 < 0, "Not yet", IF( DATEDIF($F28,W$16,"D") < DATEDIF(R$16,W$16,"D"), DATEDIF($F28,W$16,"D") + 1, DATEDIF(R$16,W$16,"D") + MIN(0,V28-DATEDIF(R$16,W$16,"D")))),0) -> 365 | X28: =Y28-T28 -> 4285714.3 | Y28: =IF(NOT(V28=0), IFERROR(_xlfn.SWITCH( $G28, "SLN", SLN($D28,, $E28*365) * ($L28-AA28), "DDB", SUM(DDB($D28,, $E28*365, SEQUENCE(DATEDIF($F29,W$16,"D")+1), IF($E28<=4,1.5,2))), "" ), ""), "--") -> 11084149 | AA28: =V28-W28 -> 1611
A29: 45708 | B29: Air conditioning system | C29: Furnitures & Fixtures | D29: 850000000 | E29: 10 | F29: 45809 | G29: SLN | H29: =IF(DATEDIF($F29,H$16,"D")+1<#REF!*365, IF(DATEDIF($F29,H$16,"D")+1<0, "Not yet", IF(DATEDIF($F29,H$16,"D")+1<365, DATEDIF($F29,H$16,"D")+1,365)), IF(DATEDIF($M$16,H$16,"D")+DATEDIF(D$16,H$16,"D")-(DATEDIF($F29,H$16,"D")+1)>0, DATEDIF($M$16,H$16,"D")+DATEDIF(D$16,H$16,"D")-(DATEDIF($F29,H$16,"D")+1), "Expired" )) -> #NUM! | L29: =E29*365 -> 3650 | M29: =IFERROR( IF( DATEDIF($F29, M$16, "D") + 1 < 0, "Not yet", IF( DATEDIF($F29,M$16,"D") < DATEDIF(H$16,M$16,"D"), DATEDIF($F29,M$16,"D") + 1, DATEDIF(H$16,M$16,"D") + MIN(0,L29-DATEDIF(H$16,M$16,"D")))),0) -> 214 | N29: =O29-J29 -> 49835616 | O29: =IF(NOT(L29=0), IFERROR(_xlfn.SWITCH( $G29, "SLN", SLN($D29,, $E29*365) * ($L29-Q29), "DDB", SUM(DDB($D29,, $E29*365, SEQUENCE(DATEDIF($F30,M$16,"D")+1), IF($E29<=4,1.5,2))), "" ), ""), "--") -> 49835616 | Q29: =IFERROR(L29-M29,$L29) -> 3436 | R29: =IFERROR( IF( DATEDIF($F29, R$16, "D") + 1 < 0, "Not yet", IF( DATEDIF($F29,R$16,"D") < DATEDIF(M$16,R$16,"D"), DATEDIF($F29,R$16,"D") + 1, DATEDIF(M$16,R$16,"D") + MIN(0,Q29-DATEDIF(M$16,R$16,"D")))),0) -> 365 | S29: =T29-O29 -> 85000000 | T29: =IF(NOT(Q29=0), IFERROR(_xlfn.SWITCH( $G29, "SLN", SLN($D29,, $E29*365) * ($L29-V29), "DDB", SUM(DDB($D29,, $E29*365, SEQUENCE(DATEDIF($F30,R$16,"D")+1), IF($E29<=4,1.5,2))), "" ), ""), "--") -> 1.3483562e+08 | V29: =Q29-R29 -> 3071 | W29: =IFERROR( IF( DATEDIF($F29, W$16, "D") + 1 < 0, "Not yet", IF( DATEDIF($F29,W$16,"D") < DATEDIF(R$16,W$16,"D"), DATEDIF($F29,W$16,"D") + 1, DATEDIF(R$16,W$16,"D") + MIN(0,V29-DATEDIF(R$16,W$16,"D")))),0) -> 365 | X29: =Y29-T29 -> 85000000 | Y29: =IF(NOT(V29=0), IFERROR(_xlfn.SWITCH( $G29, "SLN", SLN($D29,, $E29*365) * ($L29-AA29), "DDB", SUM(DDB($D29,, $E29*365, SEQUENCE(DATEDIF($F30,W$16,"D")+1), IF($E29<=4,1.5,2))), "" ), ""), "--") -> 2.1983562e+08 | AA29: =V29-W29 -> 2706
A30: 45802 | B30: 12 Delivery vans | C30: Vehicles | D30: =2000000000*3 -> 6000000000 | E30: 8 | F30: 45818 | G30: SLN | H30: =IF(DATEDIF($F30,H$16,"D")+1<#REF!*365, IF(DATEDIF($F30,H$16,"D")+1<0, "Not yet", IF(DATEDIF($F30,H$16,"D")+1<365, DATEDIF($F30,H$16,"D")+1,365)), IF(DATEDIF($M$16,H$16,"D")+DATEDIF(D$16,H$16,"D")-(DATEDIF($F30,H$16,"D")+1)>0, DATEDIF($M$16,H$16,"D")+DATEDIF(D$16,H$16,"D")-(DATEDIF($F30,H$16,"D")+1), "Expired" )) -> #NUM! | L30: =E30*365 -> 2920 | M30: =IFERROR( IF( DATEDIF($F30, M$16, "D") + 1 < 0, "Not yet", IF( DATEDIF($F30,M$16,"D") < DATEDIF(H$16,M$16,"D"), DATEDIF($F30,M$16,"D") + 1, DATEDIF(H$16,M$16,"D") + MIN(0,L30-DATEDIF(H$16,M$16,"D")))),0) -> 205 | N30: =O30-J30 -> 4.2123288e+08 | O30: =IF(NOT(L30=0), IFERROR(_xlfn.SWITCH( $G30, "SLN", SLN($D30,, $E30*365) * ($L30-Q30), "DDB", SUM(DDB($D30,, $E30*365, SEQUENCE(DATEDIF($F31,M$16,"D")+1), IF($E30<=4,1.5,2))), "" ), ""), "--") -> 4.2123288e+08 | Q30: =IFERROR(L30-M30,$L30) -> 2715 | R30: =IFERROR( IF( DATEDIF($F30, R$16, "D") + 1 < 0, "Not yet", IF( DATEDIF($F30,R$16,"D") < DATEDIF(M$16,R$16,"D"), DATEDIF($F30,R$16,"D") + 1, DATEDIF(M$16,R$16,"D") + MIN(0,Q30-DATEDIF(M$16,R$16,"D")))),0) -> 365 | S30: =T30-O30 -> 7.5e+08 | T30: =IF(NOT(Q30=0), IFERROR(_xlfn.SWITCH( $G30, "SLN", SLN($D30,, $E30*365) * ($L30-V30), "DDB", SUM(DDB($D30,, $E30*365, SEQUENCE(DATEDIF($F31,R$16,"D")+1), IF($E30<=4,1.5,2))), "" ), ""), "--") -> 1.1712329e+09 | V30: =Q30-R30 -> 2350 | W30: =IFERROR( IF( DATEDIF($F30, W$16, "D") + 1 < 0, "Not yet", IF( DATEDIF($F30,W$16,"D") < DATEDIF(R$16,W$16,"D"), DATEDIF($F30,W$16,"D") + 1, DATEDIF(R$16,W$16,"D") + MIN(0,V30-DATEDIF(R$16,W$16,"D")))),0) -> 365 | X30: =Y30-T30 -> 750000000 | Y30: =IF(NOT(V30=0), IFERROR(_xlfn.SWITCH( $G30, "SLN", SLN($D30,, $E30*365) * ($L30-AA30), "DDB", SUM(DDB($D30,, $E30*365, SEQUENCE(DATEDIF($F31,W$16,"D")+1), IF($E30<=4,1.5,2))), "" ), ""), "--") -> 1.9212329e+09 | AA30: =V30-W30 -> 1985
A31: 45713 | B31: 6 Company cars | C31: Vehicles | D31: =2100000000*3 -> 6300000000 | E31: 8 | F31: 45809 | G31: SLN | H31: =IF(DATEDIF($F31,H$16,"D")+1<#REF!*365, IF(DATEDIF($F31,H$16,"D")+1<0, "Not yet", IF(DATEDIF($F31,H$16,"D")+1<365, DATEDIF($F31,H$16,"D")+1,365)), IF(DATEDIF($M$16,H$16,"D")+DATEDIF(D$16,H$16,"D")-(DATEDIF($F31,H$16,"D")+1)>0, DATEDIF($M$16,H$16,"D")+DATEDIF(D$16,H$16,"D")-(DATEDIF($F31,H$16,"D")+1), "Expired" )) -> #NUM! | L31: =E31*365 -> 2920 | M31: =IFERROR( IF( DATEDIF($F31, M$16, "D") + 1 < 0, "Not yet", IF( DATEDIF($F31,M$16,"D") < DATEDIF(H$16,M$16,"D"), DATEDIF($F31,M$16,"D") + 1, DATEDIF(H$16,M$16,"D") + MIN(0,L31-DATEDIF(H$16,M$16,"D")))),0) -> 214 | N31: =O31-J31 -> 4.6171233e+08 | O31: =IF(NOT(L31=0), IFERROR(_xlfn.SWITCH( $G31, "SLN", SLN($D31,, $E31*365) * ($L31-Q31), "DDB", SUM(DDB($D31,, $E31*365, SEQUENCE(DATEDIF($F32,M$16,"D")+1), IF($E31<=4,1.5,2))), "" ), ""), "--") -> 4.6171233e+08 | Q31: =IFERROR(L31-M31,$L31) -> 2706 | R31: =IFERROR( IF( DATEDIF($F31, R$16, "D") + 1 < 0, "Not yet", IF( DATEDIF($F31,R$16,"D") < DATEDIF(M$16,R$16,"D"), DATEDIF($F31,R$16,"D") + 1, DATEDIF(M$16,R$16,"D") + MIN(0,Q31-DATEDIF(M$16,R$16,"D")))),0) -> 365 | S31: =T31-O31 -> 787500000 | T31: =IF(NOT(Q31=0), IFERROR(_xlfn.SWITCH( $G31, "SLN", SLN($D31,, $E31*365) * ($L31-V31), "DDB", SUM(DDB($D31,, $E31*365, SEQUENCE(DATEDIF($F32,R$16,"D")+1), IF($E31<=4,1.5,2))), "" ), ""), "--") -> 1.2492123e+09 | V31: =Q31-R31 -> 2341 | W31: =IFERROR( IF( DATEDIF($F31, W$16, "D") + 1 < 0, "Not yet", IF( DATEDIF($F31,W$16,"D") < DATEDIF(R$16,W$16,"D"), DATEDIF($F31,W$16,"D") + 1, DATEDIF(R$16,W$16,"D") + MIN(0,V31-DATEDIF(R$16,W$16,"D")))),0) -> 365 | X31: =Y31-T31 -> 787500000 | Y31: =IF(NOT(V31=0), IFERROR(_xlfn.SWITCH( $G31, "SLN", SLN($D31,, $E31*365) * ($L31-AA31), "DDB", SUM(DDB($D31,, $E31*365, SEQUENCE(DATEDIF($F32,W$16,"D")+1), IF($E31<=4,1.5,2))), "" ), ""), "--") -> 2.0367123e+09 | AA31: =V31-W31 -> 1976
